Workbook

Sheet Indicator Master
A1: Credit Monitoring — Indicator Master
A3: UID | B3: Module | C3: Indicator | D3: Description | E3: Category | F3: Critical (Yes/No) | G3: What to Track (Input) | H3: Data Source Channel | I3: Acquisition Mechanism | J3: Data Type | K3: Update Frequency | L3: Functional Calculation Formula | M3: Threshold & Score | N3: Max Score
A4: CM-001 | B4: Credit Monitoring | C4: DPD (days past due) | D4: Delay in interest payment | E4: Account Conduct | F4: No | G4: EMI / interest overdue by 1-30 days | H4: Bank Core System (CBS) | I4: Direct CBS extract | J4: Quantitative | K4: Daily | L4: MAX days past due across facilities as of run date | M4: 0 days = 0 | 1-30 DPD = 10 | 31-60 DPD = 20 | 61-90 DPD = 30 | 90+ DPD = 40 | N4: 40
A5: CM-002 | B5: Credit Monitoring | C5: Excess over DP/limit % | D5: Overdrawing beyond sanctioned limit | E5: Account Conduct | F5: No | G5: Drawing power breach or limit excess | H5: Bank Core System (CBS) | I5: Direct CBS extract | J5: Quantitative | K5: Daily | L5: Excess% = (Outstanding - DrawingPower)/DrawingPower | M5: No breach = 0 | Up to 5% breach = 10 | 5-10% = 20 | >10% or repeated = 30 | N5: 30
A6: CM-003 | B6: Credit Monitoring | C6: GST turnover change % / vs bank credits | D6: Decline in GST turnover | E6: Financial Performance | F6: No | G6: GST sales lower than projected or lower than bank statement credits | H6: External API | I6: GST portal / GSTN API (with consent) | J6: Quantitative | K6: Monthly | L6: GSTChange% vs prior period; and GST vs bank credits | M6: Stable/increasing = 0 | 10-20% decline = 10 | 20-40% decline = 20 | >40% decline = 35 | N6: 35
A7: CM-004 | B7: Credit Monitoring | C7: Cash Flow from Operations (sign / periods) | D7: Negative cash flow from operations | E7: Financial Performance | F7: No | G7: CFO negative for repeated periods | H7: Bank-provided Financial Statements | I7: Audited financials / CMA | J7: Quantitative | K7: Quarterly | L7: Sign(CFO) & count of consecutive negative periods | M7: Positive CFO = 0 | 1 negative period = 15 | 2 consecutive periods = 30 | ≥3 consecutive period or severe negative = 40 | N7: 40
A8: CM-005 | B8: Credit Monitoring | C8: Current Ratio | D8: Weak current ratio | E8: Financial Performance | F8: No | G8: Current assets lower compared to current liabilities | H8: Bank-provided Financial Statements | I8: Audited financials / CMA | J8: Quantitative | K8: Quarterly | L8: Compute Current Ratio then compare to threshold bands | M8: >=1.33 = 0 | 1.10-1.32 = 10 | 1.00-1.09 = 20 | <1.00 = 35 | N8: 35
A9: CM-006 | B9: Credit Monitoring | C9: Audit opinion classification | D9: Adverse audit remarks | E9: Audit | F9: No | G9: Qualified audit opinion or going concern issue | H9: External + Internal Docs | I9: Audited financials and Ministry of Corporate Affairs (MCA) filings | J9: Qualitative | K9: Annual | L9: Classify event severity for 'Adverse audit remarks' (no numeric calc) | M9: No issue = 0 | delayed/minor qualification = 10 | material qualification/change = 25 | going concern/adverse = 40 | N9: 40
A10: CM-007 | B10: Credit Monitoring | C10: NCLT/IBC admission status | D10: NCLT/IBC proceedings | E10: Insolvency | F10: No | G10: Insolvency filing against borrower or group | H10: External (Legal DB) | I10: Court/NCLT DB or paid aggregator | J10: Qualitative | K10: Event | L10: NCLT/IBC admission = TRUE/FALSE | M10: No case = 0 | civil/regulatory notice = 15 | multiple/material cases = 30 | IBC/NCLT = 50 | N10: 50
A11: CM-008 | B11: Credit Monitoring | C11: Restructuring request status | D11: Frequent restructuring requests | E11: Credit Risk | F11: No | G11: Moratorium, repayment extension, lower interest request | H11: External + Internal Docs | I11: Map in data discovery | J11: Qualitative | K11: Event | L11: Check restructuring request status | M11: No request = 0 | informal request = 15 | formal restructuring = 30 | repeated = 40 | N11: 40
A12: CM-009 | B12: Credit Monitoring | C12: Security/collateral cover ratio | D12: Reduction in security cover | E12: Collateral Risk | F12: No | G12: Collateral value falling | H12: Internal Tracker | I12: Collateral register + valuer | J12: Quantitative | K12: Quarterly | L12: Compute Security/collateral cover ratio then compare to threshold bands | M12: ≥1.25 (adequate) = 0 | 1.10–1.25 (minor shortfall) = 15 | 1.00–1.10 (major shortfall) = 30 | <1.00 (under-secured) = 40 | N12: 40
A13: CM-010 | B13: Credit Monitoring | C13: Insurance validity / days to expiry | D13: Insurance policy expiry | E13: Collateral Risk | F13: No | G13: Stock/property/machinery insurance not renewed | H13: Internal Tracker | I13: Collateral/insurance register + valuer | J13: Qualitative | K13: Event | L13: DaysToExpiry(insurance); lapsed = TRUE/FALSE | M13: Adequate/current = 0 | minor shortfall/lapse = 15 | major shortfall/lapse = 30 | uninsured/under-secured = 40 | N13: 40
A14: CM-011 | B14: Credit Monitoring | C14: Top-customer revenue concentration % | D14: Concentration of customers | E14: Business Risk | F14: No | G14: High sales from one or few customers | H14: Bank Core System (CBS) + Financials Statement | I14: Map in data discovery | J14: Quantitative | K14: Annual | L14: Compute Top-customer revenue concentration % then compare to threshold bands | M14: <25% exposure = 0 | 25-40% = 10 | 40-60% = 20 | >60% = 30 | N14: 30
A15: CM-012 | B15: Credit Monitoring | C15: Top-supplier purchase concentration % | D15: Concentration of suppliers | E15: Business Risk | F15: No | G15: Dependence on few suppliers | H15: Bank Core System (CBS) + Financials Statement | I15: Map in data discovery | J15: Quantitative | K15: Annual | L15: Compute Top-supplier purchase concentration % then compare to threshold bands | M15: <25% exposure = 0 | 25-40% = 10 | 40-60% = 20 | >60% = 30 | N15: 30
... A24: CM-021 | B24: Credit Monitoring | C24: Count of overdue events (rolling 3-6m) | D24: Frequent overdues | E24: Account Conduct | F24: No | G24: Number of times borrower delays payment in last 3-6 months | H24: Bank Core System (CBS) | I24: Direct CBS extract | J24: Quantitative | K24: Daily | L24: COUNT(overdue events) in rolling 3-6 months | M24: 0 instances = 0 | 1 instance = 5 | 2 instances = 15 | 3+ instances = 25 | N24: 25

Sheet Functional Logic
A1: Functional Logic (per indicator)
A2: Input → Calculation/Classification → Threshold Evaluation → Raw Score → Normalised Score. Max Score links to the Master.
A4: UID | B4: Indicator | C4: Module | D4: Step 1 — Input (What to Track) | E4: Step 2 — Calculation / Classification | F4: Step 3 — Threshold Evaluation (bands) | G4: Max Score | H4: Step 4 — Raw Score rule | I4: Step 5 — Normalised Score
A5: CM-001 | B5: DPD (days past due) | C5: Credit Monitoring | D5: EMI / interest overdue by 1-30 days | E5: MAX days past due across facilities as of run date | F5: 0 days = 0 | 1-30 DPD = 10 | 31-60 DPD = 20 | 61-90 DPD = 30 | 90+ DPD = 40 | G5: =INDEX('Indicator Master'!$N$4:$N$24,MATCH($A5,'Indicator Master'!$A$4:$A$24,0)) -> 40 | H5: Raw Score = score of the single band whose condition the borrower value satisfies; 0 if none is breached. | I5: Normalised = Raw ÷ Max Score × 100 (0–100). Fed into the Overall Score Engine.
A6: CM-002 | B6: Excess over DP/limit % | C6: Credit Monitoring | D6: Drawing power breach or limit excess | E6: Excess% = (Outstanding - DrawingPower)/DrawingPower | F6: No breach = 0 | Up to 5% breach = 10 | 5-10% = 20 | >10% or repeated = 30 | G6: =INDEX('Indicator Master'!$N$4:$N$24,MATCH($A6,'Indicator Master'!$A$4:$A$24,0)) -> 30 | H6: Raw Score = score of the single band whose condition the borrower value satisfies; 0 if none is breached. | I6: Normalised = Raw ÷ Max Score × 100 (0–100). Fed into the Overall Score Engine.
A7: CM-003 | B7: GST turnover change % / vs bank credits | C7: Credit Monitoring | D7: GST sales lower than projected or lower than bank statement credits | E7: GSTChange% vs prior period; and GST vs bank credits | F7: Stable/increasing = 0 | 10-20% decline = 10 | 20-40% decline = 20 | >40% decline = 35 | G7: =INDEX('Indicator Master'!$N$4:$N$24,MATCH($A7,'Indicator Master'!$A$4:$A$24,0)) -> 35 | H7: Raw Score = score of the single band whose condition the borrower value satisfies; 0 if none is breached. | I7: Normalised = Raw ÷ Max Score × 100 (0–100). Fed into the Overall Score Engine.
A8: CM-004 | B8: Cash Flow from Operations (sign / periods) | C8: Credit Monitoring | D8: CFO negative for repeated periods | E8: Sign(CFO) & count of consecutive negative periods | F8: Positive CFO = 0 | 1 negative period = 15 | 2 consecutive periods = 30 | ≥3 consecutive period or severe negative = 40 | G8: =INDEX('Indicator Master'!$N$4:$N$24,MATCH($A8,'Indicator Master'!$A$4:$A$24,0)) -> 40 | H8: Raw Score = score of the single band whose condition the borrower value satisfies; 0 if none is breached. | I8: Normalised = Raw ÷ Max Score × 100 (0–100). Fed into the Overall Score Engine.
A9: CM-005 | B9: Current Ratio | C9: Credit Monitoring | D9: Current assets lower compared to current liabilities | E9: Compute Current Ratio then compare to threshold bands | F9: >=1.33 = 0 | 1.10-1.32 = 10 | 1.00-1.09 = 20 | <1.00 = 35 | G9: =INDEX('Indicator Master'!$N$4:$N$24,MATCH($A9,'Indicator Master'!$A$4:$A$24,0)) -> 35 | H9: Raw Score = score of the single band whose condition the borrower value satisfies; 0 if none is breached. | I9: Normalised = Raw ÷ Max Score × 100 (0–100). Fed into the Overall Score Engine.
A10: CM-006 | B10: Audit opinion classification | C10: Credit Monitoring | D10: Qualified audit opinion or going concern issue | E10: Classify event severity for 'Adverse audit remarks' (no numeric calc) | F10: No issue = 0 | delayed/minor qualification = 10 | material qualification/change = 25 | going concern/adverse = 40 | G10: =INDEX('Indicator Master'!$N$4:$N$24,MATCH($A10,'Indicator Master'!$A$4:$A$24,0)) -> 40 | H10: Raw Score = score of the single band whose condition the borrower value satisfies; 0 if none is breached. | I10: Normalised = Raw ÷ Max Score × 100 (0–100). Fed into the Overall Score Engine.
A11: CM-007 | B11: NCLT/IBC admission status | C11: Credit Monitoring | D11: Insolvency filing against borrower or group | E11: NCLT/IBC admission = TRUE/FALSE | F11: No case = 0 | civil/regulatory notice = 15 | multiple/material cases = 30 | IBC/NCLT = 50 | G11: =INDEX('Indicator Master'!$N$4:$N$24,MATCH($A11,'Indicator Master'!$A$4:$A$24,0)) -> 50 | H11: Raw Score = score of the single band whose condition the borrower value satisfies; 0 if none is breached. | I11: Normalised = Raw ÷ Max Score × 100 (0–100). Fed into the Overall Score Engine.
A12: CM-008 | B12: Restructuring request status | C12: Credit Monitoring | D12: Moratorium, repayment extension, lower interest request | E12: Check restructuring request status | F12: No request = 0 | informal request = 15 | formal restructuring = 30 | repeated = 40 | G12: =INDEX('Indicator Master'!$N$4:$N$24,MATCH($A12,'Indicator Master'!$A$4:$A$24,0)) -> 40 | H12: Raw Score = score of the single band whose condition the borrower value satisfies; 0 if none is breached. | I12: Normalised = Raw ÷ Max Score × 100 (0–100). Fed into the Overall Score Engine.
A13: CM-009 | B13: Security/collateral cover ratio | C13: Credit Monitoring | D13: Collateral value falling | E13: Compute Security/collateral cover ratio then compare to threshold bands | F13: ≥1.25 (adequate) = 0 | 1.10–1.25 (minor shortfall) = 15 | 1.00–1.10 (major shortfall) = 30 | <1.00 (under-secured) = 40 | G13: =INDEX('Indicator Master'!$N$4:$N$24,MATCH($A13,'Indicator Master'!$A$4:$A$24,0)) -> 40 | H13: Raw Score = score of the single band whose condition the borrower value satisfies; 0 if none is breached. | I13: Normalised = Raw ÷ Max Score × 100 (0–100). Fed into the Overall Score Engine.
A14: CM-010 | B14: Insurance validity / days to expiry | C14: Credit Monitoring | D14: Stock/property/machinery insurance not renewed | E14: DaysToExpiry(insurance); lapsed = TRUE/FALSE | F14: Adequate/current = 0 | minor shortfall/lapse = 15 | major shortfall/lapse = 30 | uninsured/under-secured = 40 | G14: =INDEX('Indicator Master'!$N$4:$N$24,MATCH($A14,'Indicator Master'!$A$4:$A$24,0)) -> 40 | H14: Raw Score = score of the single band whose condition the borrower value satisfies; 0 if none is breached. | I14: Normalised = Raw ÷ Max Score × 100 (0–100). Fed into the Overall Score Engine.
A15: CM-011 | B15: Top-customer revenue concentration % | C15: Credit Monitoring | D15: High sales from one or few customers | E15: Compute Top-customer revenue concentration % then compare to threshold bands | F15: <25% exposure = 0 | 25-40% = 10 | 40-60% = 20 | >60% = 30 | G15: =INDEX('Indicator Master'!$N$4:$N$24,MATCH($A15,'Indicator Master'!$A$4:$A$24,0)) -> 30 | H15: Raw Score = score of the single band whose condition the borrower value satisfies; 0 if none is breached. | I15: Normalised = Raw ÷ Max Score × 100 (0–100). Fed into the Overall Score Engine.
A16: CM-012 | B16: Top-supplier purchase concentration % | C16: Credit Monitoring | D16: Dependence on few suppliers | E16: Compute Top-supplier purchase concentration % then compare to threshold bands | F16: <25% exposure = 0 | 25-40% = 10 | 40-60% = 20 | >60% = 30 | G16: =INDEX('Indicator Master'!$N$4:$N$24,MATCH($A16,'Indicator Master'!$A$4:$A$24,0)) -> 30 | H16: Raw Score = score of the single band whose condition the borrower value satisfies; 0 if none is breached. | I16: Normalised = Raw ÷ Max Score × 100 (0–100). Fed into the Overall Score Engine.
... A25: CM-021 | B25: Count of overdue events (rolling 3-6m) | C25: Credit Monitoring | D25: Number of times borrower delays payment in last 3-6 months | E25: COUNT(overdue events) in rolling 3-6 months | F25: 0 instances = 0 | 1 instance = 5 | 2 instances = 15 | 3+ instances = 25 | G25: =INDEX('Indicator Master'!$N$4:$N$24,MATCH($A25,'Indicator Master'!$A$4:$A$24,0)) -> 25 | H25: Raw Score = score of the single band whose condition the borrower value satisfies; 0 if none is breached. | I25: Normalised = Raw ÷ Max Score × 100 (0–100). Fed into the Overall Score Engine.

Sheet Scoring Engine (Rules)
A1: Threshold & Scoring Engine — Machine-Readable Rules + Remedial Playbook
A2: One row per band. Rule Type/Lower/Upper/Operator are data-type driven; Normalised@Band & Is-Max are live; key = UID|Raw.
A4: UID | B4: Indicator | C4: Module | D4: Metric / Input | E4: Band Order | F4: Condition | G4: Rule Type | H4: Lower Bound | I4: Upper Bound | J4: Operator | K4: Raw Score | L4: Normalised @ Band | M4: Is Max Band | N4: Critical Event Flag | O4: What it signals & likely drivers | P4: Remedial action plan (step-by-step) | Q4: Primary owner | R4: key (helper)
A5: CM-001 | B5: DPD (days past due) | C5: Credit Monitoring | D5: EMI / interest overdue by 1-30 days | E5: 1 | F5: 0 days | G5: Count/Days Exact | H5: 0 | I5: 0 | J5: exactly = value | K5: 0 | L5: =$K5/INDEX('Indicator Master'!$N$4:$N$24,MATCH($A5,'Indicator Master'!$A$4:$A$24,0))*'Risk Bands (Config)'!$B$5 -> 0 | M5: =IF($K5=INDEX('Indicator Master'!$N$4:$N$24,MATCH($A5,'Indicator Master'!$A$4:$A$24,0)),1,0) -> 0 | O5: Normal — no days past due; servicing on time. | P5: No remedial action required. Continue routine monitoring at the standard review cycle and record the reading. | Q5: RM (routine) | R5: =$A5&"|"&$K5 -> CM-001|0
A6: CM-001 | B6: DPD (days past due) | C6: Credit Monitoring | D6: EMI / interest overdue by 1-30 days | E6: 2 | F6: 1-30 DPD | G6: Days Range | H6: 1 | I6: 30 | J6: ≥ lower & ≤ upper | K6: 10 | L6: =$K6/INDEX('Indicator Master'!$N$4:$N$24,MATCH($A6,'Indicator Master'!$A$4:$A$24,0))*'Risk Bands (Config)'!$B$5 -> 25 | M6: =IF($K6=INDEX('Indicator Master'!$N$4:$N$24,MATCH($A6,'Indicator Master'!$A$4:$A$24,0)),1,0) -> 0 | O6: Early warning — 1–30 days past due (SMA-0); a short cash-flow slip. | P6: 1) Contact the borrower; obtain the reason and a dated payment commitment. 2) Tag SMA-0. 3) Watch daily. | Q6: Relationship Manager (Branch) | R6: =$A6&"|"&$K6 -> CM-001|10
A7: CM-001 | B7: DPD (days past due) | C7: Credit Monitoring | D7: EMI / interest overdue by 1-30 days | E7: 3 | F7: 31-60 DPD | G7: Days Range | H7: 31 | I7: 60 | J7: ≥ lower & ≤ upper | K7: 20 | L7: =$K7/INDEX('Indicator Master'!$N$4:$N$24,MATCH($A7,'Indicator Master'!$A$4:$A$24,0))*'Risk Bands (Config)'!$B$5 -> 50 | M7: =IF($K7=INDEX('Indicator Master'!$N$4:$N$24,MATCH($A7,'Indicator Master'!$A$4:$A$24,0)),1,0) -> 0 | O7: Elevated concern — 31–60 days past due (SMA-1); persistent delay indicating liquidity stress. | P7: 1) Escalate follow-up; RM engagement. 2) Tag SMA-1; obtain a corrective plan. 3) Review limit conduct. | Q7: RM + Credit Analyst | R7: =$A7&"|"&$K7 -> CM-001|20
A8: CM-001 | B8: DPD (days past due) | C8: Credit Monitoring | D8: EMI / interest overdue by 1-30 days | E8: 4 | F8: 61-90 DPD | G8: Days Range | H8: 61 | I8: 90 | J8: ≥ lower & ≤ upper | K8: 30 | L8: =$K8/INDEX('Indicator Master'!$N$4:$N$24,MATCH($A8,'Indicator Master'!$A$4:$A$24,0))*'Risk Bands (Config)'!$B$5 -> 75 | M8: =IF($K8=INDEX('Indicator Master'!$N$4:$N$24,MATCH($A8,'Indicator Master'!$A$4:$A$24,0)),1,0) -> 0 | O8: High concern — 61–90 days past due (SMA-2); serious delinquency approaching NPA. | P8: 1) Tag SMA-2; issue a formal notice. 2) Assess security and recovery options. 3) Escalate to Credit; provisioning review. | Q8: Credit Committee / Zonal Credit | R8: =$A8&"|"&$K8 -> CM-001|30
A9: CM-001 | B9: DPD (days past due) | C9: Credit Monitoring | D9: EMI / interest overdue by 1-30 days | E9: 5 | F9: 90+ DPD | G9: Days Threshold | H9: 90 | J9: > lower | K9: 40 | L9: =$K9/INDEX('Indicator Master'!$N$4:$N$24,MATCH($A9,'Indicator Master'!$A$4:$A$24,0))*'Risk Bands (Config)'!$B$5 -> 100 | M9: =IF($K9=INDEX('Indicator Master'!$N$4:$N$24,MATCH($A9,'Indicator Master'!$A$4:$A$24,0)),1,0) -> 1 | O9: Severe / critical — 90+ days past due; NPA-level default. | P9: 1) Classify NPA per norms and provide. 2) Invoke recovery / SARFAESI as warranted. 3) Escalate to Credit Committee / Recovery. | Q9: Credit Head / Risk | R9: =$A9&"|"&$K9 -> CM-001|40
A10: CM-002 | B10: Excess over DP/limit % | C10: Credit Monitoring | D10: Drawing power breach or limit excess | E10: 1 | F10: No breach | G10: Percent Threshold | I10: 0 | J10: ≤ upper | K10: 0 | L10: =$K10/INDEX('Indicator Master'!$N$4:$N$24,MATCH($A10,'Indicator Master'!$A$4:$A$24,0))*'Risk Bands (Config)'!$B$5 -> 0 | M10: =IF($K10=INDEX('Indicator Master'!$N$4:$N$24,MATCH($A10,'Indicator Master'!$A$4:$A$24,0)),1,0) -> 0 | O10: Normal — outstanding within the sanctioned DP/limit. | P10: No remedial action required. Continue routine monitoring at the standard review cycle and record the reading. | Q10: RM (routine) | R10: =$A10&"|"&$K10 -> CM-002|0
A11: CM-002 | B11: Excess over DP/limit % | C11: Credit Monitoring | D11: Drawing power breach or limit excess | E11: 2 | F11: Up to 5% breach | G11: Percent Range | H11: 0 | I11: 5 | J11: > lower & ≤ upper | K11: 10 | L11: =$K11/INDEX('Indicator Master'!$N$4:$N$24,MATCH($A11,'Indicator Master'!$A$4:$A$24,0))*'Risk Bands (Config)'!$B$5 -> 33.333333 | M11: =IF($K11=INDEX('Indicator Master'!$N$4:$N$24,MATCH($A11,'Indicator Master'!$A$4:$A$24,0)),1,0) -> 0 | O11: Early warning — excess up to 5%; minor, likely a timing over-draw. | P11: 1) Regularise the excess promptly. 2) Ascertain the reason. 3) Allow no fresh excess. | Q11: RM + Credit Analyst | R11: =$A11&"|"&$K11 -> CM-002|10
A12: CM-002 | B12: Excess over DP/limit % | C12: Credit Monitoring | D12: Drawing power breach or limit excess | E12: 3 | F12: 5-10% | G12: Percent Range | H12: 5 | I12: 10 | J12: > lower & ≤ upper | K12: 20 | L12: =$K12/INDEX('Indicator Master'!$N$4:$N$24,MATCH($A12,'Indicator Master'!$A$4:$A$24,0))*'Risk Bands (Config)'!$B$5 -> 66.666667 | M12: =IF($K12=INDEX('Indicator Master'!$N$4:$N$24,MATCH($A12,'Indicator Master'!$A$4:$A$24,0)),1,0) -> 0 | O12: Elevated concern — excess 5–10%; recurring over-limit use — DP or limit pressure. | P12: 1) Review DP/limit adequacy vs turnover. 2) Restrict further drawals. 3) Monitor; flag to Credit. | Q12: Credit Committee / Zonal Credit | R12: =$A12&"|"&$K12 -> CM-002|20
A13: CM-002 | B13: Excess over DP/limit % | C13: Credit Monitoring | D13: Drawing power breach or limit excess | E13: 4 | F13: >10% or repeated | G13: Percent Threshold | H13: 10 | J13: > lower (or repeated breach) | K13: 30 | L13: =$K13/INDEX('Indicator Master'!$N$4:$N$24,MATCH($A13,'Indicator Master'!$A$4:$A$24,0))*'Risk Bands (Config)'!$B$5 -> 100 | M13: =IF($K13=INDEX('Indicator Master'!$N$4:$N$24,MATCH($A13,'Indicator Master'!$A$4:$A$24,0)),1,0) -> 1 | O13: Severe / critical — excess >10% or repeated breaches; persistent over-drawing / liquidity stress. | P13: 1) Freeze fresh drawals pending review. 2) Reassess limits and conduct; corrective plan. 3) Escalate to Credit. | Q13: Credit Head / Risk | R13: =$A13&"|"&$K13 -> CM-002|30
A14: CM-003 | B14: GST turnover change % / vs bank credits | C14: Credit Monitoring | D14: GST sales lower than projected or lower than bank statement credits | E14: 1 | F14: Stable/increasing | G14: Percent Threshold | I14: 10 | J14: < upper | K14: 0 | L14: =$K14/INDEX('Indicator Master'!$N$4:$N$24,MATCH($A14,'Indicator Master'!$A$4:$A$24,0))*'Risk Bands (Config)'!$B$5 -> 0 | M14: =IF($K14=INDEX('Indicator Master'!$N$4:$N$24,MATCH($A14,'Indicator Master'!$A$4:$A$24,0)),1,0) -> 0 | O14: Normal — GST turnover stable or rising; activity intact. | P14: No remedial action required. Continue routine monitoring at the standard review cycle and record the reading. | Q14: RM (routine) | R14: =$A14&"|"&$K14 -> CM-003|0
A15: CM-003 | B15: GST turnover change % / vs bank credits | C15: Credit Monitoring | D15: GST sales lower than projected or lower than bank statement credits | E15: 2 | F15: 10-20% decline | G15: Percent Range | H15: 10 | I15: 20 | J15: ≥ lower & < upper | K15: 10 | L15: =$K15/INDEX('Indicator Master'!$N$4:$N$24,MATCH($A15,'Indicator Master'!$A$4:$A$24,0))*'Risk Bands (Config)'!$B$5 -> 28.571429 | M15: =IF($K15=INDEX('Indicator Master'!$N$4:$N$24,MATCH($A15,'Indicator Master'!$A$4:$A$24,0)),1,0) -> 0 | O15: Early warning — GST turnover down 10–20%; early softening or partial under-reporting. | P15: 1) Reconcile GST vs book sales vs bank credits. 2) Obtain the reason. 3) Monitor monthly. | Q15: Relationship Manager (Branch) | R15: =$A15&"|"&$K15 -> CM-003|10
A16: CM-003 | B16: GST turnover change % / vs bank credits | C16: Credit Monitoring | D16: GST sales lower than projected or lower than bank statement credits | E16: 3 | F16: 20-40% decline | G16: Percent Range | H16: 20 | I16: 40 | J16: ≥ lower & < upper | K16: 20 | L16: =$K16/INDEX('Indicator Master'!$N$4:$N$24,MATCH($A16,'Indicator Master'!$A$4:$A$24,0))*'Risk Bands (Config)'!$B$5 -> 57.142857 | M16: =IF($K16=INDEX('Indicator Master'!$N$4:$N$24,MATCH($A16,'Indicator Master'!$A$4:$A$24,0)),1,0) -> 0 | O16: Elevated concern — down 20–40%; material fall — demand loss or diversion of billing. | P16: 1) Reassess WC and projections. 2) Investigate under-reporting/diversion. 3) Enhanced monitoring; flag to Credit. | Q16: RM + Credit Analyst | R16: =$A16&"|"&$K16 -> CM-003|20
A17: CM-003 | B17: GST turnover change % / vs bank credits | C17: Credit Monitoring | D17: GST sales lower than projected or lower than bank statement credits | E17: 4 | F17: >40% decline | G17: Percent Threshold | H17: 40 | J17: ≥ lower | K17: 35 | L17: =$K17/INDEX('Indicator Master'!$N$4:$N$24,MATCH($A17,'Indicator Master'!$A$4:$A$24,0))*'Risk Bands (Config)'!$B$5 -> 100 | M17: =IF($K17=INDEX('Indicator Master'!$N$4:$N$24,MATCH($A17,'Indicator Master'!$A$4:$A$24,0)),1,0) -> 1 | O17: Severe / critical — down >40%; severe — sharp contraction or suppressed reporting. | P17: 1) Full turnover/viability review; verify against e-way bills/returns. 2) Corrective plan. 3) Escalate to Credit. | Q17: Credit Head / Risk | R17: =$A17&"|"&$K17 -> CM-003|35
A18: CM-004 | B18: Cash Flow from Operations (sign / periods) | C18: Credit Monitoring | D18: CFO negative for repeated periods | E18: 1 | F18: Positive CFO | G18: Count Exact | H18: 0 | I18: 0 | J18: exactly = value (positive CFO) | K18: 0 | L18: =$K18/INDEX('Indicator Master'!$N$4:$N$24,MATCH($A18,'Indicator Master'!$A$4:$A$24,0))*'Risk Bands (Config)'!$B$5 -> 0 | M18: =IF($K18=INDEX('Indicator Master'!$N$4:$N$24,MATCH($A18,'Indicator Master'!$A$4:$A$24,0)),1,0) -> 0 | O18: Normal — operating cash flow positive; self-funding operations. | P18: No remedial action required. Continue routine monitoring at the standard review cycle and record the reading. | Q18: RM (routine) | R18: =$A18&"|"&$K18 -> CM-004|0
A19: CM-004 | B19: Cash Flow from Operations (sign / periods) | C19: Credit Monitoring | D19: CFO negative for repeated periods | E19: 2 | F19: 1 negative period | G19: Count Exact | H19: 1 | I19: 1 | J19: exactly = value (1 negative period) | K19: 15 | L19: =$K19/INDEX('Indicator Master'!$N$4:$N$24,MATCH($A19,'Indicator Master'!$A$4:$A$24,0))*'Risk Bands (Config)'!$B$5 -> 37.5 | M19: =IF($K19=INDEX('Indicator Master'!$N$4:$N$24,MATCH($A19,'Indicator Master'!$A$4:$A$24,0)),1,0) -> 0 | O19: Elevated concern — one negative CFO period; isolated — watch for persistence. | P19: 1) Analyse the CFO driver (WC swing vs loss). 2) Obtain an explanation. 3) Monitor next period. | Q19: RM + Credit Analyst | R19: =$A19&"|"&$K19 -> CM-004|15
A20: CM-004 | B20: Cash Flow from Operations (sign / periods) | C20: Credit Monitoring | D20: CFO negative for repeated periods | E20: 3 | F20: 2 consecutive periods | G20: Count Exact | H20: 2 | I20: 2 | J20: exactly = value (2 consecutive) | K20: 30 | L20: =$K20/INDEX('Indicator Master'!$N$4:$N$24,MATCH($A20,'Indicator Master'!$A$4:$A$24,0))*'Risk Bands (Config)'!$B$5 -> 75 | M20: =IF($K20=INDEX('Indicator Master'!$N$4:$N$24,MATCH($A20,'Indicator Master'!$A$4:$A$24,0)),1,0) -> 0 | O20: High concern — two consecutive negative CFO periods; operations not generating cash. | P20: 1) Reassess debt-servicing capacity. 2) Seek promoter support; enhanced monitoring. 3) Flag to Credit. | Q20: Credit Committee / Zonal Credit | R20: =$A20&"|"&$K20 -> CM-004|30
A21: CM-004 | B21: Cash Flow from Operations (sign / periods) | C21: Credit Monitoring | D21: CFO negative for repeated periods | E21: 4 | F21: severe negative | G21: Count Threshold | H21: 3 | J21: ≥ lower (or severe negative) | K21: 40 | L21: =$K21/INDEX('Indicator Master'!$N$4:$N$24,MATCH($A21,'Indicator Master'!$A$4:$A$24,0))*'Risk Bands (Config)'!$B$5 -> 100 | M21: =IF($K21=INDEX('Indicator Master'!$N$4:$N$24,MATCH($A21,'Indicator Master'!$A$4:$A$24,0)),1,0) -> 1 | O21: Severe / critical — severe negative CFO; operations consuming significant cash — acute stress. | P21: 1) Reassess viability / restructuring need. 2) Corrective cash-flow plan. 3) Escalate to Credit. | Q21: Credit Head / Risk | R21: =$A21&"|"&$K21 -> CM-004|40
A22: CM-005 | B22: Current Ratio | C22: Credit Monitoring | D22: Current assets lower compared to current liabilities | E22: 1 | F22: >=1.33 | G22: Ratio Threshold | H22: 1.33 | J22: ≥ lower | K22: 0 | L22: =$K22/INDEX('Indicator Master'!$N$4:$N$24,MATCH($A22,'Indicator Master'!$A$4:$A$24,0))*'Risk Bands (Config)'!$B$5 -> 0 | M22: =IF($K22=INDEX('Indicator Master'!$N$4:$N$24,MATCH($A22,'Indicator Master'!$A$4:$A$24,0)),1,0) -> 0 | O22: Normal — current ratio ≥1.33; comfortable short-term liquidity. | P22: No remedial action required. Continue routine monitoring at the standard review cycle and record the reading. | Q22: RM (routine) | R22: =$A22&"|"&$K22 -> CM-005|0
A23: CM-005 | B23: Current Ratio | C23: Credit Monitoring | D23: Current assets lower compared to current liabilities | E23: 2 | F23: 1.10-1.32 | G23: Ratio Range | H23: 1.1 | I23: 1.33 | J23: ≥ lower & < upper | K23: 10 | L23: =$K23/INDEX('Indicator Master'!$N$4:$N$24,MATCH($A23,'Indicator Master'!$A$4:$A$24,0))*'Risk Bands (Config)'!$B$5 -> 28.571429 | M23: =IF($K23=INDEX('Indicator Master'!$N$4:$N$24,MATCH($A23,'Indicator Master'!$A$4:$A$24,0)),1,0) -> 0 | O23: Early warning — current ratio 1.10–1.32; adequate but easing liquidity. | P23: 1) Note the easing; review the WC position. 2) Watch the next statement. | Q23: Relationship Manager (Branch) | R23: =$A23&"|"&$K23 -> CM-005|10
A24: CM-005 | B24: Current Ratio | C24: Credit Monitoring | D24: Current assets lower compared to current liabilities | E24: 3 | F24: 1.00-1.09 | G24: Ratio Range | H24: 1 | I24: 1.1 | J24: ≥ lower & < upper | K24: 20 | L24: =$K24/INDEX('Indicator Master'!$N$4:$N$24,MATCH($A24,'Indicator Master'!$A$4:$A$24,0))*'Risk Bands (Config)'!$B$5 -> 57.142857 | M24: =IF($K24=INDEX('Indicator Master'!$N$4:$N$24,MATCH($A24,'Indicator Master'!$A$4:$A$24,0)),1,0) -> 0 | O24: Elevated concern — current ratio 1.00–1.09; thin liquidity buffer. | P24: 1) Assess NWC adequacy; seek promoter infusion. 2) Enhanced monitoring. 3) Flag to Credit. | Q24: RM + Credit Analyst | R24: =$A24&"|"&$K24 -> CM-005|20
A25: CM-005 | B25: Current Ratio | C25: Credit Monitoring | D25: Current assets lower compared to current liabilities | E25: 4 | F25: <1.00 | G25: Ratio Threshold | I25: 1 | J25: < upper | K25: 35 | L25: =$K25/INDEX('Indicator Master'!$N$4:$N$24,MATCH($A25,'Indicator Master'!$A$4:$A$24,0))*'Risk Bands (Config)'!$B$5 -> 100 | M25: =IF($K25=INDEX('Indicator Master'!$N$4:$N$24,MATCH($A25,'Indicator Master'!$A$4:$A$24,0)),1,0) -> 1 | O25: Severe / critical — current ratio below 1.00; current liabilities exceed current assets — liquidity stress. | P25: 1) Reassess limits and liquidity; corrective plan. 2) Monitor closely. 3) Escalate to Credit. | Q25: Credit Head / Risk | R25: =$A25&"|"&$K25 -> CM-005|35
A26: CM-006 | B26: Audit opinion classification | C26: Credit Monitoring | D26: Qualified audit opinion or going concern issue | E26: 1 | F26: No issue | G26: Ordinal Classification | J26: category | K26: 0 | L26: =$K26/INDEX('Indicator Master'!$N$4:$N$24,MATCH($A26,'Indicator Master'!$A$4:$A$24,0))*'Risk Bands (Config)'!$B$5 -> 0 | M26: =IF($K26=INDEX('Indicator Master'!$N$4:$N$24,MATCH($A26,'Indicator Master'!$A$4:$A$24,0)),1,0) -> 0 | O26: Normal — clean audit opinion; reliable reporting. | P26: No remedial action required. Continue routine monitoring at the standard review cycle and record the reading. | Q26: RM (routine) | R26: =$A26&"|"&$K26 -> CM-006|0
A27: CM-006 | B27: Audit opinion classification | C27: Credit Monitoring | D27: Qualified audit opinion or going concern issue | E27: 2 | F27: delayed/minor qualification | G27: Ordinal Classification | J27: category | K27: 10 | L27: =$K27/INDEX('Indicator Master'!$N$4:$N$24,MATCH($A27,'Indicator Master'!$A$4:$A$24,0))*'Risk Bands (Config)'!$B$5 -> 25 | M27: =IF($K27=INDEX('Indicator Master'!$N$4:$N$24,MATCH($A27,'Indicator Master'!$A$4:$A$24,0)),1,0) -> 0 | O27: Early warning — delayed audit or a minor qualification; low-level concern. | P27: 1) Read the qualification; assess materiality. 2) Seek clarification. 3) Monitor. | Q27: Relationship Manager (Branch) | R27: =$A27&"|"&$K27 -> CM-006|10
A28: CM-006 | B28: Audit opinion classification | C28: Credit Monitoring | D28: Qualified audit opinion or going concern issue | E28: 3 | F28: material qualification/change | G28: Ordinal Classification | J28: category | K28: 25 | L28: =$K28/INDEX('Indicator Master'!$N$4:$N$24,MATCH($A28,'Indicator Master'!$A$4:$A$24,0))*'Risk Bands (Config)'!$B$5 -> 62.5 | M28: =IF($K28=INDEX('Indicator Master'!$N$4:$N$24,MATCH($A28,'Indicator Master'!$A$4:$A$24,0)),1,0) -> 0 | O28: Elevated concern — material qualification or an auditor change; reporting reliability in question. | P28: 1) Adjust the analysis for the qualification. 2) Independent/special review. 3) Escalate to Credit. | Q28: Credit Committee / Zonal Credit | R28: =$A28&"|"&$K28 -> CM-006|25
A29: CM-006 | B29: Audit opinion classification | C29: Credit Monitoring | D29: Qualified audit opinion or going concern issue | E29: 4 | F29: going concern/adverse | G29: Ordinal Classification | J29: category | K29: 40 | L29: =$K29/INDEX('Indicator Master'!$N$4:$N$24,MATCH($A29,'Indicator Master'!$A$4:$A$24,0))*'Risk Bands (Config)'!$B$5 -> 100 | M29: =IF($K29=INDEX('Indicator Master'!$N$4:$N$24,MATCH($A29,'Indicator Master'!$A$4:$A$24,0)),1,0) -> 1 | O29: Severe / critical — going-concern or adverse opinion; doubt over viability. | P29: 1) Treat as a material adverse change; forensic review. 2) Reassess exposure and security. 3) Escalate to Credit Committee. | Q29: Credit Head / Risk | R29: =$A29&"|"&$K29 -> CM-006|40
A30: CM-007 | B30: NCLT/IBC admission status | C30: Credit Monitoring | D30: Insolvency filing against borrower or group | E30: 1 | F30: No case | G30: Ordinal Classification | J30: category | K30: 0 | L30: =$K30/INDEX('Indicator Master'!$N$4:$N$24,MATCH($A30,'Indicator Master'!$A$4:$A$24,0))*'Risk Bands (Config)'!$B$5 -> 0 | M30: =IF($K30=INDEX('Indicator Master'!$N$4:$N$24,MATCH($A30,'Indicator Master'!$A$4:$A$24,0)),1,0) -> 0 | O30: Normal — no insolvency/legal proceedings; clean status. | P30: No remedial action required. Continue routine monitoring at the standard review cycle and record the reading. | Q30: RM (routine) | R30: =$A30&"|"&$K30 -> CM-007|0
A31: CM-007 | B31: NCLT/IBC admission status | C31: Credit Monitoring | D31: Insolvency filing against borrower or group | E31: 2 | F31: civil/regulatory notice | G31: Ordinal Classification | J31: category | K31: 15 | L31: =$K31/INDEX('Indicator Master'!$N$4:$N$24,MATCH($A31,'Indicator Master'!$A$4:$A$24,0))*'Risk Bands (Config)'!$B$5 -> 30 | M31: =IF($K31=INDEX('Indicator Master'!$N$4:$N$24,MATCH($A31,'Indicator Master'!$A$4:$A$24,0)),1,0) -> 0 | O31: Early warning — a civil/regulatory notice; early legal exposure. | P31: 1) Obtain case details; assess materiality. 2) Legal review. 3) Monitor. | Q31: Relationship Manager (Branch) | R31: =$A31&"|"&$K31 -> CM-007|15
A32: CM-007 | B32: NCLT/IBC admission status | C32: Credit Monitoring | D32: Insolvency filing against borrower or group | E32: 3 | F32: multiple/material cases | G32: Ordinal Classification | J32: category | K32: 30 | L32: =$K32/INDEX('Indicator Master'!$N$4:$N$24,MATCH($A32,'Indicator Master'!$A$4:$A$24,0))*'Risk Bands (Config)'!$B$5 -> 60 | M32: =IF($K32=INDEX('Indicator Master'!$N$4:$N$24,MATCH($A32,'Indicator Master'!$A$4:$A$24,0)),1,0) -> 0 | O32: Elevated concern — multiple or material cases; escalating legal risk. | P32: 1) Quantify exposure; provision if material. 2) Protect the bank's charge. 3) Escalate to Credit/Legal. | Q32: RM + Credit Analyst | R32: =$A32&"|"&$K32 -> CM-007|30
A33: CM-007 | B33: NCLT/IBC admission status | C33: Credit Monitoring | D33: Insolvency filing against borrower or group | E33: 4 | F33: IBC/NCLT | G33: Ordinal Classification | J33: category | K33: 50 | L33: =$K33/INDEX('Indicator Master'!$N$4:$N$24,MATCH($A33,'Indicator Master'!$A$4:$A$24,0))*'Risk Bands (Config)'!$B$5 -> 100 | M33: =IF($K33=INDEX('Indicator Master'!$N$4:$N$24,MATCH($A33,'Indicator Master'!$A$4:$A$24,0)),1,0) -> 1 | O33: Severe / critical — IBC/NCLT admission; a default/recovery event. | P33: 1) Verify status; file/protect the claim. 2) Participate in the CoC; full provisioning. 3) Escalate to Credit Committee / Recovery. | Q33: Credit Head / Legal / Recovery | R33: =$A33&"|"&$K33 -> CM-007|50
A34: CM-008 | B34: Restructuring request status | C34: Credit Monitoring | D34: Moratorium, repayment extension, lower interest request | E34: 1 | F34: No request | G34: Ordinal Classification | J34: category | K34: 0 | L34: =$K34/INDEX('Indicator Master'!$N$4:$N$24,MATCH($A34,'Indicator Master'!$A$4:$A$24,0))*'Risk Bands (Config)'!$B$5 -> 0 | M34: =IF($K34=INDEX('Indicator Master'!$N$4:$N$24,MATCH($A34,'Indicator Master'!$A$4:$A$24,0)),1,0) -> 0 | O34: Normal — no restructuring sought; performing to terms. | P34: No remedial action required. Continue routine monitoring at the standard review cycle and record the reading. | Q34: RM (routine) | R34: =$A34&"|"&$K34 -> CM-008|0
A35: CM-008 | B35: Restructuring request status | C35: Credit Monitoring | D35: Moratorium, repayment extension, lower interest request | E35: 2 | F35: informal request | G35: Ordinal Classification | J35: category | K35: 15 | L35: =$K35/INDEX('Indicator Master'!$N$4:$N$24,MATCH($A35,'Indicator Master'!$A$4:$A$24,0))*'Risk Bands (Config)'!$B$5 -> 37.5 | M35: =IF($K35=INDEX('Indicator Master'!$N$4:$N$24,MATCH($A35,'Indicator Master'!$A$4:$A$24,0)),1,0) -> 0 | O35: Elevated concern — an informal restructuring/moratorium enquiry; early stress signal. | P35: 1) Obtain the rationale; assess genuine stress vs willful. 2) Seek cash-flow data. 3) Monitor. | Q35: RM + Credit Analyst | R35: =$A35&"|"&$K35 -> CM-008|15
A36: CM-008 | B36: Restructuring request status | C36: Credit Monitoring | D36: Moratorium, repayment extension, lower interest request | E36: 3 | F36: formal restructuring | G36: Ordinal Classification | J36: category | K36: 30 | L36: =$K36/INDEX('Indicator Master'!$N$4:$N$24,MATCH($A36,'Indicator Master'!$A$4:$A$24,0))*'Risk Bands (Config)'!$B$5 -> 75 | M36: =IF($K36=INDEX('Indicator Master'!$N$4:$N$24,MATCH($A36,'Indicator Master'!$A$4:$A$24,0)),1,0) -> 0 | O36: High concern — a formal restructuring request; acknowledged inability to service on current terms. | P36: 1) Conduct a viability/TEV assessment under the applicable framework. 2) Determine sacrifice/provisioning. 3) Escalate to Credit. | Q36: Credit Committee / Zonal Credit | R36: =$A36&"|"&$K36 -> CM-008|30
A37: CM-008 | B37: Restructuring request status | C37: Credit Monitoring | D37: Moratorium, repayment extension, lower interest request | E37: 4 | F37: repeated | G37: Ordinal Classification | J37: category | K37: 40 | L37: =$K37/INDEX('Indicator Master'!$N$4:$N$24,MATCH($A37,'Indicator Master'!$A$4:$A$24,0))*'Risk Bands (Config)'!$B$5 -> 100 | M37: =IF($K37=INDEX('Indicator Master'!$N$4:$N$24,MATCH($A37,'Indicator Master'!$A$4:$A$24,0)),1,0) -> 1 | O37: Severe / critical — repeated restructuring; chronic stress / evergreening risk. | P37: 1) Treat as chronic stress; guard against evergreening. 2) Reassess exit/recovery. 3) Escalate to Credit Committee. | Q37: Credit Head / Risk | R37: =$A37&"|"&$K37 -> CM-008|40
A38: CM-009 | B38: Security/collateral cover ratio | C38: Credit Monitoring | D38: Collateral value falling | E38: 1 | F38: ≥1.25 (adequate) | G38: Ratio Threshold | H38: 1.25 | J38: ≥ lower | K38: 0 | L38: =$K38/INDEX('Indicator Master'!$N$4:$N$24,MATCH($A38,'Indicator Master'!$A$4:$A$24,0))*'Risk Bands (Config)'!$B$5 -> 0 | M38: =IF($K38=INDEX('Indicator Master'!$N$4:$N$24,MATCH($A38,'Indicator Master'!$A$4:$A$24,0)),1,0) -> 0 | O38: Normal — collateral cover adequate and current. | P38: No remedial action required. Continue routine monitoring at the standard review cycle and record the reading. | Q38: RM (routine) | R38: =$A38&"|"&$K38 -> CM-009|0
A39: CM-009 | B39: Security/collateral cover ratio | C39: Credit Monitoring | D39: Collateral value falling | E39: 2 | F39: 1.10–1.25 (minor shortfall) | G39: Ratio Range | H39: 1.1 | I39: 1.25 | J39: ≥ lower & < upper | K39: 15 | L39: =$K39/INDEX('Indicator Master'!$N$4:$N$24,MATCH($A39,'Indicator Master'!$A$4:$A$24,0))*'Risk Bands (Config)'!$B$5 -> 37.5 | M39: =IF($K39=INDEX('Indicator Master'!$N$4:$N$24,MATCH($A39,'Indicator Master'!$A$4:$A$24,0)),1,0) -> 0 | O39: Elevated concern — a minor shortfall or lapse in cover; top-up needed. | P39: 1) Revalue security; seek a top-up. 2) Adjust DP to available cover. 3) Monitor to closure. | Q39: RM + Credit Analyst | R39: =$A39&"|"&$K39 -> CM-009|15
A40: CM-009 | B40: Security/collateral cover ratio | C40: Credit Monitoring | D40: Collateral value falling | E40: 3 | F40: 1.00–1.10 (major shortfall) | G40: Ratio Range | H40: 1 | I40: 1.1 | J40: ≥ lower & < upper | K40: 30 | L40: =$K40/INDEX('Indicator Master'!$N$4:$N$24,MATCH($A40,'Indicator Master'!$A$4:$A$24,0))*'Risk Bands (Config)'!$B$5 -> 75 | M40: =IF($K40=INDEX('Indicator Master'!$N$4:$N$24,MATCH($A40,'Indicator Master'!$A$4:$A$24,0)),1,0) -> 0 | O40: High concern — a major shortfall; the exposure is materially under-secured. | P40: 1) Obtain additional collateral/margin. 2) Reduce exposure to cover; reprice. 3) Escalate to Credit. | Q40: Credit Committee / Zonal Credit | R40: =$A40&"|"&$K40 -> CM-009|30
A41: CM-009 | B41: Security/collateral cover ratio | C41: Credit Monitoring | D41: Collateral value falling | E41: 4 | F41: <1.00 (under-secured) | G41: Ratio Threshold | I41: 1 | J41: < upper | K41: 40 | L41: =$K41/INDEX('Indicator Master'!$N$4:$N$24,MATCH($A41,'Indicator Master'!$A$4:$A$24,0))*'Risk Bands (Config)'!$B$5 -> 100 | M41: =IF($K41=INDEX('Indicator Master'!$N$4:$N$24,MATCH($A41,'Indicator Master'!$A$4:$A$24,0)),1,0) -> 1 | O41: Severe / critical — uninsured / significantly under-secured; the bank's security is impaired. | P41: 1) Demand additional security or accelerated repayment. 2) Perfect/protect the charge. 3) Escalate to Credit Committee. | Q41: Credit Head / Risk | R41: =$A41&"|"&$K41 -> CM-009|40
A42: CM-010 | B42: Insurance validity / days to expiry | C42: Credit Monitoring | D42: Stock/property/machinery insurance not renewed | E42: 1 | F42: Adequate/current | G42: Ordinal Classification | J42: category | K42: 0 | L42: =$K42/INDEX('Indicator Master'!$N$4:$N$24,MATCH($A42,'Indicator Master'!$A$4:$A$24,0))*'Risk Bands (Config)'!$B$5 -> 0 | M42: =IF($K42=INDEX('Indicator Master'!$N$4:$N$24,MATCH($A42,'Indicator Master'!$A$4:$A$24,0)),1,0) -> 0 | O42: Normal — insurance valid and adequate with the bank clause. | P42: No remedial action required. Continue routine monitoring at the standard review cycle and record the reading. | Q42: RM (routine) | R42: =$A42&"|"&$K42 -> CM-010|0
A43: CM-010 | B43: Insurance validity / days to expiry | C43: Credit Monitoring | D43: Stock/property/machinery insurance not renewed | E43: 2 | F43: minor shortfall/lapse | G43: Ordinal Classification | J43: category | K43: 15 | L43: =$K43/INDEX('Indicator Master'!$N$4:$N$24,MATCH($A43,'Indicator Master'!$A$4:$A$24,0))*'Risk Bands (Config)'!$B$5 -> 37.5 | M43: =IF($K43=INDEX('Indicator Master'!$N$4:$N$24,MATCH($A43,'Indicator Master'!$A$4:$A$24,0)),1,0) -> 0 | O43: Elevated concern — a minor lapse or approaching expiry; renewal needed. | P43: 1) Follow up for renewal with the bank clause; note the expiry. 2) Obtain the policy. 3) Monitor. | Q43: RM + Credit Analyst | R43: =$A43&"|"&$K43 -> CM-010|15
A44: CM-010 | B44: Insurance validity / days to expiry | C44: Credit Monitoring | D44: Stock/property/machinery insurance not renewed | E44: 3 | F44: major shortfall/lapse | G44: Ordinal Classification | J44: category | K44: 30 | L44: =$K44/INDEX('Indicator Master'!$N$4:$N$24,MATCH($A44,'Indicator Master'!$A$4:$A$24,0))*'Risk Bands (Config)'!$B$5 -> 75 | M44: =IF($K44=INDEX('Indicator Master'!$N$4:$N$24,MATCH($A44,'Indicator Master'!$A$4:$A$24,0)),1,0) -> 0 | O44: High concern — a major lapse; charged assets materially uninsured. | P44: 1) Insist on immediate renewal; set a debit mandate. 2) Verify adequate sum insured. 3) Escalate to Credit. | Q44: Credit Committee / Zonal Credit | R44: =$A44&"|"&$K44 -> CM-010|30
A45: CM-010 | B45: Insurance validity / days to expiry | C45: Credit Monitoring | D45: Stock/property/machinery insurance not renewed | E45: 4 | F45: uninsured/under-secured | G45: Ordinal Classification | J45: category | K45: 40 | L45: =$K45/INDEX('Indicator Master'!$N$4:$N$24,MATCH($A45,'Indicator Master'!$A$4:$A$24,0))*'Risk Bands (Config)'!$B$5 -> 100 | M45: =IF($K45=INDEX('Indicator Master'!$N$4:$N$24,MATCH($A45,'Indicator Master'!$A$4:$A$24,0)),1,0) -> 1 | O45: Severe / critical — assets uninsured for a prolonged period; security exposed. | P45: 1) Bank to insure at the borrower's cost. 2) Record a covenant breach; reassess risk. 3) Escalate to Credit Committee. | Q45: Credit Head / Risk | R45: =$A45&"|"&$K45 -> CM-010|40
A46: CM-011 | B46: Top-customer revenue concentration % | C46: Credit Monitoring | D46: High sales from one or few customers | E46: 1 | F46: <25% exposure | G46: Percent Threshold | I46: 25 | J46: < upper | K46: 0 | L46: =$K46/INDEX('Indicator Master'!$N$4:$N$24,MATCH($A46,'Indicator Master'!$A$4:$A$24,0))*'Risk Bands (Config)'!$B$5 -> 0 | M46: =IF($K46=INDEX('Indicator Master'!$N$4:$N$24,MATCH($A46,'Indicator Master'!$A$4:$A$24,0)),1,0) -> 0 | O46: Normal — top-customer concentration below 25%; well diversified. | P46: No remedial action required. Continue routine monitoring at the standard review cycle and record the reading. | Q46: RM (routine) | R46: =$A46&"|"&$K46 -> CM-011|0
A47: CM-011 | B47: Top-customer revenue concentration % | C47: Credit Monitoring | D47: High sales from one or few customers | E47: 2 | F47: 25-40% | G47: Percent Range | H47: 25 | I47: 40 | J47: ≥ lower & < upper | K47: 10 | L47: =$K47/INDEX('Indicator Master'!$N$4:$N$24,MATCH($A47,'Indicator Master'!$A$4:$A$24,0))*'Risk Bands (Config)'!$B$5 -> 33.333333 | M47: =IF($K47=INDEX('Indicator Master'!$N$4:$N$24,MATCH($A47,'Indicator Master'!$A$4:$A$24,0)),1,0) -> 0 | O47: Early warning — concentration 25–40%; moderate dependence on a key customer. | P47: 1) Review the customer mix. 2) Encourage diversification. 3) Monitor the key customer's health. | Q47: RM + Credit Analyst | R47: =$A47&"|"&$K47 -> CM-011|10
A48: CM-011 | B48: Top-customer revenue concentration % | C48: Credit Monitoring | D48: High sales from one or few customers | E48: 3 | F48: 40-60% | G48: Percent Range | H48: 40 | I48: 60 | J48: ≥ lower & < upper | K48: 20 | L48: =$K48/INDEX('Indicator Master'!$N$4:$N$24,MATCH($A48,'Indicator Master'!$A$4:$A$24,0))*'Risk Bands (Config)'!$B$5 -> 66.666667 | M48: =IF($K48=INDEX('Indicator Master'!$N$4:$N$24,MATCH($A48,'Indicator Master'!$A$4:$A$24,0)),1,0) -> 0 | O48: Elevated concern — concentration 40–60%; high dependence — demand-loss risk. | P48: 1) Assess the key customer's creditworthiness. 2) Reassess viability on concentration risk. 3) Flag to Credit. | Q48: Credit Committee / Zonal Credit | R48: =$A48&"|"&$K48 -> CM-011|20
A49: CM-011 | B49: Top-customer revenue concentration % | C49: Credit Monitoring | D49: High sales from one or few customers | E49: 4 | F49: >60% | G49: Percent Threshold | H49: 60 | J49: ≥ lower | K49: 30 | L49: =$K49/INDEX('Indicator Master'!$N$4:$N$24,MATCH($A49,'Indicator Master'!$A$4:$A$24,0))*'Risk Bands (Config)'!$B$5 -> 100 | M49: =IF($K49=INDEX('Indicator Master'!$N$4:$N$24,MATCH($A49,'Indicator Master'!$A$4:$A$24,0)),1,0) -> 1 | O49: Severe / critical — concentration above 60%; severe single-customer dependence. | P49: 1) Stress-test loss of the key customer. 2) Contingency/viability review. 3) Escalate to Credit. | Q49: Credit Head / Risk | R49: =$A49&"|"&$K49 -> CM-011|30
A50: CM-012 | B50: Top-supplier purchase concentration % | C50: Credit Monitoring | D50: Dependence on few suppliers | E50: 1 | F50: <25% exposure | G50: Percent Threshold | I50: 25 | J50: < upper | K50: 0 | L50: =$K50/INDEX('Indicator Master'!$N$4:$N$24,MATCH($A50,'Indicator Master'!$A$4:$A$24,0))*'Risk Bands (Config)'!$B$5 -> 0 | M50: =IF($K50=INDEX('Indicator Master'!$N$4:$N$24,MATCH($A50,'Indicator Master'!$A$4:$A$24,0)),1,0) -> 0 | O50: Normal — top-supplier concentration below 25%; diversified sourcing. | P50: No remedial action required. Continue routine monitoring at the standard review cycle and record the reading. | Q50: RM (routine) | R50: =$A50&"|"&$K50 -> CM-012|0
A51: CM-012 | B51: Top-supplier purchase concentration % | C51: Credit Monitoring | D51: Dependence on few suppliers | E51: 2 | F51: 25-40% | G51: Percent Range | H51: 25 | I51: 40 | J51: ≥ lower & < upper | K51: 10 | L51: =$K51/INDEX('Indicator Master'!$N$4:$N$24,MATCH($A51,'Indicator Master'!$A$4:$A$24,0))*'Risk Bands (Config)'!$B$5 -> 33.333333 | M51: =IF($K51=INDEX('Indicator Master'!$N$4:$N$24,MATCH($A51,'Indicator Master'!$A$4:$A$24,0)),1,0) -> 0 | O51: Early warning — concentration 25–40%; moderate supplier dependence. | P51: 1) Review the sourcing mix. 2) Encourage alternate suppliers. 3) Monitor. | Q51: RM + Credit Analyst | R51: =$A51&"|"&$K51 -> CM-012|10
A52: CM-012 | B52: Top-supplier purchase concentration % | C52: Credit Monitoring | D52: Dependence on few suppliers | E52: 3 | F52: 40-60% | G52: Percent Range | H52: 40 | I52: 60 | J52: ≥ lower & < upper | K52: 20 | L52: =$K52/INDEX('Indicator Master'!$N$4:$N$24,MATCH($A52,'Indicator Master'!$A$4:$A$24,0))*'Risk Bands (Config)'!$B$5 -> 66.666667 | M52: =IF($K52=INDEX('Indicator Master'!$N$4:$N$24,MATCH($A52,'Indicator Master'!$A$4:$A$24,0)),1,0) -> 0 | O52: Elevated concern — concentration 40–60%; high dependence — supply-disruption risk. | P52: 1) Assess supply-continuity risk. 2) Reassess viability. 3) Flag to Credit. | Q52: Credit Committee / Zonal Credit | R52: =$A52&"|"&$K52 -> CM-012|20
A53: CM-012 | B53: Top-supplier purchase concentration % | C53: Credit Monitoring | D53: Dependence on few suppliers | E53: 4 | F53: >60% | G53: Percent Threshold | H53: 60 | J53: ≥ lower | K53: 30 | L53: =$K53/INDEX('Indicator Master'!$N$4:$N$24,MATCH($A53,'Indicator Master'!$A$4:$A$24,0))*'Risk Bands (Config)'!$B$5 -> 100 | M53: =IF($K53=INDEX('Indicator Master'!$N$4:$N$24,MATCH($A53,'Indicator Master'!$A$4:$A$24,0)),1,0) -> 1 | O53: Severe / critical — concentration above 60%; severe single-supplier dependence. | P53: 1) Stress-test loss of the key supplier. 2) Contingency/viability review. 3) Escalate to Credit. | Q53: Credit Head / Risk | R53: =$A53&"|"&$K53 -> CM-012|30
A54: CM-013 | B54: Sector stress classification x exposure | C54: Credit Monitoring | D54: Sector-level demand decline or margin pressure | E54: 1 | F54: Low exposure | G54: Ordinal Classification | J54: category | K54: 0 | L54: =$K54/INDEX('Indicator Master'!$N$4:$N$24,MATCH($A54,'Indicator Master'!$A$4:$A$24,0))*'Risk Bands (Config)'!$B$5 -> 0 | M54: =IF($K54=INDEX('Indicator Master'!$N$4:$N$24,MATCH($A54,'Indicator Master'!$A$4:$A$24,0)),1,0) -> 0 | O54: Normal — low exposure to sector stress; benign. | P54: No remedial action required. Continue routine monitoring at the standard review cycle and record the reading. | Q54: RM (routine) | R54: =$A54&"|"&$K54 -> CM-013|0
A55: CM-013 | B55: Sector stress classification x exposure | C55: Credit Monitoring | D55: Sector-level demand decline or margin pressure | E55: 2 | F55: moderate exposure/stress | G55: Ordinal Classification | J55: category | K55: 10 | L55: =$K55/INDEX('Indicator Master'!$N$4:$N$24,MATCH($A55,'Indicator Master'!$A$4:$A$24,0))*'Risk Bands (Config)'!$B$5 -> 28.571429 | M55: =IF($K55=INDEX('Indicator Master'!$N$4:$N$24,MATCH($A55,'Indicator Master'!$A$4:$A$24,0)),1,0) -> 0 | O55: Early warning — moderate sector exposure/stress; monitor headwinds. | P55: 1) Note the sector outlook. 2) Assess the borrower's relative position. 3) Monitor. | Q55: Relationship Manager (Branch) | R55: =$A55&"|"&$K55 -> CM-013|10
A56: CM-013 | B56: Sector stress classification x exposure | C56: Credit Monitoring | D56: Sector-level demand decline or margin pressure | E56: 3 | F56: high stress | G56: Ordinal Classification | J56: category | K56: 20 | L56: =$K56/INDEX('Indicator Master'!$N$4:$N$24,MATCH($A56,'Indicator Master'!$A$4:$A$24,0))*'Risk Bands (Config)'!$B$5 -> 57.142857 | M56: =IF($K56=INDEX('Indicator Master'!$N$4:$N$24,MATCH($A56,'Indicator Master'!$A$4:$A$24,0)),1,0) -> 0 | O56: Elevated concern — high sector stress affecting the borrower's segment. | P56: 1) Reassess sector exposure and pricing. 2) Enhanced monitoring. 3) Flag to Credit. | Q56: RM + Credit Analyst | R56: =$A56&"|"&$K56 -> CM-013|20
A57: CM-013 | B57: Sector stress classification x exposure | C57: Credit Monitoring | D57: Sector-level demand decline or margin pressure | E57: 4 | F57: severe disruption | G57: Ordinal Classification | J57: category | K57: 35 | L57: =$K57/INDEX('Indicator Master'!$N$4:$N$24,MATCH($A57,'Indicator Master'!$A$4:$A$24,0))*'Risk Bands (Config)'!$B$5 -> 100 | M57: =IF($K57=INDEX('Indicator Master'!$N$4:$N$24,MATCH($A57,'Indicator Master'!$A$4:$A$24,0)),1,0) -> 1 | O57: Severe / critical — severe sector disruption; a systemic threat to the business. | P57: 1) Reassess viability under sector stress. 2) De-risk exposure where feasible. 3) Escalate to Credit. | Q57: Credit Head / Risk | R57: =$A57&"|"&$K57 -> CM-013|35
A58: CM-014 | B58: Commodity exposure/stress classification | C58: Credit Monitoring | D58: Raw material cost increase or selling price fall | E58: 1 | F58: Low exposure | G58: Ordinal Classification | J58: category | K58: 0 | L58: =$K58/INDEX('Indicator Master'!$N$4:$N$24,MATCH($A58,'Indicator Master'!$A$4:$A$24,0))*'Risk Bands (Config)'!$B$5 -> 0 | M58: =IF($K58=INDEX('Indicator Master'!$N$4:$N$24,MATCH($A58,'Indicator Master'!$A$4:$A$24,0)),1,0) -> 0 | O58: Normal — low commodity-price exposure. | P58: No remedial action required. Continue routine monitoring at the standard review cycle and record the reading. | Q58: RM (routine) | R58: =$A58&"|"&$K58 -> CM-014|0
A59: CM-014 | B59: Commodity exposure/stress classification | C59: Credit Monitoring | D59: Raw material cost increase or selling price fall | E59: 2 | F59: moderate exposure/stress | G59: Ordinal Classification | J59: category | K59: 10 | L59: =$K59/INDEX('Indicator Master'!$N$4:$N$24,MATCH($A59,'Indicator Master'!$A$4:$A$24,0))*'Risk Bands (Config)'!$B$5 -> 28.571429 | M59: =IF($K59=INDEX('Indicator Master'!$N$4:$N$24,MATCH($A59,'Indicator Master'!$A$4:$A$24,0)),1,0) -> 0 | O59: Early warning — moderate commodity exposure; margin sensitivity. | P59: 1) Assess the pass-through ability. 2) Encourage hedging. 3) Monitor margins. | Q59: Relationship Manager (Branch) | R59: =$A59&"|"&$K59 -> CM-014|10
A60: CM-014 | B60: Commodity exposure/stress classification | C60: Credit Monitoring | D60: Raw material cost increase or selling price fall | E60: 3 | F60: high stress | G60: Ordinal Classification | J60: category | K60: 20 | L60: =$K60/INDEX('Indicator Master'!$N$4:$N$24,MATCH($A60,'Indicator Master'!$A$4:$A$24,0))*'Risk Bands (Config)'!$B$5 -> 57.142857 | M60: =IF($K60=INDEX('Indicator Master'!$N$4:$N$24,MATCH($A60,'Indicator Master'!$A$4:$A$24,0)),1,0) -> 0 | O60: Elevated concern — high commodity stress squeezing margins. | P60: 1) Reassess margins; stipulate hedging where feasible. 2) Enhanced monitoring. 3) Flag to Credit. | Q60: RM + Credit Analyst | R60: =$A60&"|"&$K60 -> CM-014|20
A61: CM-014 | B61: Commodity exposure/stress classification | C61: Credit Monitoring | D61: Raw material cost increase or selling price fall | E61: 4 | F61: severe disruption | G61: Ordinal Classification | J61: category | K61: 35 | L61: =$K61/INDEX('Indicator Master'!$N$4:$N$24,MATCH($A61,'Indicator Master'!$A$4:$A$24,0))*'Risk Bands (Config)'!$B$5 -> 100 | M61: =IF($K61=INDEX('Indicator Master'!$N$4:$N$24,MATCH($A61,'Indicator Master'!$A$4:$A$24,0)),1,0) -> 1 | O61: Severe / critical — severe commodity shock; margins/viability threatened. | P61: 1) Viability review under the commodity shock. 2) Corrective plan. 3) Escalate to Credit. | Q61: Credit Head / Risk | R61: =$A61&"|"&$K61 -> CM-014|35
A62: CM-015 | B62: Geopolitical exposure classification | C62: Credit Monitoring | D62: Exports/imports to conflict-prone countries | E62: 1 | F62: Low exposure | G62: Ordinal Classification | J62: category | K62: 0 | L62: =$K62/INDEX('Indicator Master'!$N$4:$N$24,MATCH($A62,'Indicator Master'!$A$4:$A$24,0))*'Risk Bands (Config)'!$B$5 -> 0 | M62: =IF($K62=INDEX('Indicator Master'!$N$4:$N$24,MATCH($A62,'Indicator Master'!$A$4:$A$24,0)),1,0) -> 0 | O62: Normal — low geopolitical/cross-border exposure. | P62: No remedial action required. Continue routine monitoring at the standard review cycle and record the reading. | Q62: RM (routine) | R62: =$A62&"|"&$K62 -> CM-015|0
A63: CM-015 | B63: Geopolitical exposure classification | C63: Credit Monitoring | D63: Exports/imports to conflict-prone countries | E63: 2 | F63: moderate exposure/stress | G63: Ordinal Classification | J63: category | K63: 10 | L63: =$K63/INDEX('Indicator Master'!$N$4:$N$24,MATCH($A63,'Indicator Master'!$A$4:$A$24,0))*'Risk Bands (Config)'!$B$5 -> 28.571429 | M63: =IF($K63=INDEX('Indicator Master'!$N$4:$N$24,MATCH($A63,'Indicator Master'!$A$4:$A$24,0)),1,0) -> 0 | O63: Early warning — moderate exposure to an affected geography. | P63: 1) Map the exposure to the affected geography. 2) Assess receivables/supply risk. 3) Monitor. | Q63: Relationship Manager (Branch) | R63: =$A63&"|"&$K63 -> CM-015|10
A64: CM-015 | B64: Geopolitical exposure classification | C64: Credit Monitoring | D64: Exports/imports to conflict-prone countries | E64: 3 | F64: high stress | G64: Ordinal Classification | J64: category | K64: 20 | L64: =$K64/INDEX('Indicator Master'!$N$4:$N$24,MATCH($A64,'Indicator Master'!$A$4:$A$24,0))*'Risk Bands (Config)'!$B$5 -> 57.142857 | M64: =IF($K64=INDEX('Indicator Master'!$N$4:$N$24,MATCH($A64,'Indicator Master'!$A$4:$A$24,0)),1,0) -> 0 | O64: Elevated concern — high geopolitical exposure disrupting trade/receivables. | P64: 1) Reassess exposure; seek ECGC cover / re-routing. 2) Enhanced monitoring. 3) Flag to Credit. | Q64: RM + Credit Analyst | R64: =$A64&"|"&$K64 -> CM-015|20
A65: CM-015 | B65: Geopolitical exposure classification | C65: Credit Monitoring | D65: Exports/imports to conflict-prone countries | E65: 4 | F65: severe disruption | G65: Ordinal Classification | J65: category | K65: 35 | L65: =$K65/INDEX('Indicator Master'!$N$4:$N$24,MATCH($A65,'Indicator Master'!$A$4:$A$24,0))*'Risk Bands (Config)'!$B$5 -> 100 | M65: =IF($K65=INDEX('Indicator Master'!$N$4:$N$24,MATCH($A65,'Indicator Master'!$A$4:$A$24,0)),1,0) -> 1 | O65: Severe / critical — severe disruption from geopolitical events. | P65: 1) Contingency/viability review. 2) Protect the bank's position. 3) Escalate to Credit. | Q65: Credit Head / Risk | R65: =$A65&"|"&$K65 -> CM-015|35
A66: CM-016 | B66: Project schedule variance % | C66: Credit Monitoring | D66: Time overrun in project loans | E66: 1 | F66: On track | G66: Percent Threshold | I66: 0 | J66: ≤ upper | K66: 0 | L66: =$K66/INDEX('Indicator Master'!$N$4:$N$24,MATCH($A66,'Indicator Master'!$A$4:$A$24,0))*'Risk Bands (Config)'!$B$5 -> 0 | M66: =IF($K66=INDEX('Indicator Master'!$N$4:$N$24,MATCH($A66,'Indicator Master'!$A$4:$A$24,0)),1,0) -> 0 | O66: Normal — project on schedule; no cost/time overrun. | P66: No remedial action required. Continue routine monitoring at the standard review cycle and record the reading. | Q66: RM (routine) | R66: =$A66&"|"&$K66 -> CM-016|0
A67: CM-016 | B67: Project schedule variance % | C67: Credit Monitoring | D67: Time overrun in project loans | E67: 2 | F67: delay up to 10% | G67: Percent Range | H67: 0 | I67: 10 | J67: > lower & ≤ upper | K67: 10 | L67: =$K67/INDEX('Indicator Master'!$N$4:$N$24,MATCH($A67,'Indicator Master'!$A$4:$A$24,0))*'Risk Bands (Config)'!$B$5 -> 25 | M67: =IF($K67=INDEX('Indicator Master'!$N$4:$N$24,MATCH($A67,'Indicator Master'!$A$4:$A$24,0)),1,0) -> 0 | O67: Early warning — up to 10% delay/overrun; minor slippage. | P67: 1) Review the revised schedule. 2) Confirm funding for the small overrun. 3) Monitor milestones. | Q67: Relationship Manager (Branch) | R67: =$A67&"|"&$K67 -> CM-016|10
A68: CM-016 | B68: Project schedule variance % | C68: Credit Monitoring | D68: Time overrun in project loans | E68: 3 | F68: 10-25% | G68: Percent Range | H68: 10 | I68: 25 | J68: > lower & ≤ upper | K68: 25 | L68: =$K68/INDEX('Indicator Master'!$N$4:$N$24,MATCH($A68,'Indicator Master'!$A$4:$A$24,0))*'Risk Bands (Config)'!$B$5 -> 62.5 | M68: =IF($K68=INDEX('Indicator Master'!$N$4:$N$24,MATCH($A68,'Indicator Master'!$A$4:$A$24,0)),1,0) -> 0 | O68: Elevated concern — 10–25% overrun; material schedule/cost slippage — DCCO risk. | P68: 1) Reassess cost and means-of-finance. 2) Assess the DCCO impact. 3) Flag to Credit. | Q68: Credit Committee / Zonal Credit | R68: =$A68&"|"&$K68 -> CM-016|25
A69: CM-016 | B69: Project schedule variance % | C69: Credit Monitoring | D69: Time overrun in project loans | E69: 4 | F69: >25% or stopped | G69: Percent Threshold | H69: 25 | J69: > lower (or project stopped) | K69: 40 | L69: =$K69/INDEX('Indicator Master'!$N$4:$N$24,MATCH($A69,'Indicator Master'!$A$4:$A$24,0))*'Risk Bands (Config)'!$B$5 -> 100 | M69: =IF($K69=INDEX('Indicator Master'!$N$4:$N$24,MATCH($A69,'Indicator Master'!$A$4:$A$24,0)),1,0) -> 1 | O69: Severe / critical — >25% overrun or the project has stopped; severe — viability/DCCO threat. | P69: 1) DCCO / restructuring assessment; tie up the funding gap. 2) Provisioning review. 3) Escalate to Credit. | Q69: Credit Head / Risk | R69: =$A69&"|"&$K69 -> CM-016|40
A70: CM-017 | B70: Project cost variance % | C70: Credit Monitoring | D70: Actual cost higher than original estimate | E70: 1 | F70: On track | G70: Percent Threshold | I70: 0 | J70: ≤ upper | K70: 0 | L70: =$K70/INDEX('Indicator Master'!$N$4:$N$24,MATCH($A70,'Indicator Master'!$A$4:$A$24,0))*'Risk Bands (Config)'!$B$5 -> 0 | M70: =IF($K70=INDEX('Indicator Master'!$N$4:$N$24,MATCH($A70,'Indicator Master'!$A$4:$A$24,0)),1,0) -> 0 | O70: Normal — project cost within estimate. | P70: No remedial action required. Continue routine monitoring at the standard review cycle and record the reading. | Q70: RM (routine) | R70: =$A70&"|"&$K70 -> CM-017|0
A71: CM-017 | B71: Project cost variance % | C71: Credit Monitoring | D71: Actual cost higher than original estimate | E71: 2 | F71: cost overrun up to 10% | G71: Percent Range | H71: 0 | I71: 10 | J71: > lower & ≤ upper | K71: 10 | L71: =$K71/INDEX('Indicator Master'!$N$4:$N$24,MATCH($A71,'Indicator Master'!$A$4:$A$24,0))*'Risk Bands (Config)'!$B$5 -> 25 | M71: =IF($K71=INDEX('Indicator Master'!$N$4:$N$24,MATCH($A71,'Indicator Master'!$A$4:$A$24,0)),1,0) -> 0 | O71: Early warning — cost overrun up to 10%; minor and fundable. | P71: 1) Confirm the overrun and the funding tie-up. 2) Monitor. | Q71: Relationship Manager (Branch) | R71: =$A71&"|"&$K71 -> CM-017|10
A72: CM-017 | B72: Project cost variance % | C72: Credit Monitoring | D72: Actual cost higher than original estimate | E72: 3 | F72: 10-25% | G72: Percent Range | H72: 10 | I72: 25 | J72: > lower & ≤ upper | K72: 25 | L72: =$K72/INDEX('Indicator Master'!$N$4:$N$24,MATCH($A72,'Indicator Master'!$A$4:$A$24,0))*'Risk Bands (Config)'!$B$5 -> 62.5 | M72: =IF($K72=INDEX('Indicator Master'!$N$4:$N$24,MATCH($A72,'Indicator Master'!$A$4:$A$24,0)),1,0) -> 0 | O72: Elevated concern — 10–25% cost overrun; a funding gap is opening. | P72: 1) Assess additional means-of-finance / promoter contribution. 2) Reassess viability. 3) Flag to Credit. | Q72: Credit Committee / Zonal Credit | R72: =$A72&"|"&$K72 -> CM-017|25
A73: CM-017 | B73: Project cost variance % | C73: Credit Monitoring | D73: Actual cost higher than original estimate | E73: 4 | F73: >25% or stopped | G73: Percent Threshold | H73: 25 | J73: > lower (or project stopped) | K73: 40 | L73: =$K73/INDEX('Indicator Master'!$N$4:$N$24,MATCH($A73,'Indicator Master'!$A$4:$A$24,0))*'Risk Bands (Config)'!$B$5 -> 100 | M73: =IF($K73=INDEX('Indicator Master'!$N$4:$N$24,MATCH($A73,'Indicator Master'!$A$4:$A$24,0)),1,0) -> 1 | O73: Severe / critical — >25% overrun or stalled; severe funding-gap/viability risk. | P73: 1) Tie up the funding gap; viability/restructuring review. 2) Provisioning review. 3) Escalate to Credit. | Q73: Credit Head / Risk | R73: =$A73&"|"&$K73 -> CM-017|40
A74: CM-018 | B74: Plant Shutdown | C74: Credit Monitoring | D74: Occurrence, duration and extent of plant shutdown | E74: 1 | F74: No shutdown | G74: Days Exact | H74: 0 | I74: 0 | J74: exactly = value | K74: 0 | L74: =$K74/INDEX('Indicator Master'!$N$4:$N$24,MATCH($A74,'Indicator Master'!$A$4:$A$24,0))*'Risk Bands (Config)'!$B$5 -> 0 | M74: =IF($K74=INDEX('Indicator Master'!$N$4:$N$24,MATCH($A74,'Indicator Master'!$A$4:$A$24,0)),1,0) -> 0 | O74: Normal — plant operating normally; no shutdown. | P74: No remedial action required. Continue routine monitoring at the standard review cycle and record the reading. | Q74: RM (routine) | R74: =$A74&"|"&$K74 -> CM-018|0
A75: CM-018 | B75: Plant Shutdown | C75: Credit Monitoring | D75: Occurrence, duration and extent of plant shutdown | E75: 2 | F75: Temporary shutdown | G75: Days Threshold | I75: 15 | J75: < upper (temporary) | K75: 10 | L75: =$K75/INDEX('Indicator Master'!$N$4:$N$24,MATCH($A75,'Indicator Master'!$A$4:$A$24,0))*'Risk Bands (Config)'!$B$5 -> 33.333333 | M75: =IF($K75=INDEX('Indicator Master'!$N$4:$N$24,MATCH($A75,'Indicator Master'!$A$4:$A$24,0)),1,0) -> 0 | O75: Early warning — a temporary/short shutdown; limited impact. | P75: 1) Ascertain the reason and expected restart. 2) Assess the limited impact. 3) Monitor. | Q75: RM + Credit Analyst | R75: =$A75&"|"&$K75 -> CM-018|10
A76: CM-018 | B76: Plant Shutdown | C76: Credit Monitoring | D76: Occurrence, duration and extent of plant shutdown | E76: 3 | F76: Shutdown >15 days | G76: Days Range | H76: 15 | I76: 30 | J76: > lower & ≤ upper | K76: 20 | L76: =$K76/INDEX('Indicator Master'!$N$4:$N$24,MATCH($A76,'Indicator Master'!$A$4:$A$24,0))*'Risk Bands (Config)'!$B$5 -> 66.666667 | M76: =IF($K76=INDEX('Indicator Master'!$N$4:$N$24,MATCH($A76,'Indicator Master'!$A$4:$A$24,0)),1,0) -> 0 | O76: Elevated concern — shutdown exceeding 15 days; material production/cash-flow loss. | P76: 1) Assess the cash-flow/production impact. 2) Engage the borrower on restart. 3) Flag to Credit. | Q76: Credit Committee / Zonal Credit | R76: =$A76&"|"&$K76 -> CM-018|20
A77: CM-018 | B77: Plant Shutdown | C77: Credit Monitoring | D77: Occurrence, duration and extent of plant shutdown | E77: 4 | F77: Shutdown >30 days / prolonged shutdown | G77: Days Threshold | H77: 30 | J77: > lower | K77: 30 | L77: =$K77/INDEX('Indicator Master'!$N$4:$N$24,MATCH($A77,'Indicator Master'!$A$4:$A$24,0))*'Risk Bands (Config)'!$B$5 -> 100 | M77: =IF($K77=INDEX('Indicator Master'!$N$4:$N$24,MATCH($A77,'Indicator Master'!$A$4:$A$24,0)),1,0) -> 1 | O77: Severe / critical — shutdown over 30 days or prolonged; severe revenue disruption. | P77: 1) Reassess viability given prolonged closure. 2) Protect security. 3) Escalate to Credit. | Q77: Credit Head / Risk | R77: =$A77&"|"&$K77 -> CM-018|30
A78: CM-019 | B78: Cyber/operational disruption classification | C78: Credit Monitoring | D78: System outage, ransomware, data breach | E78: 1 | F78: No incident | G78: Ordinal Classification | J78: category | K78: 0 | L78: =$K78/INDEX('Indicator Master'!$N$4:$N$24,MATCH($A78,'Indicator Master'!$A$4:$A$24,0))*'Risk Bands (Config)'!$B$5 -> 0 | M78: =IF($K78=INDEX('Indicator Master'!$N$4:$N$24,MATCH($A78,'Indicator Master'!$A$4:$A$24,0)),1,0) -> 0 | O78: Normal — no cyber/operational incident. | P78: No remedial action required. Continue routine monitoring at the standard review cycle and record the reading. | Q78: RM (routine) | R78: =$A78&"|"&$K78 -> CM-019|0
A79: CM-019 | B79: Cyber/operational disruption classification | C79: Credit Monitoring | D79: System outage, ransomware, data breach | E79: 2 | F79: minor incident | G79: Ordinal Classification | J79: category | K79: 10 | L79: =$K79/INDEX('Indicator Master'!$N$4:$N$24,MATCH($A79,'Indicator Master'!$A$4:$A$24,0))*'Risk Bands (Config)'!$B$5 -> 25 | M79: =IF($K79=INDEX('Indicator Master'!$N$4:$N$24,MATCH($A79,'Indicator Master'!$A$4:$A$24,0)),1,0) -> 0 | O79: Early warning — a minor incident; limited, contained impact. | P79: 1) Ascertain the scope. 2) Confirm recovery. 3) Monitor. | Q79: Relationship Manager (Branch) | R79: =$A79&"|"&$K79 -> CM-019|10
A80: CM-019 | B80: Cyber/operational disruption classification | C80: Credit Monitoring | D80: System outage, ransomware, data breach | E80: 3 | F80: major disruption | G80: Ordinal Classification | J80: category | K80: 25 | L80: =$K80/INDEX('Indicator Master'!$N$4:$N$24,MATCH($A80,'Indicator Master'!$A$4:$A$24,0))*'Risk Bands (Config)'!$B$5 -> 62.5 | M80: =IF($K80=INDEX('Indicator Master'!$N$4:$N$24,MATCH($A80,'Indicator Master'!$A$4:$A$24,0)),1,0) -> 0 | O80: Elevated concern — a major disruption to operations. | P80: 1) Assess the operational/financial impact. 2) Reassess resilience. 3) Flag to Credit. | Q80: Credit Committee / Zonal Credit | R80: =$A80&"|"&$K80 -> CM-019|25
A81: CM-019 | B81: Cyber/operational disruption classification | C81: Credit Monitoring | D81: System outage, ransomware, data breach | E81: 4 | F81: prolonged outage/data loss | G81: Ordinal Classification | J81: category | K81: 40 | L81: =$K81/INDEX('Indicator Master'!$N$4:$N$24,MATCH($A81,'Indicator Master'!$A$4:$A$24,0))*'Risk Bands (Config)'!$B$5 -> 100 | M81: =IF($K81=INDEX('Indicator Master'!$N$4:$N$24,MATCH($A81,'Indicator Master'!$A$4:$A$24,0)),1,0) -> 1 | O81: Severe / critical — a prolonged outage or data loss; severe continuity risk. | P81: 1) Continuity/viability review. 2) Protect the bank's position. 3) Escalate to Credit. | Q81: Credit Head / Risk | R81: =$A81&"|"&$K81 -> CM-019|40
A82: CM-020 | B82: End-use compliance status | C82: Credit Monitoring | D82: End-use certificate not submitted or mismatch found | E82: 1 | F82: Compliant | G82: Ordinal Classification | J82: category | K82: 0 | L82: =$K82/INDEX('Indicator Master'!$N$4:$N$24,MATCH($A82,'Indicator Master'!$A$4:$A$24,0))*'Risk Bands (Config)'!$B$5 -> 0 | M82: =IF($K82=INDEX('Indicator Master'!$N$4:$N$24,MATCH($A82,'Indicator Master'!$A$4:$A$24,0)),1,0) -> 0 | O82: Normal — funds used for the sanctioned purpose; compliant. | P82: No remedial action required. Continue routine monitoring at the standard review cycle and record the reading. | Q82: RM (routine) | R82: =$A82&"|"&$K82 -> CM-020|0
A83: CM-020 | B83: End-use compliance status | C83: Credit Monitoring | D83: End-use certificate not submitted or mismatch found | E83: 2 | F83: delayed certificate | G83: Ordinal Classification | J83: category | K83: 10 | L83: =$K83/INDEX('Indicator Master'!$N$4:$N$24,MATCH($A83,'Indicator Master'!$A$4:$A$24,0))*'Risk Bands (Config)'!$B$5 -> 20 | M83: =IF($K83=INDEX('Indicator Master'!$N$4:$N$24,MATCH($A83,'Indicator Master'!$A$4:$A$24,0)),1,0) -> 0 | O83: Early warning — end-use certificate delayed; verification pending. | P83: 1) Follow up for the CA end-use certificate. 2) Verify utilisation. 3) Monitor. | Q83: Relationship Manager (Branch) | R83: =$A83&"|"&$K83 -> CM-020|10
A84: CM-020 | B84: End-use compliance status | C84: Credit Monitoring | D84: End-use certificate not submitted or mismatch found | E84: 3 | F84: mismatch | G84: Ordinal Classification | J84: category | K84: 25 | L84: =$K84/INDEX('Indicator Master'!$N$4:$N$24,MATCH($A84,'Indicator Master'!$A$4:$A$24,0))*'Risk Bands (Config)'!$B$5 -> 50 | M84: =IF($K84=INDEX('Indicator Master'!$N$4:$N$24,MATCH($A84,'Indicator Master'!$A$4:$A$24,0)),1,0) -> 0 | O84: Elevated concern — an end-use mismatch; funds partly used off-purpose. | P84: 1) Commission an end-use audit. 2) Tighten disbursement; caution the borrower. 3) Flag to Credit. | Q84: RM + Credit Analyst | R84: =$A84&"|"&$K84 -> CM-020|25
A85: CM-020 | B85: End-use compliance status | C85: Credit Monitoring | D85: End-use certificate not submitted or mismatch found | E85: 4 | F85: misuse confirmed | G85: Ordinal Classification | J85: category | K85: 50 | L85: =$K85/INDEX('Indicator Master'!$N$4:$N$24,MATCH($A85,'Indicator Master'!$A$4:$A$24,0))*'Risk Bands (Config)'!$B$5 -> 100 | M85: =IF($K85=INDEX('Indicator Master'!$N$4:$N$24,MATCH($A85,'Indicator Master'!$A$4:$A$24,0)),1,0) -> 1 | O85: Severe / critical — confirmed misuse/diversion of loan funds. | P85: 1) Confirmed diversion — treat as a serious breach; forensic audit. 2) Freeze/recall as warranted. 3) Escalate to Credit Committee; legal action. | Q85: Credit Head / Risk / Fraud | R85: =$A85&"|"&$K85 -> CM-020|50
A86: CM-021 | B86: Count of overdue events (rolling 3-6m) | C86: Credit Monitoring | D86: Number of times borrower delays payment in last 3-6 months | E86: 1 | F86: 0 instances | G86: Count Exact | H86: 0 | I86: 0 | J86: exactly = value | K86: 0 | L86: =$K86/INDEX('Indicator Master'!$N$4:$N$24,MATCH($A86,'Indicator Master'!$A$4:$A$24,0))*'Risk Bands (Config)'!$B$5 -> 0 | M86: =IF($K86=INDEX('Indicator Master'!$N$4:$N$24,MATCH($A86,'Indicator Master'!$A$4:$A$24,0)),1,0) -> 0 | O86: Normal — no overdue events in the window; clean conduct. | P86: No remedial action required. Continue routine monitoring at the standard review cycle and record the reading. | Q86: RM (routine) | R86: =$A86&"|"&$K86 -> CM-021|0
A87: CM-021 | B87: Count of overdue events (rolling 3-6m) | C87: Credit Monitoring | D87: Number of times borrower delays payment in last 3-6 months | E87: 2 | F87: 1 instance | G87: Count Exact | H87: 1 | I87: 1 | J87: exactly = value | K87: 5 | L87: =$K87/INDEX('Indicator Master'!$N$4:$N$24,MATCH($A87,'Indicator Master'!$A$4:$A$24,0))*'Risk Bands (Config)'!$B$5 -> 20 | M87: =IF($K87=INDEX('Indicator Master'!$N$4:$N$24,MATCH($A87,'Indicator Master'!$A$4:$A$24,0)),1,0) -> 0 | O87: Early warning — one overdue event; an isolated slip. | P87: 1) Note the event and reason. 2) Caution informally. 3) Watch the next cycle. | Q87: Relationship Manager (Branch) | R87: =$A87&"|"&$K87 -> CM-021|5
A88: CM-021 | B88: Count of overdue events (rolling 3-6m) | C88: Credit Monitoring | D88: Number of times borrower delays payment in last 3-6 months | E88: 3 | F88: 2 instances | G88: Count Exact | H88: 2 | I88: 2 | J88: exactly = value | K88: 15 | L88: =$K88/INDEX('Indicator Master'!$N$4:$N$24,MATCH($A88,'Indicator Master'!$A$4:$A$24,0))*'Risk Bands (Config)'!$B$5 -> 60 | M88: =IF($K88=INDEX('Indicator Master'!$N$4:$N$24,MATCH($A88,'Indicator Master'!$A$4:$A$24,0)),1,0) -> 0 | O88: Elevated concern — two overdue events; a pattern forming. | P88: 1) Obtain a written explanation. 2) Enforce due-date discipline. 3) Place on the watch-list. | Q88: RM + Credit Analyst | R88: =$A88&"|"&$K88 -> CM-021|15
A89: CM-021 | B89: Count of overdue events (rolling 3-6m) | C89: Credit Monitoring | D89: Number of times borrower delays payment in last 3-6 months | E89: 4 | F89: 3+ instances | G89: Count Threshold | H89: 3 | J89: ≥ lower | K89: 25 | L89: =$K89/INDEX('Indicator Master'!$N$4:$N$24,MATCH($A89,'Indicator Master'!$A$4:$A$24,0))*'Risk Bands (Config)'!$B$5 -> 100 | M89: =IF($K89=INDEX('Indicator Master'!$N$4:$N$24,MATCH($A89,'Indicator Master'!$A$4:$A$24,0)),1,0) -> 1 | O89: Severe / critical — three or more overdue events; persistent irregularity / stress. | P89: 1) Treat as incipient stress; SMA watch. 2) Corrective plan. 3) Escalate to Credit. | Q89: Credit Head / Risk | R89: =$A89&"|"&$K89 -> CM-021|25

Sheet Overall Score Engine
A1: Overall Score Engine (Live Calculator)
A2: Yellow cells are inputs. Overall = average of normalised scores of applicable indicators with valid data (missing excluded, never zero). Credit Monitoring has no CRITICAL indicators, so no override applies.
A4: Borrower Name | B4: Acme Textiles Pvt Ltd
A5: Assessment Date | B5: 31-Aug-2026
A7: Total Indicators | B7: =COUNTA($A$23:$A$43) -> 21
A8: Applicable Indicators | B8: =COUNTIF($F$23:$F$43,"Y") -> 18 | C8: Indicators relevant to this borrower (N/A excluded).
A9: Scored (valid data) | B9: =SUM($J$23:$J$43) -> 17 | C9: Applicable AND data available AND a raw score entered.
A10: Missing Data (applicable) | B10: =COUNTIFS($F$23:$F$43,"Y",$G$23:$G$43,"N") -> 1 | C10: Applicable but no data — EXCLUDED from the average (not treated as zero).
A11: Not Applicable (N/A) | B11: =COUNTIF($F$23:$F$43,"N") -> 3
A12: Data Coverage % | B12: =IF(B8=0,0,B9/B8*100) -> 94.444444 | C12: Reported separately; does NOT affect the Overall Score.
A13: Sum of Normalised (scored) | B13: =SUM($K$23:$K$43) -> 473.09524
A14: Overall EWS Score | B14: =IF(B9=0,0,B13/B9) -> 27.829132 | C14: Average of normalised scores of applicable indicators with valid data.
A15: Numeric Risk Band | B15: =INDEX('Risk Bands (Config)'!$A$9:$A$13,MATCH(B14,'Risk Bands (Config)'!$D$9:$D$13,1)) -> Yellow | C15: Band implied by the Overall Score alone (before critical override).
A16: Critical Override Triggered? | B16: =IF(SUM($L$23:$L$43)>0,"YES","NO") -> NO | C16: YES if any CRITICAL indicator reaches the override trigger ('6. Risk Bands (Config)'!$B$6).
A17: Critical Indicators Fired | B17: None
A18: FINAL STATUS | B18: =IF(B16="YES","CRITICAL (Override)",IF(B12<'Risk Bands (Config)'!$B$16,"INSUFFICIENT DATA (band: "&B15&")",B15)) -> Yellow
A19: Final Interpretation | B19: =IF(B16="YES",INDEX('Risk Bands (Config)'!$E$9:$E$13,5),IF(B12<'Risk Bands (Config)'!$B$16,"Low data coverage — treat score as low-confidence; obtain missing data before acting.",INDEX('Risk Bands (Config)'!$E$9:$E$13,MATCH(B14,'Risk Bands (Config)'!$D$9:$D$13,1)))) -> Early Deterioration / Monitor
A20: Traceability: FINAL STATUS ← Overall Score / Critical Override ← per-indicator Normalised ← Raw Score ← borrower Observed Value ← applicable threshold band.
A22: UID | B22: Indicator | C22: Module | D22: Critical | E22: Max Score | F22: Applicable (Y/N) | G22: Data Available (Y/N) | H22: Observed Value / Note | I22: Raw Score | J22: Scored Flag | K22: Normalised Score | L22: Critical Fire | M22: Crit Fire UID (helper) | N22: What it signals & likely drivers | O22: Remedial action plan (step-by-step) | P22: Primary owner
A23: CM-001 | B23: DPD (days past due) | C23: Credit Monitoring | D23: =INDEX('Indicator Master'!$F$4:$F$24,MATCH($A23,'Indicator Master'!$A$4:$A$24,0)) -> No | E23: =INDEX('Indicator Master'!$N$4:$N$24,MATCH($A23,'Indicator Master'!$A$4:$A$24,0)) -> 40 | F23: Y | G23: Y | H23: One instalment ~12 days late, since regularised → band '1-30 DPD' | I23: 10 | J23: =IF(AND($F23="Y",$G23="Y",ISNUMBER($I23)),1,0) -> 1 | K23: =IF($J23=1,$I23/$E23*'Risk Bands (Config)'!$B$5,"") -> 25 | L23: =IF(AND($D23="Yes",$J23=1,$I23/$E23*'Risk Bands (Config)'!$B$5>='Risk Bands (Config)'!$B$6),1,0) -> 0 | M23: =IF($L23=1,$A23,"") | N23: =IF($J23=1,IFERROR(INDEX('Scoring Engine (Rules)'!$O$5:$O$89,MATCH($A23&"|"&$I23,'Scoring Engine (Rules)'!$R$5:$R$89,0)),""),"") -> Early warning — 1–30 days past due (SMA-0); a short cash-flow slip. | O23: =IF($J23=1,IFERROR(INDEX('Scoring Engine (Rules)'!$P$5:$P$89,MATCH($A23&"|"&$I23,'Scoring Engine (Rules)'!$R$5:$R$89,0)),""),"") -> 1) Contact the borrower; obtain the reason and a dated payment commitment. 2) Tag SMA-0. 3) Watch daily. | P23: =IF($J23=1,IFERROR(INDEX('Scoring Engine (Rules)'!$Q$5:$Q$89,MATCH($A23&"|"&$I23,'Scoring Engine (Rules)'!$R$5:$R$89,0)),""),"") -> Relationship Manager (Branch)
A24: CM-002 | B24: Excess over DP/limit % | C24: Credit Monitoring | D24: =INDEX('Indicator Master'!$F$4:$F$24,MATCH($A24,'Indicator Master'!$A$4:$A$24,0)) -> No | E24: =INDEX('Indicator Master'!$N$4:$N$24,MATCH($A24,'Indicator Master'!$A$4:$A$24,0)) -> 30 | F24: Y | G24: Y | H24: CC drawn ~4% over DP for a few days, since corrected → band 'Up to 5% breach' | I24: 10 | J24: =IF(AND($F24="Y",$G24="Y",ISNUMBER($I24)),1,0) -> 1 | K24: =IF($J24=1,$I24/$E24*'Risk Bands (Config)'!$B$5,"") -> 33.333333 | L24: =IF(AND($D24="Yes",$J24=1,$I24/$E24*'Risk Bands (Config)'!$B$5>='Risk Bands (Config)'!$B$6),1,0) -> 0 | M24: =IF($L24=1,$A24,"") | N24: =IF($J24=1,IFERROR(INDEX('Scoring Engine (Rules)'!$O$5:$O$89,MATCH($A24&"|"&$I24,'Scoring Engine (Rules)'!$R$5:$R$89,0)),""),"") -> Early warning — excess up to 5%; minor, likely a timing over-draw. | O24: =IF($J24=1,IFERROR(INDEX('Scoring Engine (Rules)'!$P$5:$P$89,MATCH($A24&"|"&$I24,'Scoring Engine (Rules)'!$R$5:$R$89,0)),""),"") -> 1) Regularise the excess promptly. 2) Ascertain the reason. 3) Allow no fresh excess. | P24: =IF($J24=1,IFERROR(INDEX('Scoring Engine (Rules)'!$Q$5:$Q$89,MATCH($A24&"|"&$I24,'Scoring Engine (Rules)'!$R$5:$R$89,0)),""),"") -> RM + Credit Analyst
A25: CM-003 | B25: GST turnover change % / vs bank credits | C25: Credit Monitoring | D25: =INDEX('Indicator Master'!$F$4:$F$24,MATCH($A25,'Indicator Master'!$A$4:$A$24,0)) -> No | E25: =INDEX('Indicator Master'!$N$4:$N$24,MATCH($A25,'Indicator Master'!$A$4:$A$24,0)) -> 35 | F25: Y | G25: Y | H25: GST turnover down ~30% vs prior period → band '20-40% decline' | I25: 20 | J25: =IF(AND($F25="Y",$G25="Y",ISNUMBER($I25)),1,0) -> 1 | K25: =IF($J25=1,$I25/$E25*'Risk Bands (Config)'!$B$5,"") -> 57.142857 | L25: =IF(AND($D25="Yes",$J25=1,$I25/$E25*'Risk Bands (Config)'!$B$5>='Risk Bands (Config)'!$B$6),1,0) -> 0 | M25: =IF($L25=1,$A25,"") | N25: =IF($J25=1,IFERROR(INDEX('Scoring Engine (Rules)'!$O$5:$O$89,MATCH($A25&"|"&$I25,'Scoring Engine (Rules)'!$R$5:$R$89,0)),""),"") -> Elevated concern — down 20–40%; material fall — demand loss or diversion of billing. | O25: =IF($J25=1,IFERROR(INDEX('Scoring Engine (Rules)'!$P$5:$P$89,MATCH($A25&"|"&$I25,'Scoring Engine (Rules)'!$R$5:$R$89,0)),""),"") -> 1) Reassess WC and projections. 2) Investigate under-reporting/diversion. 3) Enhanced monitoring; flag to Credit. | P25: =IF($J25=1,IFERROR(INDEX('Scoring Engine (Rules)'!$Q$5:$Q$89,MATCH($A25&"|"&$I25,'Scoring Engine (Rules)'!$R$5:$R$89,0)),""),"") -> RM + Credit Analyst
A26: CM-004 | B26: Cash Flow from Operations (sign / periods) | C26: Credit Monitoring | D26: =INDEX('Indicator Master'!$F$4:$F$24,MATCH($A26,'Indicator Master'!$A$4:$A$24,0)) -> No | E26: =INDEX('Indicator Master'!$N$4:$N$24,MATCH($A26,'Indicator Master'!$A$4:$A$24,0)) -> 40 | F26: Y | G26: Y | H26: One negative operating cash-flow quarter → band 'one negative period' | I26: 15 | J26: =IF(AND($F26="Y",$G26="Y",ISNUMBER($I26)),1,0) -> 1 | K26: =IF($J26=1,$I26/$E26*'Risk Bands (Config)'!$B$5,"") -> 37.5 | L26: =IF(AND($D26="Yes",$J26=1,$I26/$E26*'Risk Bands (Config)'!$B$5>='Risk Bands (Config)'!$B$6),1,0) -> 0 | M26: =IF($L26=1,$A26,"") | N26: =IF($J26=1,IFERROR(INDEX('Scoring Engine (Rules)'!$O$5:$O$89,MATCH($A26&"|"&$I26,'Scoring Engine (Rules)'!$R$5:$R$89,0)),""),"") -> Elevated concern — one negative CFO period; isolated — watch for persistence. | O26: =IF($J26=1,IFERROR(INDEX('Scoring Engine (Rules)'!$P$5:$P$89,MATCH($A26&"|"&$I26,'Scoring Engine (Rules)'!$R$5:$R$89,0)),""),"") -> 1) Analyse the CFO driver (WC swing vs loss). 2) Obtain an explanation. 3) Monitor next period. | P26: =IF($J26=1,IFERROR(INDEX('Scoring Engine (Rules)'!$Q$5:$Q$89,MATCH($A26&"|"&$I26,'Scoring Engine (Rules)'!$R$5:$R$89,0)),""),"") -> RM + Credit Analyst
A27: CM-005 | B27: Current Ratio | C27: Credit Monitoring | D27: =INDEX('Indicator Master'!$F$4:$F$24,MATCH($A27,'Indicator Master'!$A$4:$A$24,0)) -> No | E27: =INDEX('Indicator Master'!$N$4:$N$24,MATCH($A27,'Indicator Master'!$A$4:$A$24,0)) -> 35 | F27: Y | G27: Y | H27: Current ratio at 1.05 → band '1.00-1.09' | I27: 20 | J27: =IF(AND($F27="Y",$G27="Y",ISNUMBER($I27)),1,0) -> 1 | K27: =IF($J27=1,$I27/$E27*'Risk Bands (Config)'!$B$5,"") -> 57.142857 | L27: =IF(AND($D27="Yes",$J27=1,$I27/$E27*'Risk Bands (Config)'!$B$5>='Risk Bands (Config)'!$B$6),1,0) -> 0 | M27: =IF($L27=1,$A27,"") | N27: =IF($J27=1,IFERROR(INDEX('Scoring Engine (Rules)'!$O$5:$O$89,MATCH($A27&"|"&$I27,'Scoring Engine (Rules)'!$R$5:$R$89,0)),""),"") -> Elevated concern — current ratio 1.00–1.09; thin liquidity buffer. | O27: =IF($J27=1,IFERROR(INDEX('Scoring Engine (Rules)'!$P$5:$P$89,MATCH($A27&"|"&$I27,'Scoring Engine (Rules)'!$R$5:$R$89,0)),""),"") -> 1) Assess NWC adequacy; seek promoter infusion. 2) Enhanced monitoring. 3) Flag to Credit. | P27: =IF($J27=1,IFERROR(INDEX('Scoring Engine (Rules)'!$Q$5:$Q$89,MATCH($A27&"|"&$I27,'Scoring Engine (Rules)'!$R$5:$R$89,0)),""),"") -> RM + Credit Analyst
A28: CM-006 | B28: Audit opinion classification | C28: Credit Monitoring | D28: =INDEX('Indicator Master'!$F$4:$F$24,MATCH($A28,'Indicator Master'!$A$4:$A$24,0)) -> No | E28: =INDEX('Indicator Master'!$N$4:$N$24,MATCH($A28,'Indicator Master'!$A$4:$A$24,0)) -> 40 | F28: Y | G28: Y | H28: Clean audit opinion, no qualification → band 'No issue' | I28: 0 | J28: =IF(AND($F28="Y",$G28="Y",ISNUMBER($I28)),1,0) -> 1 | K28: =IF($J28=1,$I28/$E28*'Risk Bands (Config)'!$B$5,"") -> 0 | L28: =IF(AND($D28="Yes",$J28=1,$I28/$E28*'Risk Bands (Config)'!$B$5>='Risk Bands (Config)'!$B$6),1,0) -> 0 | M28: =IF($L28=1,$A28,"") | N28: =IF($J28=1,IFERROR(INDEX('Scoring Engine (Rules)'!$O$5:$O$89,MATCH($A28&"|"&$I28,'Scoring Engine (Rules)'!$R$5:$R$89,0)),""),"") -> Normal — clean audit opinion; reliable reporting. | O28: =IF($J28=1,IFERROR(INDEX('Scoring Engine (Rules)'!$P$5:$P$89,MATCH($A28&"|"&$I28,'Scoring Engine (Rules)'!$R$5:$R$89,0)),""),"") -> No remedial action required. Continue routine monitoring at the standard review cycle and record the reading. | P28: =IF($J28=1,IFERROR(INDEX('Scoring Engine (Rules)'!$Q$5:$Q$89,MATCH($A28&"|"&$I28,'Scoring Engine (Rules)'!$R$5:$R$89,0)),""),"") -> RM (routine)
A29: CM-007 | B29: NCLT/IBC admission status | C29: Credit Monitoring | D29: =INDEX('Indicator Master'!$F$4:$F$24,MATCH($A29,'Indicator Master'!$A$4:$A$24,0)) -> No | E29: =INDEX('Indicator Master'!$N$4:$N$24,MATCH($A29,'Indicator Master'!$A$4:$A$24,0)) -> 50 | F29: Y | G29: Y | H29: No insolvency or legal proceedings on record → band 'No case' | I29: 0 | J29: =IF(AND($F29="Y",$G29="Y",ISNUMBER($I29)),1,0) -> 1 | K29: =IF($J29=1,$I29/$E29*'Risk Bands (Config)'!$B$5,"") -> 0 | L29: =IF(AND($D29="Yes",$J29=1,$I29/$E29*'Risk Bands (Config)'!$B$5>='Risk Bands (Config)'!$B$6),1,0) -> 0 | M29: =IF($L29=1,$A29,"") | N29: =IF($J29=1,IFERROR(INDEX('Scoring Engine (Rules)'!$O$5:$O$89,MATCH($A29&"|"&$I29,'Scoring Engine (Rules)'!$R$5:$R$89,0)),""),"") -> Normal — no insolvency/legal proceedings; clean status. | O29: =IF($J29=1,IFERROR(INDEX('Scoring Engine (Rules)'!$P$5:$P$89,MATCH($A29&"|"&$I29,'Scoring Engine (Rules)'!$R$5:$R$89,0)),""),"") -> No remedial action required. Continue routine monitoring at the standard review cycle and record the reading. | P29: =IF($J29=1,IFERROR(INDEX('Scoring Engine (Rules)'!$Q$5:$Q$89,MATCH($A29&"|"&$I29,'Scoring Engine (Rules)'!$R$5:$R$89,0)),""),"") -> RM (routine)
A30: CM-008 | B30: Restructuring request status | C30: Credit Monitoring | D30: =INDEX('Indicator Master'!$F$4:$F$24,MATCH($A30,'Indicator Master'!$A$4:$A$24,0)) -> No | E30: =INDEX('Indicator Master'!$N$4:$N$24,MATCH($A30,'Indicator Master'!$A$4:$A$24,0)) -> 40 | F30: Y | G30: Y | H30: Informal moratorium request raised by the borrower → band 'informal request' | I30: 15 | J30: =IF(AND($F30="Y",$G30="Y",ISNUMBER($I30)),1,0) -> 1 | K30: =IF($J30=1,$I30/$E30*'Risk Bands (Config)'!$B$5,"") -> 37.5 | L30: =IF(AND($D30="Yes",$J30=1,$I30/$E30*'Risk Bands (Config)'!$B$5>='Risk Bands (Config)'!$B$6),1,0) -> 0 | M30: =IF($L30=1,$A30,"") | N30: =IF($J30=1,IFERROR(INDEX('Scoring Engine (Rules)'!$O$5:$O$89,MATCH($A30&"|"&$I30,'Scoring Engine (Rules)'!$R$5:$R$89,0)),""),"") -> Elevated concern — an informal restructuring/moratorium enquiry; early stress signal. | O30: =IF($J30=1,IFERROR(INDEX('Scoring Engine (Rules)'!$P$5:$P$89,MATCH($A30&"|"&$I30,'Scoring Engine (Rules)'!$R$5:$R$89,0)),""),"") -> 1) Obtain the rationale; assess genuine stress vs willful. 2) Seek cash-flow data. 3) Monitor. | P30: =IF($J30=1,IFERROR(INDEX('Scoring Engine (Rules)'!$Q$5:$Q$89,MATCH($A30&"|"&$I30,'Scoring Engine (Rules)'!$R$5:$R$89,0)),""),"") -> RM + Credit Analyst
A31: CM-009 | B31: Security/collateral cover ratio | C31: Credit Monitoring | D31: =INDEX('Indicator Master'!$F$4:$F$24,MATCH($A31,'Indicator Master'!$A$4:$A$24,0)) -> No | E31: =INDEX('Indicator Master'!$N$4:$N$24,MATCH($A31,'Indicator Master'!$A$4:$A$24,0)) -> 40 | F31: Y | G31: Y | H31: Minor collateral-cover shortfall pending revaluation → band 'minor shortfall/lapse' | I31: 15 | J31: =IF(AND($F31="Y",$G31="Y",ISNUMBER($I31)),1,0) -> 1 | K31: =IF($J31=1,$I31/$E31*'Risk Bands (Config)'!$B$5,"") -> 37.5 | L31: =IF(AND($D31="Yes",$J31=1,$I31/$E31*'Risk Bands (Config)'!$B$5>='Risk Bands (Config)'!$B$6),1,0) -> 0 | M31: =IF($L31=1,$A31,"") | N31: =IF($J31=1,IFERROR(INDEX('Scoring Engine (Rules)'!$O$5:$O$89,MATCH($A31&"|"&$I31,'Scoring Engine (Rules)'!$R$5:$R$89,0)),""),"") -> Elevated concern — a minor shortfall or lapse in cover; top-up needed. | O31: =IF($J31=1,IFERROR(INDEX('Scoring Engine (Rules)'!$P$5:$P$89,MATCH($A31&"|"&$I31,'Scoring Engine (Rules)'!$R$5:$R$89,0)),""),"") -> 1) Revalue security; seek a top-up. 2) Adjust DP to available cover. 3) Monitor to closure. | P31: =IF($J31=1,IFERROR(INDEX('Scoring Engine (Rules)'!$Q$5:$Q$89,MATCH($A31&"|"&$I31,'Scoring Engine (Rules)'!$R$5:$R$89,0)),""),"") -> RM + Credit Analyst
A32: CM-010 | B32: Insurance validity / days to expiry | C32: Credit Monitoring | D32: =INDEX('Indicator Master'!$F$4:$F$24,MATCH($A32,'Indicator Master'!$A$4:$A$24,0)) -> No | E32: =INDEX('Indicator Master'!$N$4:$N$24,MATCH($A32,'Indicator Master'!$A$4:$A$24,0)) -> 40 | F32: Y | G32: Y | H32: Stock insurance lapsed; renewal pending → band 'minor shortfall/lapse' | I32: 15 | J32: =IF(AND($F32="Y",$G32="Y",ISNUMBER($I32)),1,0) -> 1 | K32: =IF($J32=1,$I32/$E32*'Risk Bands (Config)'!$B$5,"") -> 37.5 | L32: =IF(AND($D32="Yes",$J32=1,$I32/$E32*'Risk Bands (Config)'!$B$5>='Risk Bands (Config)'!$B$6),1,0) -> 0 | M32: =IF($L32=1,$A32,"") | N32: =IF($J32=1,IFERROR(INDEX('Scoring Engine (Rules)'!$O$5:$O$89,MATCH($A32&"|"&$I32,'Scoring Engine (Rules)'!$R$5:$R$89,0)),""),"") -> Elevated concern — a minor lapse or approaching expiry; renewal needed. | O32: =IF($J32=1,IFERROR(INDEX('Scoring Engine (Rules)'!$P$5:$P$89,MATCH($A32&"|"&$I32,'Scoring Engine (Rules)'!$R$5:$R$89,0)),""),"") -> 1) Follow up for renewal with the bank clause; note the expiry. 2) Obtain the policy. 3) Monitor. | P32: =IF($J32=1,IFERROR(INDEX('Scoring Engine (Rules)'!$Q$5:$Q$89,MATCH($A32&"|"&$I32,'Scoring Engine (Rules)'!$R$5:$R$89,0)),""),"") -> RM + Credit Analyst
A33: CM-011 | B33: Top-customer revenue concentration % | C33: Credit Monitoring | D33: =INDEX('Indicator Master'!$F$4:$F$24,MATCH($A33,'Indicator Master'!$A$4:$A$24,0)) -> No | E33: =INDEX('Indicator Master'!$N$4:$N$24,MATCH($A33,'Indicator Master'!$A$4:$A$24,0)) -> 30 | F33: Y | G33: Y | H33: Top customer ~32% of revenue → band '25-40%' | I33: 10 | J33: =IF(AND($F33="Y",$G33="Y",ISNUMBER($I33)),1,0) -> 1 | K33: =IF($J33=1,$I33/$E33*'Risk Bands (Config)'!$B$5,"") -> 33.333333 | L33: =IF(AND($D33="Yes",$J33=1,$I33/$E33*'Risk Bands (Config)'!$B$5>='Risk Bands (Config)'!$B$6),1,0) -> 0 | M33: =IF($L33=1,$A33,"") | N33: =IF($J33=1,IFERROR(INDEX('Scoring Engine (Rules)'!$O$5:$O$89,MATCH($A33&"|"&$I33,'Scoring Engine (Rules)'!$R$5:$R$89,0)),""),"") -> Early warning — concentration 25–40%; moderate dependence on a key customer. | O33: =IF($J33=1,IFERROR(INDEX('Scoring Engine (Rules)'!$P$5:$P$89,MATCH($A33&"|"&$I33,'Scoring Engine (Rules)'!$R$5:$R$89,0)),""),"") -> 1) Review the customer mix. 2) Encourage diversification. 3) Monitor the key customer's health. | P33: =IF($J33=1,IFERROR(INDEX('Scoring Engine (Rules)'!$Q$5:$Q$89,MATCH($A33&"|"&$I33,'Scoring Engine (Rules)'!$R$5:$R$89,0)),""),"") -> RM + Credit Analyst
A34: CM-012 | B34: Top-supplier purchase concentration % | C34: Credit Monitoring | D34: =INDEX('Indicator Master'!$F$4:$F$24,MATCH($A34,'Indicator Master'!$A$4:$A$24,0)) -> No | E34: =INDEX('Indicator Master'!$N$4:$N$24,MATCH($A34,'Indicator Master'!$A$4:$A$24,0)) -> 30 | F34: Y | G34: Y | H34: Top supplier ~18% of purchases → band '<25% exposure' | I34: 0 | J34: =IF(AND($F34="Y",$G34="Y",ISNUMBER($I34)),1,0) -> 1 | K34: =IF($J34=1,$I34/$E34*'Risk Bands (Config)'!$B$5,"") -> 0 | L34: =IF(AND($D34="Yes",$J34=1,$I34/$E34*'Risk Bands (Config)'!$B$5>='Risk Bands (Config)'!$B$6),1,0) -> 0 | M34: =IF($L34=1,$A34,"") | N34: =IF($J34=1,IFERROR(INDEX('Scoring Engine (Rules)'!$O$5:$O$89,MATCH($A34&"|"&$I34,'Scoring Engine (Rules)'!$R$5:$R$89,0)),""),"") -> Normal — top-supplier concentration below 25%; diversified sourcing. | O34: =IF($J34=1,IFERROR(INDEX('Scoring Engine (Rules)'!$P$5:$P$89,MATCH($A34&"|"&$I34,'Scoring Engine (Rules)'!$R$5:$R$89,0)),""),"") -> No remedial action required. Continue routine monitoring at the standard review cycle and record the reading. | P34: =IF($J34=1,IFERROR(INDEX('Scoring Engine (Rules)'!$Q$5:$Q$89,MATCH($A34&"|"&$I34,'Scoring Engine (Rules)'!$R$5:$R$89,0)),""),"") -> RM (routine)
... A36: CM-014 | B36: Commodity exposure/stress classification | C36: Credit Monitoring | D36: =INDEX('Indicator Master'!$F$4:$F$24,MATCH($A36,'Indicator Master'!$A$4:$A$24,0)) -> No | E36: =INDEX('Indicator Master'!$N$4:$N$24,MATCH($A36,'Indicator Master'!$A$4:$A$24,0)) -> 35 | F36: Y | G36: Y | H36: Cotton-price volatility; moderate margin pressure → band 'moderate exposure/stress' | I36: 10 | J36: =IF(AND($F36="Y",$G36="Y",ISNUMBER($I36)),1,0) -> 1 | K36: =IF($J36=1,$I36/$E36*'Risk Bands (Config)'!$B$5,"") -> 28.571429 | L36: =IF(AND($D36="Yes",$J36=1,$I36/$E36*'Risk Bands (Config)'!$B$5>='Risk Bands (Config)'!$B$6),1,0) -> 0 | M36: =IF($L36=1,$A36,"") | N36: =IF($J36=1,IFERROR(INDEX('Scoring Engine (Rules)'!$O$5:$O$89,MATCH($A36&"|"&$I36,'Scoring Engine (Rules)'!$R$5:$R$89,0)),""),"") -> Early warning — moderate commodity exposure; margin sensitivity. | O36: =IF($J36=1,IFERROR(INDEX('Scoring Engine (Rules)'!$P$5:$P$89,MATCH($A36&"|"&$I36,'Scoring Engine (Rules)'!$R$5:$R$89,0)),""),"") -> 1) Assess the pass-through ability. 2) Encourage hedging. 3) Monitor margins. | P36: =IF($J36=1,IFERROR(INDEX('Scoring Engine (Rules)'!$Q$5:$Q$89,MATCH($A36&"|"&$I36,'Scoring Engine (Rules)'!$R$5:$R$89,0)),""),"") -> Relationship Manager (Branch)
A37: CM-015 | B37: Geopolitical exposure classification | C37: Credit Monitoring | D37: =INDEX('Indicator Master'!$F$4:$F$24,MATCH($A37,'Indicator Master'!$A$4:$A$24,0)) -> No | E37: =INDEX('Indicator Master'!$N$4:$N$24,MATCH($A37,'Indicator Master'!$A$4:$A$24,0)) -> 35 | F37: N | H37: Not applicable to this borrower (domestic operations only) | J37: =IF(AND($F37="Y",$G37="Y",ISNUMBER($I37)),1,0) -> 0 | K37: =IF($J37=1,$I37/$E37*'Risk Bands (Config)'!$B$5,"") | L37: =IF(AND($D37="Yes",$J37=1,$I37/$E37*'Risk Bands (Config)'!$B$5>='Risk Bands (Config)'!$B$6),1,0) -> 0 | M37: =IF($L37=1,$A37,"") | N37: =IF($J37=1,IFERROR(INDEX('Scoring Engine (Rules)'!$O$5:$O$89,MATCH($A37&"|"&$I37,'Scoring Engine (Rules)'!$R$5:$R$89,0)),""),"") | O37: =IF($J37=1,IFERROR(INDEX('Scoring Engine (Rules)'!$P$5:$P$89,MATCH($A37&"|"&$I37,'Scoring Engine (Rules)'!$R$5:$R$89,0)),""),"") | P37: =IF($J37=1,IFERROR(INDEX('Scoring Engine (Rules)'!$Q$5:$Q$89,MATCH($A37&"|"&$I37,'Scoring Engine (Rules)'!$R$5:$R$89,0)),""),"")
A38: CM-016 | B38: Project schedule variance % | C38: Credit Monitoring | D38: =INDEX('Indicator Master'!$F$4:$F$24,MATCH($A38,'Indicator Master'!$A$4:$A$24,0)) -> No | E38: =INDEX('Indicator Master'!$N$4:$N$24,MATCH($A38,'Indicator Master'!$A$4:$A$24,0)) -> 40 | F38: N | H38: Not applicable to this borrower (no project/term-loan under implementation) | J38: =IF(AND($F38="Y",$G38="Y",ISNUMBER($I38)),1,0) -> 0 | K38: =IF($J38=1,$I38/$E38*'Risk Bands (Config)'!$B$5,"") | L38: =IF(AND($D38="Yes",$J38=1,$I38/$E38*'Risk Bands (Config)'!$B$5>='Risk Bands (Config)'!$B$6),1,0) -> 0 | M38: =IF($L38=1,$A38,"") | N38: =IF($J38=1,IFERROR(INDEX('Scoring Engine (Rules)'!$O$5:$O$89,MATCH($A38&"|"&$I38,'Scoring Engine (Rules)'!$R$5:$R$89,0)),""),"") | O38: =IF($J38=1,IFERROR(INDEX('Scoring Engine (Rules)'!$P$5:$P$89,MATCH($A38&"|"&$I38,'Scoring Engine (Rules)'!$R$5:$R$89,0)),""),"") | P38: =IF($J38=1,IFERROR(INDEX('Scoring Engine (Rules)'!$Q$5:$Q$89,MATCH($A38&"|"&$I38,'Scoring Engine (Rules)'!$R$5:$R$89,0)),""),"")
A39: CM-017 | B39: Project cost variance % | C39: Credit Monitoring | D39: =INDEX('Indicator Master'!$F$4:$F$24,MATCH($A39,'Indicator Master'!$A$4:$A$24,0)) -> No | E39: =INDEX('Indicator Master'!$N$4:$N$24,MATCH($A39,'Indicator Master'!$A$4:$A$24,0)) -> 40 | F39: N | H39: Not applicable to this borrower (no project/term-loan under implementation) | J39: =IF(AND($F39="Y",$G39="Y",ISNUMBER($I39)),1,0) -> 0 | K39: =IF($J39=1,$I39/$E39*'Risk Bands (Config)'!$B$5,"") | L39: =IF(AND($D39="Yes",$J39=1,$I39/$E39*'Risk Bands (Config)'!$B$5>='Risk Bands (Config)'!$B$6),1,0) -> 0 | M39: =IF($L39=1,$A39,"") | N39: =IF($J39=1,IFERROR(INDEX('Scoring Engine (Rules)'!$O$5:$O$89,MATCH($A39&"|"&$I39,'Scoring Engine (Rules)'!$R$5:$R$89,0)),""),"") | O39: =IF($J39=1,IFERROR(INDEX('Scoring Engine (Rules)'!$P$5:$P$89,MATCH($A39&"|"&$I39,'Scoring Engine (Rules)'!$R$5:$R$89,0)),""),"") | P39: =IF($J39=1,IFERROR(INDEX('Scoring Engine (Rules)'!$Q$5:$Q$89,MATCH($A39&"|"&$I39,'Scoring Engine (Rules)'!$R$5:$R$89,0)),""),"")
A40: CM-018 | B40: Plant Shutdown | C40: Credit Monitoring | D40: =INDEX('Indicator Master'!$F$4:$F$24,MATCH($A40,'Indicator Master'!$A$4:$A$24,0)) -> No | E40: =INDEX('Indicator Master'!$N$4:$N$24,MATCH($A40,'Indicator Master'!$A$4:$A$24,0)) -> 30 | F40: Y | G40: Y | H40: Plant operating normally; no shutdown → band 'No shutdown' | I40: 0 | J40: =IF(AND($F40="Y",$G40="Y",ISNUMBER($I40)),1,0) -> 1 | K40: =IF($J40=1,$I40/$E40*'Risk Bands (Config)'!$B$5,"") -> 0 | L40: =IF(AND($D40="Yes",$J40=1,$I40/$E40*'Risk Bands (Config)'!$B$5>='Risk Bands (Config)'!$B$6),1,0) -> 0 | M40: =IF($L40=1,$A40,"") | N40: =IF($J40=1,IFERROR(INDEX('Scoring Engine (Rules)'!$O$5:$O$89,MATCH($A40&"|"&$I40,'Scoring Engine (Rules)'!$R$5:$R$89,0)),""),"") -> Normal — plant operating normally; no shutdown. | O40: =IF($J40=1,IFERROR(INDEX('Scoring Engine (Rules)'!$P$5:$P$89,MATCH($A40&"|"&$I40,'Scoring Engine (Rules)'!$R$5:$R$89,0)),""),"") -> No remedial action required. Continue routine monitoring at the standard review cycle and record the reading. | P40: =IF($J40=1,IFERROR(INDEX('Scoring Engine (Rules)'!$Q$5:$Q$89,MATCH($A40&"|"&$I40,'Scoring Engine (Rules)'!$R$5:$R$89,0)),""),"") -> RM (routine)
A41: CM-019 | B41: Cyber/operational disruption classification | C41: Credit Monitoring | D41: =INDEX('Indicator Master'!$F$4:$F$24,MATCH($A41,'Indicator Master'!$A$4:$A$24,0)) -> No | E41: =INDEX('Indicator Master'!$N$4:$N$24,MATCH($A41,'Indicator Master'!$A$4:$A$24,0)) -> 40 | F41: Y | G41: N | H41: Applicable but data not available (cyber-risk assessment not yet available) — excluded, not zero | J41: =IF(AND($F41="Y",$G41="Y",ISNUMBER($I41)),1,0) -> 0 | K41: =IF($J41=1,$I41/$E41*'Risk Bands (Config)'!$B$5,"") | L41: =IF(AND($D41="Yes",$J41=1,$I41/$E41*'Risk Bands (Config)'!$B$5>='Risk Bands (Config)'!$B$6),1,0) -> 0 | M41: =IF($L41=1,$A41,"") | N41: =IF($J41=1,IFERROR(INDEX('Scoring Engine (Rules)'!$O$5:$O$89,MATCH($A41&"|"&$I41,'Scoring Engine (Rules)'!$R$5:$R$89,0)),""),"") | O41: =IF($J41=1,IFERROR(INDEX('Scoring Engine (Rules)'!$P$5:$P$89,MATCH($A41&"|"&$I41,'Scoring Engine (Rules)'!$R$5:$R$89,0)),""),"") | P41: =IF($J41=1,IFERROR(INDEX('Scoring Engine (Rules)'!$Q$5:$Q$89,MATCH($A41&"|"&$I41,'Scoring Engine (Rules)'!$R$5:$R$89,0)),""),"")
A42: CM-020 | B42: End-use compliance status | C42: Credit Monitoring | D42: =INDEX('Indicator Master'!$F$4:$F$24,MATCH($A42,'Indicator Master'!$A$4:$A$24,0)) -> No | E42: =INDEX('Indicator Master'!$N$4:$N$24,MATCH($A42,'Indicator Master'!$A$4:$A$24,0)) -> 50 | F42: Y | G42: Y | H42: End-use certified compliant by the CA → band 'Compliant' | I42: 0 | J42: =IF(AND($F42="Y",$G42="Y",ISNUMBER($I42)),1,0) -> 1 | K42: =IF($J42=1,$I42/$E42*'Risk Bands (Config)'!$B$5,"") -> 0 | L42: =IF(AND($D42="Yes",$J42=1,$I42/$E42*'Risk Bands (Config)'!$B$5>='Risk Bands (Config)'!$B$6),1,0) -> 0 | M42: =IF($L42=1,$A42,"") | N42: =IF($J42=1,IFERROR(INDEX('Scoring Engine (Rules)'!$O$5:$O$89,MATCH($A42&"|"&$I42,'Scoring Engine (Rules)'!$R$5:$R$89,0)),""),"") -> Normal — funds used for the sanctioned purpose; compliant. | O42: =IF($J42=1,IFERROR(INDEX('Scoring Engine (Rules)'!$P$5:$P$89,MATCH($A42&"|"&$I42,'Scoring Engine (Rules)'!$R$5:$R$89,0)),""),"") -> No remedial action required. Continue routine monitoring at the standard review cycle and record the reading. | P42: =IF($J42=1,IFERROR(INDEX('Scoring Engine (Rules)'!$Q$5:$Q$89,MATCH($A42&"|"&$I42,'Scoring Engine (Rules)'!$R$5:$R$89,0)),""),"") -> RM (routine)
A43: CM-021 | B43: Count of overdue events (rolling 3-6m) | C43: Credit Monitoring | D43: =INDEX('Indicator Master'!$F$4:$F$24,MATCH($A43,'Indicator Master'!$A$4:$A$24,0)) -> No | E43: =INDEX('Indicator Master'!$N$4:$N$24,MATCH($A43,'Indicator Master'!$A$4:$A$24,0)) -> 25 | F43: Y | G43: Y | H43: 2 overdue events in the last 3-6 months → band '2 instances' | I43: 15 | J43: =IF(AND($F43="Y",$G43="Y",ISNUMBER($I43)),1,0) -> 1 | K43: =IF($J43=1,$I43/$E43*'Risk Bands (Config)'!$B$5,"") -> 60 | L43: =IF(AND($D43="Yes",$J43=1,$I43/$E43*'Risk Bands (Config)'!$B$5>='Risk Bands (Config)'!$B$6),1,0) -> 0 | M43: =IF($L43=1,$A43,"") | N43: =IF($J43=1,IFERROR(INDEX('Scoring Engine (Rules)'!$O$5:$O$89,MATCH($A43&"|"&$I43,'Scoring Engine (Rules)'!$R$5:$R$89,0)),""),"") -> Elevated concern — two overdue events; a pattern forming. | O43: =IF($J43=1,IFERROR(INDEX('Scoring Engine (Rules)'!$P$5:$P$89,MATCH($A43&"|"&$I43,'Scoring Engine (Rules)'!$R$5:$R$89,0)),""),"") -> 1) Obtain a written explanation. 2) Enforce due-date discipline. 3) Place on the watch-list. | P43: =IF($J43=1,IFERROR(INDEX('Scoring Engine (Rules)'!$Q$5:$Q$89,MATCH($A43&"|"&$I43,'Scoring Engine (Rules)'!$R$5:$R$89,0)),""),"") -> RM + Credit Analyst
A45: Additional risk controls
A46: Previous Overall Score (last review) | C46: Optional input. Enter the prior review’s Overall Score to enable band-transition alerts.
A47: Score movement vs last review | B47: =IF($B$46="","(enter previous score)",$B$14-$B$46) -> (enter previous score) | C47: Positive = deterioration since last review.
A48: Data Sufficiency / Confidence | B48: =IF($B$12>='Risk Bands (Config)'!$B$16,"Adequate","LOW — insufficient data; treat score as low-confidence") -> Adequate | C48: Compares Data Coverage % to the minimum-coverage floor on the Config sheet.

Sheet Borrower Example
A1: Borrower Example — End-to-End Worked Trace
A2: Hypothetical borrower. Every figure below is a live link to the Overall Score Engine, so the trace always matches the engine.
A4: Profile: Acme Textiles Pvt Ltd — unlisted MSME, working-capital (CC/OD) + term loan, domestic textile manufacturer. Under moderate stress: a GST-turnover dip, a negative CFO quarter, thin current ratio, an informal moratorium request, minor collateral/insurance lapses and a couple of overdue events. No FX, geopolitical or project exposure.
A6: Overall Score | B6: Numeric Risk Band | C6: Data Coverage % | D6: Critical Override? | E6: Critical Fired | F6: FINAL STATUS
A7: ='Overall Score Engine'!$B$14 -> 27.829132 | B7: ='Overall Score Engine'!$B$15 -> Yellow | C7: ='Overall Score Engine'!$B$12 -> 94.444444 | D7: ='Overall Score Engine'!$B$16 -> NO | E7: ='Overall Score Engine'!$B$17 -> None | F7: ='Overall Score Engine'!$B$18 -> Yellow
A9: Step-by-step trace of the highest-impact indicators (Input → Threshold band → Raw → Max → Normalised). Live from the engine:
A10: UID | B10: Indicator | C10: Borrower Observation | D10: Raw | E10: Max | F10: Normalised | G10: Notes
A11: ='Overall Score Engine'!$A$43 -> CM-021 | B11: ='Overall Score Engine'!$B$43 -> Count of overdue events (rolling 3-6m) | C11: ='Overall Score Engine'!$H$43 -> 2 overdue events in the last 3-6 months → band '2 instances' | D11: ='Overall Score Engine'!$I$43 -> 15 | E11: ='Overall Score Engine'!$E$43 -> 25 | F11: ='Overall Score Engine'!$K$43 -> 60 | G11: Contributes to the average
A12: ='Overall Score Engine'!$A$25 -> CM-003 | B12: ='Overall Score Engine'!$B$25 -> GST turnover change % / vs bank credits | C12: ='Overall Score Engine'!$H$25 -> GST turnover down ~30% vs prior period → band '20-40% decline' | D12: ='Overall Score Engine'!$I$25 -> 20 | E12: ='Overall Score Engine'!$E$25 -> 35 | F12: ='Overall Score Engine'!$K$25 -> 57.142857 | G12: Contributes to the average
A13: ='Overall Score Engine'!$A$27 -> CM-005 | B13: ='Overall Score Engine'!$B$27 -> Current Ratio | C13: ='Overall Score Engine'!$H$27 -> Current ratio at 1.05 → band '1.00-1.09' | D13: ='Overall Score Engine'!$I$27 -> 20 | E13: ='Overall Score Engine'!$E$27 -> 35 | F13: ='Overall Score Engine'!$K$27 -> 57.142857 | G13: Contributes to the average
A14: ='Overall Score Engine'!$A$26 -> CM-004 | B14: ='Overall Score Engine'!$B$26 -> Cash Flow from Operations (sign / periods) | C14: ='Overall Score Engine'!$H$26 -> One negative operating cash-flow quarter → band 'one negative period' | D14: ='Overall Score Engine'!$I$26 -> 15 | E14: ='Overall Score Engine'!$E$26 -> 40 | F14: ='Overall Score Engine'!$K$26 -> 37.5 | G14: Contributes to the average
A15: ='Overall Score Engine'!$A$30 -> CM-008 | B15: ='Overall Score Engine'!$B$30 -> Restructuring request status | C15: ='Overall Score Engine'!$H$30 -> Informal moratorium request raised by the borrower → band 'informal request' | D15: ='Overall Score Engine'!$I$30 -> 15 | E15: ='Overall Score Engine'!$E$30 -> 40 | F15: ='Overall Score Engine'!$K$30 -> 37.5 | G15: Contributes to the average
A16: ='Overall Score Engine'!$A$31 -> CM-009 | B16: ='Overall Score Engine'!$B$31 -> Security/collateral cover ratio | C16: ='Overall Score Engine'!$H$31 -> Minor collateral-cover shortfall pending revaluation → band 'minor shortfall/lapse' | D16: ='Overall Score Engine'!$I$31 -> 15 | E16: ='Overall Score Engine'!$E$31 -> 40 | F16: ='Overall Score Engine'!$K$31 -> 37.5 | G16: Contributes to the average
A17: ='Overall Score Engine'!$A$41 -> CM-019 | B17: ='Overall Score Engine'!$B$41 -> Cyber/operational disruption classification | C17: ='Overall Score Engine'!$H$41 -> Applicable but data not available (cyber-risk assessment not yet available) — excluded, not zero | D17: ='Overall Score Engine'!$I$41 -> 0 | E17: ='Overall Score Engine'!$E$41 -> 40 | F17: ='Overall Score Engine'!$K$41 | G17: Applicable, no data → excluded (not zero)
A18: ='Overall Score Engine'!$A$37 -> CM-015 | B18: ='Overall Score Engine'!$B$37 -> Geopolitical exposure classification | C18: ='Overall Score Engine'!$H$37 -> Not applicable to this borrower (domestic operations only) | D18: ='Overall Score Engine'!$I$37 -> 0 | E18: ='Overall Score Engine'!$E$37 -> 35 | F18: ='Overall Score Engine'!$K$37 | G18: Not applicable → excluded
A20: The Overall Score is the average of the normalised scores of applicable Credit-Monitoring indicators with valid data (missing data excluded, N/A excluded). Credit Monitoring has no CRITICAL-flagged indicators, so no override applies and the Final Status equals the numeric risk band.

Sheet Risk Bands (Config)
A1: Risk Bands & Scoring Configuration
A2: PROPOSED — not present in the source file. All values below are editable; every other sheet reads from here.
A4: Parameter | B4: Value | C4: Notes
A5: Normalisation Base | B5: 100 | C5: Normalised Score = Raw Score ÷ Maximum Score × Base
A6: Critical Override Trigger (Normalised ≥) | B6: 100 | C6: A CRITICAL-flagged indicator whose normalised score reaches this value forces FINAL STATUS = Critical, regardless of the average.
A8: Risk Band | B8: Score From | C8: Score To | D8: Lower Bound (lookup) | E8: Interpretation | F8: Recommended Supervisory Posture
A9: Green | B9: 0 | C9: 19 | D9: 0 | E9: Normal / Low Concern | F9: Business-as-usual monitoring at standard frequency.
A10: Yellow | B10: 20 | C10: 39 | D10: 20 | E10: Early Deterioration / Monitor | F10: Flag account; note trend; review at next monitoring cycle.
A11: Amber | B11: 40 | C11: 59 | D11: 40 | E11: Elevated Concern / Enhanced Monitoring | F11: Enhanced monitoring; RM commentary; tighten review frequency.
A12: Red | B12: 60 | C12: 79 | D12: 60 | E12: High Concern / Immediate Review | F12: Escalate to credit committee; borrower engagement; corrective plan.
A13: Critical | B13: 80 | C13: 100 | D13: 80 | E13: Severe EWS / Immediate Intervention | F13: Immediate intervention; classify/restructure/recovery as warranted.
A15: Additional parameters & conventions
A16: Minimum Data Coverage % (confidence floor) | B16: 60 | C16: If Data Coverage % is below this, the Overall Score is labelled INSUFFICIENT DATA / low-confidence rather than a benign band.

Sheet Alert Lifecycle
A1: ALERT LIFECYCLE
A2: When the system creates an alert, how it is prioritised, and how duplicates/repeats are handled. Bands, severities and the override follow this file’s Scoring Engine and Risk Bands (Config). Distinguishes signal vs alert.
A4: A. Alert generation rules
A5: Alert ID | B5: Trigger | C5: Condition | D5: Severity | E5: Priority | F5: Recipient | G5: Notification | H5: Reason Code | I5: Action SLA | J5: Escalation | K5: Duplicate Suppression | L5: Status
A6: ALERT-001 | B6: No breach | C6: All applicable indicators in the '0' (Normal) band | D6: None | E6: — | F6: — | G6: None | H6: — | I6: — | J6: — | K6: — | L6: No alert
A7: ALERT-002 | B7: Indicator breach (single, immaterial) | C7: One indicator in a low non-zero band, not persistent | D7: Low | E7: P4 | F7: RM | G7: Dashboard only | H7: Indicator reason code | I7: TBD | J7: On repeat → P3 | K7: Collapse into one open signal per indicator | L7: Signal
A8: ALERT-003 | B8: Material / repeated indicator breach | C8: Indicator reaches its material band or repeats over lookback | D8: Medium | E8: P3 | F8: RM | G8: Dashboard + email | H8: Indicator reason code | I8: TBD | J8: Persist → Credit | K8: Suppress if same indicator already open & unchanged | L8: Alert
A9: ALERT-004 | B9: Overall score → Yellow (20-39) | C9: Band transition Green→Yellow | D9: Medium | E9: P3 | F9: RM | G9: Dashboard + email | H9: Band reason codes | I9: TBD | J9: No action in SLA → escalate | K9: One alert per band transition | L9: Yellow Alert
A10: ALERT-005 | B10: Overall score → Amber (40-59) | C10: Band transition into Amber | D10: Medium-High | E10: P2 | F10: RM + Credit | G10: Dashboard + email | H10: Band reason codes | I10: TBD | J10: → Credit review | K10: One per transition; re-fire on worsening | L10: Amber Alert
A11: ALERT-006 | B11: Overall score → Red (60-79) | C11: Band transition into Red | D11: High | E11: P2 | F11: Credit Committee | G11: Dashboard + email + workflow | H11: Band reason codes | I11: TBD | J11: → Senior credit | K11: One per transition; re-fire on worsening | L11: Red Alert
A12: ALERT-007 | B12: Overall score → Critical (80-100) | C12: Band transition into Critical | D12: Critical | E12: P1 | F12: Credit Head + Senior | G12: Email + workflow | H12: Band reason codes | I12: Immediate | J12: → Senior credit / committee | K12: One per transition; re-fire on worsening | L12: Critical Alert
A13: ALERT-008 | B13: Critical override TRUE | C13: N/A — Credit Monitoring has no CRITICAL-flagged indicators, so the override never fires | D13: — | E13: — | F13: — | G13: None | H13: Override reason | I13: — | J13: — | K13: — | L13: Not applicable (no criticals)
A15: B. Alert types (state vocabulary) & duplicate handling
A16: Alert Type | B16: Meaning | C16: Duplicate / repeat rule
A17: New Alert | B17: First time this condition fires for the borrower. | C17: Create once.
A18: Existing Alert | B18: Same condition already open and unchanged. | C18: Do NOT create a new alert; keep the open one; update timestamp/evidence.
A19: Repeat Alert | B19: Condition cleared then re-triggered later. | C19: Create a new alert linked to the prior one (history retained).
A20: Escalated Alert | B20: Open alert unresolved past SLA or severity increased. | C20: Raise priority; route to next level; keep same alert thread.
A21: Closed Alert | B21: Closure criteria met (condition cleared — see section E). | C21: Mark closed with outcome; retain for back-testing.
A22: Reopened Alert | B22: Closed alert's condition recurs / closure was premature. | C22: Reopen same thread; record reason for reopening.
A24: Duplicate suppression principle: one OPEN alert per (borrower, indicator/condition). A worsening condition re-fires at higher severity; an unchanged condition does not spam. This module has no override alert. SLA values are TO BE DEFINED per credit policy.
A26: B. RM / Credit Action Logic (by risk band)
A27: Status | B27: Trigger | C27: Responsible Role | D27: Required Action | E27: Timeline / SLA | F27: Required Documents | G27: Decision | H27: Escalation | I27: Closure Criteria
A28: Green / Normal | B28: Score 0-19, no override | C28: RM | D28: Standard monitoring; no special action. | E28: BAU cycle | F28: None extra | G28: Continue monitoring | H28: — | I28: N/A
A29: Yellow / Monitor | B29: Score 20-39 | C29: RM | D29: Log trend; RM commentary; review borrower conduct at next cycle. | E29: Next cycle (TBD) | F29: Account statement review; RM remarks | G29: RM notes cause & plan | H29: If unresolved → Credit | I29: Signals return to '0' bands / remarks accepted
A30: Amber / Watchlist | B30: Score 40-59 | C30: RM + Credit | D30: Enhanced monitoring; request updated financials; borrower discussion. | E30: 2-4 weeks (TBD) | F30: Updated financials; account review | G30: RM + Credit note cause & plan | H30: If unresolved → Credit Committee | I30: Condition improves to a lower band & remarks accepted
A31: Red / High | B31: Score 60-79 | C31: Credit Committee | D31: Credit review; obtain updated financials, stock statement, repayment plan; exposure review. | E31: 1-2 weeks (TBD) | F31: Updated financials; stock statement; repayment plan | G31: Credit decides monitoring / exit | H31: If worsening → Senior credit | I31: Condition cleared & Credit sign-off
A32: Red / Critical | B32: Score 80-100 | C32: Senior Credit / Committee | D32: Senior credit review; exposure review; possible freeze / recovery / restructuring depending on trigger. | E32: Immediate | F32: Full credit note; legal / recovery inputs | G32: Committee decision | H32: Recovery / legal / restructuring path | I32: Formal resolution per policy
A34: C. Lifecycle states
A35: State | B35: Entry condition | C35: Owner | D35: Allowed next states | E35: Backward move?
A36: Generated | B36: Alert generated in section A | C36: System | D36: Assigned | E36: No
A37: Assigned | B37: Routed to RM / Credit | C37: System | D37: Under Review | E37: No
A38: Under Review | B38: Owner investigating | C38: RM / Credit | D38: Action Required / Resolved | E38: No
A39: Action Required | B39: Borrower action / docs needed | C39: RM / Credit | D39: Escalated / Resolved | E39: No
A40: Escalated | B40: SLA breach or severity up | C40: Credit / Senior | D40: Resolved / Action Required | E40: Yes (to Action Required)
A41: Resolved | B41: Condition cleared, pending closure check | C41: Credit | D41: Closed / Reopened | E41: No
A42: Closed | B42: Closure criteria met (see section E) | C42: Credit | D42: Reopened | E42: Yes (Reopened)
A43: Reopened | B43: Condition recurs / premature closure | C43: Credit | D43: Under Review | E43: Yes

Sheet Recommendations
A1: Final Recommendation / Action & AI-Suggested Path
A2: How the Final Status maps to action, and how the tool ranks the drivers behind the score to suggest a remediation path.
A4: A. Action Matrix by Final Status
A5: Final Status | B5: What it means | C5: Recommended Action | D5: Owner | E5: Timeline
A6: Green | B6: Normal / low concern | C6: Standard monitoring; no action beyond routine review. | D6: RM | E6: Routine cycle
A7: Yellow | B7: Early deterioration | C7: Log trend; RM commentary; watch next cycle. | D7: RM | E7: Next cycle
A8: Amber | B8: Elevated concern | C8: Enhanced monitoring; request updated financials; tighten review frequency. | D8: RM + Credit | E8: 2–4 weeks
A9: Red | B9: High concern | C9: Escalate to credit committee; borrower engagement; corrective action plan. | D9: Credit Committee | E9: 1–2 weeks
A10: Critical | B10: Severe EWS | C10: Immediate intervention; site visit; classify / restructure / initiate recovery as warranted. | D10: Credit Head / Risk | E10: Immediate
A11: CRITICAL (Override) | B11: A critical event is present regardless of average | C11: Treat as Critical immediately; investigate the specific critical indicator(s) first; do not wait for the average to catch up. | D11: Credit Head / Risk | E11: Immediate
A13: B. How the AI suggests the recommended path
A14: 1. Take all applicable indicators that have valid data (the same set used for the Overall Score).
A15: 2. Rank them by Normalised Score (highest first); any CRITICAL-flagged indicator at its worst band is pulled to the top automatically.
A16: 3. Read the top contributors as the "drivers" of the score, and group them by Category (e.g., Account Conduct, Financial Performance, Compliance).
A17: 4. For each driver, pull the band-specific remark, remedial plan and owner from the Scoring Engine (Rules) sheet (matched on UID + Normalised).
A18: 5. Because every driver traces back to UID → Raw Score → threshold band → borrower input, each recommendation is fully auditable.
A20: C. Top score drivers for the Borrower Example (remarks/actions pulled live from the Rules sheet by UID + Normalised)
A21: Rank | B21: UID | C21: Indicator | D21: Category | E21: Normalised | F21: What it signals & likely drivers | G21: Remedial action plan (step-by-step) | H21: Primary owner | I21: raw (helper)
A22: 1 | B22: CM-021 | C22: Count of overdue events (rolling 3-6m) | D22: Account Conduct | E22: 60 | F22: =IFERROR(INDEX('Scoring Engine (Rules)'!$O$5:$O$89,MATCH($B22&"|"&$I22,'Scoring Engine (Rules)'!$R$5:$R$89,0)),"") -> Elevated concern — two overdue events; a pattern forming. | G22: =IFERROR(INDEX('Scoring Engine (Rules)'!$P$5:$P$89,MATCH($B22&"|"&$I22,'Scoring Engine (Rules)'!$R$5:$R$89,0)),"") -> 1) Obtain a written explanation. 2) Enforce due-date discipline. 3) Place on the watch-list. | H22: =IFERROR(INDEX('Scoring Engine (Rules)'!$Q$5:$Q$89,MATCH($B22&"|"&$I22,'Scoring Engine (Rules)'!$R$5:$R$89,0)),"") -> RM + Credit Analyst | I22: 15
A23: 2 | B23: CM-003 | C23: GST turnover change % / vs bank credits | D23: Financial Performance | E23: 57.1 | F23: =IFERROR(INDEX('Scoring Engine (Rules)'!$O$5:$O$89,MATCH($B23&"|"&$I23,'Scoring Engine (Rules)'!$R$5:$R$89,0)),"") -> Elevated concern — down 20–40%; material fall — demand loss or diversion of billing. | G23: =IFERROR(INDEX('Scoring Engine (Rules)'!$P$5:$P$89,MATCH($B23&"|"&$I23,'Scoring Engine (Rules)'!$R$5:$R$89,0)),"") -> 1) Reassess WC and projections. 2) Investigate under-reporting/diversion. 3) Enhanced monitoring; flag to Credit. | H23: =IFERROR(INDEX('Scoring Engine (Rules)'!$Q$5:$Q$89,MATCH($B23&"|"&$I23,'Scoring Engine (Rules)'!$R$5:$R$89,0)),"") -> RM + Credit Analyst | I23: 20
A24: 3 | B24: CM-005 | C24: Current Ratio | D24: Financial Performance | E24: 57.1 | F24: =IFERROR(INDEX('Scoring Engine (Rules)'!$O$5:$O$89,MATCH($B24&"|"&$I24,'Scoring Engine (Rules)'!$R$5:$R$89,0)),"") -> Elevated concern — current ratio 1.00–1.09; thin liquidity buffer. | G24: =IFERROR(INDEX('Scoring Engine (Rules)'!$P$5:$P$89,MATCH($B24&"|"&$I24,'Scoring Engine (Rules)'!$R$5:$R$89,0)),"") -> 1) Assess NWC adequacy; seek promoter infusion. 2) Enhanced monitoring. 3) Flag to Credit. | H24: =IFERROR(INDEX('Scoring Engine (Rules)'!$Q$5:$Q$89,MATCH($B24&"|"&$I24,'Scoring Engine (Rules)'!$R$5:$R$89,0)),"") -> RM + Credit Analyst | I24: 20
A25: 4 | B25: CM-004 | C25: Cash Flow from Operations (sign / periods) | D25: Financial Performance | E25: 37.5 | F25: =IFERROR(INDEX('Scoring Engine (Rules)'!$O$5:$O$89,MATCH($B25&"|"&$I25,'Scoring Engine (Rules)'!$R$5:$R$89,0)),"") -> Elevated concern — one negative CFO period; isolated — watch for persistence. | G25: =IFERROR(INDEX('Scoring Engine (Rules)'!$P$5:$P$89,MATCH($B25&"|"&$I25,'Scoring Engine (Rules)'!$R$5:$R$89,0)),"") -> 1) Analyse the CFO driver (WC swing vs loss). 2) Obtain an explanation. 3) Monitor next period. | H25: =IFERROR(INDEX('Scoring Engine (Rules)'!$Q$5:$Q$89,MATCH($B25&"|"&$I25,'Scoring Engine (Rules)'!$R$5:$R$89,0)),"") -> RM + Credit Analyst | I25: 15
A26: 5 | B26: CM-008 | C26: Restructuring request status | D26: Credit Risk | E26: 37.5 | F26: =IFERROR(INDEX('Scoring Engine (Rules)'!$O$5:$O$89,MATCH($B26&"|"&$I26,'Scoring Engine (Rules)'!$R$5:$R$89,0)),"") -> Elevated concern — an informal restructuring/moratorium enquiry; early stress signal. | G26: =IFERROR(INDEX('Scoring Engine (Rules)'!$P$5:$P$89,MATCH($B26&"|"&$I26,'Scoring Engine (Rules)'!$R$5:$R$89,0)),"") -> 1) Obtain the rationale; assess genuine stress vs willful. 2) Seek cash-flow data. 3) Monitor. | H26: =IFERROR(INDEX('Scoring Engine (Rules)'!$Q$5:$Q$89,MATCH($B26&"|"&$I26,'Scoring Engine (Rules)'!$R$5:$R$89,0)),"") -> RM + Credit Analyst | I26: 15
A27: 6 | B27: CM-009 | C27: Security/collateral cover ratio | D27: Collateral Risk | E27: 37.5 | F27: =IFERROR(INDEX('Scoring Engine (Rules)'!$O$5:$O$89,MATCH($B27&"|"&$I27,'Scoring Engine (Rules)'!$R$5:$R$89,0)),"") -> Elevated concern — a minor shortfall or lapse in cover; top-up needed. | G27: =IFERROR(INDEX('Scoring Engine (Rules)'!$P$5:$P$89,MATCH($B27&"|"&$I27,'Scoring Engine (Rules)'!$R$5:$R$89,0)),"") -> 1) Revalue security; seek a top-up. 2) Adjust DP to available cover. 3) Monitor to closure. | H27: =IFERROR(INDEX('Scoring Engine (Rules)'!$Q$5:$Q$89,MATCH($B27&"|"&$I27,'Scoring Engine (Rules)'!$R$5:$R$89,0)),"") -> RM + Credit Analyst | I27: 15
A28: 7 | B28: CM-010 | C28: Insurance validity / days to expiry | D28: Collateral Risk | E28: 37.5 | F28: =IFERROR(INDEX('Scoring Engine (Rules)'!$O$5:$O$89,MATCH($B28&"|"&$I28,'Scoring Engine (Rules)'!$R$5:$R$89,0)),"") -> Elevated concern — a minor lapse or approaching expiry; renewal needed. | G28: =IFERROR(INDEX('Scoring Engine (Rules)'!$P$5:$P$89,MATCH($B28&"|"&$I28,'Scoring Engine (Rules)'!$R$5:$R$89,0)),"") -> 1) Follow up for renewal with the bank clause; note the expiry. 2) Obtain the policy. 3) Monitor. | H28: =IFERROR(INDEX('Scoring Engine (Rules)'!$Q$5:$Q$89,MATCH($B28&"|"&$I28,'Scoring Engine (Rules)'!$R$5:$R$89,0)),"") -> RM + Credit Analyst | I28: 15
A29: 8 | B29: CM-002 | C29: Excess over DP/limit % | D29: Account Conduct | E29: 33.3 | F29: =IFERROR(INDEX('Scoring Engine (Rules)'!$O$5:$O$89,MATCH($B29&"|"&$I29,'Scoring Engine (Rules)'!$R$5:$R$89,0)),"") -> Early warning — excess up to 5%; minor, likely a timing over-draw. | G29: =IFERROR(INDEX('Scoring Engine (Rules)'!$P$5:$P$89,MATCH($B29&"|"&$I29,'Scoring Engine (Rules)'!$R$5:$R$89,0)),"") -> 1) Regularise the excess promptly. 2) Ascertain the reason. 3) Allow no fresh excess. | H29: =IFERROR(INDEX('Scoring Engine (Rules)'!$Q$5:$Q$89,MATCH($B29&"|"&$I29,'Scoring Engine (Rules)'!$R$5:$R$89,0)),"") -> RM + Credit Analyst | I29: 10
