Workbook

Sheet README
A1: EWS Functional Logic & Scoring Workbook (v1.13)
A2: 43 indicators (EWS-001…EWS-043). “Security Cover” removed; DSCR, Leverage Ratio, Current Ratio and Carbon Emission thresholds revised per the Indicator Master. Critical Combination rule retained.
A4: What changed in v1.13
A5: • Removed the indicator “Security Cover” (was EWS-044) from every sheet.
A6: • Revised thresholds/scores per the Indicator Master for DSCR (EWS-041: 1.25–1.50 = 0, <1.25 = 40), Leverage Ratio (EWS-042: ≤2.0 = 0, 2.0–3.0 = 10, >3.0 = 40), Current Ratio (EWS-043: ≥1.33 = 0, 1–1.33 = 10, <1.00 = 40) and Carbon Emission (EWS-038: within norms = 0, breach = 15, penalty/action = 40).
A7: • Sequence remains continuous EWS-001…EWS-043 (43 indicators) — the removed indicator was last, so no renumbering of others was needed.
A8: • All downstream sheets (Functional Logic, Scoring Engine (Rules), Overall Score Engine, Borrower Example, Recommendations) rebuilt from the Indicator Master.
A9: • The Critical Combination rule is unchanged (pairs EWS-004/011, EWS-005/014, EWS-009/012).
A11: Scoring & combination logic
A12: • Normalised = Raw ÷ Max Score × 100. Overall = average of normalised of applicable indicators with valid data (missing excluded, N/A excluded).
A13: • Critical Override fires on (a) any Critical indicator at its trigger, OR (b) any Critical Combination pair co-occurring (both members breached above Normal — trigger configurable on the Config sheet).
A14: • Pair 1 — EWS-004 (Payment Default Frequency) + EWS-011 (Creditor days). Pair 2 — EWS-005 (Repayment source) + EWS-014 (Unsecured loans change %). Pair 3 — EWS-009 (Debtor days) + EWS-012 (Provisions/write-offs).
... A17: • Indicator Master · Functional Logic · Scoring Engine (Rules) · Overall Score Engine (with the Critical Combination block) · Borrower Example · Risk Bands (Config) · Alert Lifecycle · Recommendations.

Sheet Indicator Master
A1: EWS Indicator Master
A3: UID | B3: Module | C3: Indicator | D3: Description | E3: Category | F3: Critical (Yes/No) | G3: What to Track (Input) | H3: Data Source Channel | I3: Acquisition Mechanism | J3: Data Type | K3: Update Frequency | L3: Functional Calculation Formula | M3: Threshold & Score | N3: Max Score
A4: EWS-001 | B4: EWS | C4: Utilization % (outstanding / sanctioned) | D4: High utilization of working capital limits | E4: Account Conduct | F4: No | G4: CC/OD utilization above 85-90% continuously | H4: Bank Core System (CBS) | I4: Direct CBS extract | J4: Quantitative | K4: Daily | L4: Utilization% = Utilized / Sanctioned; flag if >85% sustained | M4: <85% = 0 | 85-90% = 10 | 90-95% = 20 | >95% for 30+ days = 30 | N4: 30
A5: EWS-002 | B5: EWS | C5: Count of ad-hoc limit requests (rolling 12m) | D5: Frequent ad-hoc limit requests | E5: Account Conduct | F5: No | G5: Temporary limit enhancement requests | H5: Bank Core System (CBS) | I5: Map in data discovery | J5: Quantitative | K5: Event | L5: Compute Count of ad-hoc limit requests (rolling 12m) then compare to threshold bands | M5: 0-1 request/year = 0 | 2 = 10 | 3+ = 20 | emergency request = 30 | N5: 30
A6: EWS-003 | B6: EWS | C6: Monthly sales vs credit summation | D6: Lower bank account credits (Not applicable to Consortium Account) | E6: Account Conduct | F6: Yes | G6: Reduction in monthly credits in operating account | H6: Bank Core System (CBS) | I6: Direct CBS extract | J6: Quantitative | K6: Monthly | L6: CreditChange% = (CurrentMonthCredits - Baseline)/Baseline | M6: Stable/Variation upto 5% = 0 | 5-10% decline = 10 | 10-15% decline = 20 | >15% = 35 | N6: 35
A7: EWS-004 | B7: EWS | C7: Payment Default Frequency | D7: Frequent Cheque Bounces | E7: Account Conduct | F7: No | G7: Cheque returns, Cheque Bounce, ECS bounce, frequent TODs | H7: Bank Core System (CBS) | I7: Direct CBS extract | J7: Quantitative | K7: Daily | L7: Compute Count of conduct events (rolling 90d) then compare to threshold bands | M7: 0 = 0 | 1 = 5 | 2 = 15 | 3+ in 90 days = 25 | N7: 25
A8: EWS-005 | B8: EWS | C8: Repayment source classification | D8: Repayment out of other source of funds instead of sales | E8: Account Conduct | F8: No | G8: Repayment from unrelated parties or group accounts | H8: Bank Core System (CBS) | I8: Direct CBS extract | J8: Qualitative | K8: Event | L8: Classify event severity for 'Change in repayment source' (no numeric calc) | M8: Own operating cash flow = 0 | group support = 15 | unrelated source = 30 | repeated third-party payments = 40 | N8: 40
A9: EWS-006 | B9: EWS | C9: Stock reported vs audited variance % | D9: Mismatch in stock statement and financials | E9: Audit | F9: No | G9: Difference between reported stock and audited numbers | H9: Bank-provided Financial Statements | I9: Audited financials / CMA | J9: Quantitative | K9: Quarterly | L9: Compute Stock reported vs audited variance % then compare to threshold bands | M9: 0% variance = 0 | upto 10% = 10 | upto 20% = 20 | >20% = 30 | N9: 30
A10: EWS-007 | B10: EWS | C10: Sales turnover YoY/QoQ change % | D10: Decline in sales turnover | E10: Financial Performance | F10: Yes | G10: Monthly/quarterly sales drop | H10: Bank-provided Financial Statements | I10: Audited financials / CMA | J10: Quantitative | K10: Quarterly | L10: SalesChange% vs prior comparable period | M10: Stable/Variation upto 5% = 0 | 5-10% decline = 10 | 10-15% decline = 20 | >15% = 35 | N10: 35
A11: EWS-008 | B11: EWS | C11: EBITDA margin change % | D11: Decline in operating profit margin | E11: Financial Performance | F11: No | G11: EBITDA margin falling over periods | H11: Bank-provided Financial Statements | I11: Map in data discovery | J11: Quantitative | K11: Quarterly | L11: Compute EBITDA margin change % then compare to threshold bands | M11: Stable/Variation upto 5% = 0 | 5-10% decline = 10 | 10-15% decline = 20 | >15% = 35 | N11: 35
A12: EWS-009 | B12: EWS | C12: Debtor days vs normal | D12: Rising debtor days | E12: Financial Performance | F12: No | G12: Receivable days increasing sharply | H12: Bank-provided Financial Statements | I12: Audited financials / CMA | J12: Quantitative | K12: Quarterly | L12: DebtorDaysDelta = DebtorDays - Normal | M12: Within normal = 0 | upto 10 days = 10 | 10-20 days = 20 | >20 days = 30 | N12: 30
A13: EWS-010 | B13: EWS | C13: Inventory days vs normal | D13: Rising inventory days | E13: Financial Performance | F13: No | G13: Inventory holding period increasing | H13: Bank-provided Financial Statements | I13: Audited financials / CMA | J13: Quantitative | K13: Quarterly | L13: Compute Inventory days vs normal (delta days) then compare to threshold bands | M13: Within normal = 0 | +15-30 days = 10 | +30-60 days = 20 | +60 days = 30 | N13: 30
A14: EWS-011 | B14: EWS | C14: Creditor days vs normal | D14: Rising creditor days | E14: Financial Performance | F14: No | G14: Payables increasing beyond normal cycle | H14: Bank-provided Financial Statements | I14: Audited financials / CMA | J14: Quantitative | K14: Quarterly | L14: Compute Creditor days vs normal (delta days) then compare to threshold bands | M14: Within normal = 0 | +15-30 days = 10 | +30-60 days = 20 | +60 days = 30 | N14: 30 | O14: Link with 4th indicator - combination
A15: EWS-012 | B15: EWS | C15: Provisions/write-offs change % | D15: Large write-offs or provisions | E15: Financial Performance | F15: No | G15: Increase in bad debts / provisions | H15: Bank-provided Financial Statements | I15: Audited financials / CMA | J15: Quantitative | K15: Annual | L15: Compute Provisions/write-offs change % then compare to threshold bands | M15: ≤ 10% increase = 0 | >10% to 25% increase = 15 | >25% to 50% increase = 30 | >50% increase = 40 | N15: 40 | O15: Link with 9th
A16: EWS-013 | B16: EWS | C16: Actual vs CMA projection variance % | D16: Projected vs actual performance mismatch | E16: Financial Performance | F16: No | G16: Actual sales/profit/cash flow lower than CMA projections | H16: Bank Core System (CBS) + Financials Statement | I16: Map in data discovery | J16: Quantitative | K16: Quarterly | L16: Compute Actual vs CMA projection variance % then compare to threshold bands | M16: <5% = 0 | 5-10% = 10 | 10-15% = 20 | >15% = 35 | N16: 35
A17: EWS-014 | B17: EWS | C17: Unsecured loans change % | D17: Large unsecured loans taken | E17: Financial Performance | F17: Yes | G17: Increase in loans from promoters/group/private lenders | H17: Bank Core System (CBS) + Financials Statement | I17: Map in data discovery | J17: Quantitative | K17: Annual | L17: Compute Unsecured loans change % then compare to threshold bands | M17: ≤ 10% increase = 0 | >10% to 25% increase = 10 | >25% to 50% increase = 25 | >50% increase = 35 | N17: 35 | O17: Link with 5th
A18: EWS-015 | B18: EWS | C18: Finance cost growth vs sales growth % | D18: High finance cost growth | E18: Financial Performance | F18: No | G18: Interest cost rising faster than sales/profit | H18: Bank-provided Financial Statements | I18: Audited financials / CMA | J18: Quantitative | K18: Annual | L18: Compute Finance cost growth vs sales growth % then compare to threshold bands | M18: Stable = 0 | deterioration 10-20% = 10 | 20-40% = 20 | >40% or negative net worth = 40 | N18: 40
A19: EWS-016 | B19: EWS | C19: LC devolvement events | D19: LC devolvement | E19: Facility Conduct | F19: No | G19: Letter of credit not honoured by borrower | H19: Bank System (Trade Fin.) | I19: Trade-finance / Non-Fund Based (NFB) module | J19: Qualitative | K19: Event | L19: Classify event severity for 'LC devolvement' (no numeric calc) | M19: No event = 0 | one event = 15 | repeated events = 50 | N19: 50
A20: EWS-017 | B20: EWS | C20: BG invocation events | D20: Bank guarantee invocation | E20: Facility Conduct | F20: No | G20: BG invoked by beneficiary | H20: Bank System (Trade Fin.) | I20: Trade-finance / Non-Fund Based (NFB) module | J20: Qualitative | K20: Event | L20: Classify event severity for 'Bank guarantee invocation' (no numeric calc) | M20: No event = 0 | one event = 15 | repeated events = 50 | N20: 50
A21: EWS-018 | B21: EWS | C21: Rating notch movement | D21: Internal Rating downgrade | E21: Rating | F21: No | G21: Internal credit rating downgrade | H21: External (Subscription) | I21: Rating-agency feed / internal rating | J21: Qualitative | K21: Event | L21: Classify event severity for 'Rating downgrade' (no numeric calc) | M21: No change = 0 | one-notch downgrade = 15 | multi-notch/watchlist = 25 | below investment grade = 40 | N21: 40
A22: EWS-019 | B22: EWS | C22: Frequent change in Financial year/Accounting period | D22: Frequent change in Financial year/Accounting period of borrower | E22: Financial Reporting | F22: No | G22: Change in Financial year, unusual extension or shortening of financial year | H22: External + Internal Docs | I22: Audited financials and Ministry of Corporate Affairs (MCA) filings | J22: Qualitative | K22: Annual | L22: Count auditor/audit-year changes over a defined historical period and assess associated audit observations/qualifications | M22: No change/irregularity = 0 | Change in FY = 10 | Frequent/repeated change in FY = 25 | Change in FY accompanied by going-concern/adverse opinion or significant reporting concern = 40 | N22: 40
A23: EWS-020 | B23: EWS | C23: Auditor change events | D23: Frequent change of auditor | E23: Audit | F23: No | G23: Auditor resignation or repeated change | H23: External + Internal Docs | I23: Audited financials and Ministry of Corporate Affairs (MCA) filings | J23: Qualitative | K23: Event | L23: Classify event severity for 'Frequent change of auditors' (no numeric calc) | M23: No issue = 0 | delayed/minor qualification = 10 | material qualification/change = 25 | going concern/adverse = 40 | N23: 40
A24: EWS-021 | B24: EWS | C24: Key management change events | D24: Key personnel resignation or management exit | E24: Management Risk | F24: No | G24: Key promoter/director/CFO exit | H24: Bank-provided Financial Statements | I24: Map in data discovery | J24: Qualitative | K24: Event | L24: Classify event severity for 'Promoter resignation or management exit' (no numeric calc) | M24: No adverse change = 0 | moderate change = 10 | sudden key exit = 25 | control issue = 40 | N24: 40
A25: EWS-022 | B25: EWS | C25: % promoter shares pledged | D25: Promoter share pledge increase | E25: Management Risk | F25: No | G25: Higher pledged promoter shares | H25: External (Market/Filings) | I25: Exchange/Ministry of Corporate Affairs (MCA) filings | J25: Quantitative | K25: Event | L25: Compute % promoter shares pledged (delta) then compare to threshold bands | M25: ≤0% = 0 | >0% to ≤5% = 10 | >5% to ≤10% = 20 | >10% to ≤20% = 30 | >20% = 40 | N25: 40
A26: EWS-023 | B26: EWS | C26: Decline in promoter holding % | D26: Decline in promoter holding | E26: Management Risk | F26: No | G26: Significant reduction in promoter stake | H26: External (Market/Filings) | I26: Exchange/Ministry of Corporate Affairs (MCA) filings | J26: Quantitative | K26: Event | L26: Compute Promoter holding % (delta) then compare to threshold bands | M26: ≤0% decline = 0 | >0% to ≤5% decline = 10 | >5% to ≤10% decline = 20 | >10% to ≤20% decline = 30 | >20% decline = 40 | N26: 40
A27: EWS-024 | B27: EWS | C27: RPT value/share change % | D27: Related party transactions increase | E27: Management Risk | F27: No | G27: Large group-company transactions | H27: External + Internal Docs | I27: Audited financials and Ministry of Corporate Affairs (MCA) filings | J27: Quantitative | K27: Annual | L27: Compute RPT value/share change % then compare to threshold bands | M27: ≤0% = 0 | >0% to ≤10% = 10 | >10% to ≤25% = 25 | >25% = 40 | N27: 40
A28: EWS-025 | B28: EWS | C28: Group-entity stress classification | D28: Group entity stress | E28: Group Risk | F28: No | G28: Default, downgrade, insolvency, or stress in related/group company | H28: External + Internal Docs | I28: Map in data discovery | J28: Qualitative | K28: Event | L28: Classify event severity for 'Group entity stress' (no numeric calc) | M28: No group stress = 0 | downgrade/legal event = 20 | default/IBC in group = 40 | N28: 40
A29: EWS-026 | B29: EWS | C29: Statutory overdues | D29: Tax or statutory dues delay | E29: Compliance | F29: Yes | G29: Delay in GST, PF, TDS, income tax payment | H29: Bank Core System (CBS) + Financials Statement | I29: Map in data discovery | J29: Quantitative | K29: Monthly | L29: Compute Months of statutory dues overdue then compare to threshold bands | M29: On time = 0 | 1 month delayed = 10 | 2 months delayed = 20 | 3+ months = 35 | N29: 35
... A46: EWS-043 | B46: EWS | C46: Current Ratio | D46: Current Ratio (Current Assets / Current Liabilities) | E46: Financial Performance | F46: No | G46: Current ratio | H46: Audited financials / spreading | I46: Financial spreading | J46: Quantitative | K46: Quarterly / Annual | L46: Current Assets / Current Liabilities | M46: ≥1.33 = 0 | 1–1.33 = 10 | <1.00 = 40 | N46: 40

Sheet Functional Logic
A1: Functional Logic (per indicator)
A2: Input → Calculation/Classification → Threshold Evaluation → Raw Score → Normalised Score. Max Score links to the Master.
A4: UID | B4: Indicator | C4: Module | D4: Step 1 — Input (What to Track) | E4: Step 2 — Calculation / Classification | F4: Step 3 — Threshold Evaluation (bands) | G4: Max Score | H4: Step 4 — Raw Score rule | I4: Step 5 — Normalised Score
A5: EWS-001 | B5: Utilization % (outstanding / sanctioned) | C5: EWS | D5: CC/OD utilization above 85-90% continuously | E5: Utilization% = Utilized / Sanctioned; flag if >85% sustained | F5: <85% = 0 | 85-90% = 10 | 90-95% = 20 | >95% for 30+ days = 30 | G5: =INDEX('Indicator Master'!$N$4:$N$46,MATCH($A5,'Indicator Master'!$A$4:$A$46,0)) -> 30 | H5: Raw Score = score of the single band whose condition the borrower value satisfies; 0 if none is breached. | I5: Normalised = Raw ÷ Max Score × 100 (0–100). Fed into the Overall Score Engine.
A6: EWS-002 | B6: Count of ad-hoc limit requests (rolling 12m) | C6: EWS | D6: Temporary limit enhancement requests | E6: Compute Count of ad-hoc limit requests (rolling 12m) then compare to threshold bands | F6: 0-1 request/year = 0 | 2 = 10 | 3+ = 20 | emergency request = 30 | G6: =INDEX('Indicator Master'!$N$4:$N$46,MATCH($A6,'Indicator Master'!$A$4:$A$46,0)) -> 30 | H6: Raw Score = score of the single band whose condition the borrower value satisfies; 0 if none is breached. | I6: Normalised = Raw ÷ Max Score × 100 (0–100). Fed into the Overall Score Engine.
A7: EWS-003 | B7: Monthly sales vs credit summation | C7: EWS | D7: Reduction in monthly credits in operating account | E7: CreditChange% = (CurrentMonthCredits - Baseline)/Baseline | F7: Stable/Variation upto 5% = 0 | 5-10% decline = 10 | 10-15% decline = 20 | >15% = 35 | G7: =INDEX('Indicator Master'!$N$4:$N$46,MATCH($A7,'Indicator Master'!$A$4:$A$46,0)) -> 35 | H7: Raw Score = score of the single band whose condition the borrower value satisfies; 0 if none is breached. | I7: Normalised = Raw ÷ Max Score × 100 (0–100). Fed into the Overall Score Engine.
A8: EWS-004 | B8: Payment Default Frequency | C8: EWS | D8: Cheque returns, Cheque Bounce, ECS bounce, frequent TODs | E8: Compute Count of conduct events (rolling 90d) then compare to threshold bands | F8: 0 = 0 | 1 = 5 | 2 = 15 | 3+ in 90 days = 25 | G8: =INDEX('Indicator Master'!$N$4:$N$46,MATCH($A8,'Indicator Master'!$A$4:$A$46,0)) -> 25 | H8: Raw Score = score of the single band whose condition the borrower value satisfies; 0 if none is breached. | I8: Normalised = Raw ÷ Max Score × 100 (0–100). Fed into the Overall Score Engine.
A9: EWS-005 | B9: Repayment source classification | C9: EWS | D9: Repayment from unrelated parties or group accounts | E9: Classify event severity for 'Change in repayment source' (no numeric calc) | F9: Own operating cash flow = 0 | group support = 15 | unrelated source = 30 | repeated third-party payments = 40 | G9: =INDEX('Indicator Master'!$N$4:$N$46,MATCH($A9,'Indicator Master'!$A$4:$A$46,0)) -> 40 | H9: Raw Score = score of the single band whose condition the borrower value satisfies; 0 if none is breached. | I9: Normalised = Raw ÷ Max Score × 100 (0–100). Fed into the Overall Score Engine.
A10: EWS-006 | B10: Stock reported vs audited variance % | C10: EWS | D10: Difference between reported stock and audited numbers | E10: Compute Stock reported vs audited variance % then compare to threshold bands | F10: 0% variance = 0 | upto 10% = 10 | upto 20% = 20 | >20% = 30 | G10: =INDEX('Indicator Master'!$N$4:$N$46,MATCH($A10,'Indicator Master'!$A$4:$A$46,0)) -> 30 | H10: Raw Score = score of the single band whose condition the borrower value satisfies; 0 if none is breached. | I10: Normalised = Raw ÷ Max Score × 100 (0–100). Fed into the Overall Score Engine.
A11: EWS-007 | B11: Sales turnover YoY/QoQ change % | C11: EWS | D11: Monthly/quarterly sales drop | E11: SalesChange% vs prior comparable period | F11: Stable/Variation upto 5% = 0 | 5-10% decline = 10 | 10-15% decline = 20 | >15% = 35 | G11: =INDEX('Indicator Master'!$N$4:$N$46,MATCH($A11,'Indicator Master'!$A$4:$A$46,0)) -> 35 | H11: Raw Score = score of the single band whose condition the borrower value satisfies; 0 if none is breached. | I11: Normalised = Raw ÷ Max Score × 100 (0–100). Fed into the Overall Score Engine.
A12: EWS-008 | B12: EBITDA margin change % | C12: EWS | D12: EBITDA margin falling over periods | E12: Compute EBITDA margin change % then compare to threshold bands | F12: Stable/Variation upto 5% = 0 | 5-10% decline = 10 | 10-15% decline = 20 | >15% = 35 | G12: =INDEX('Indicator Master'!$N$4:$N$46,MATCH($A12,'Indicator Master'!$A$4:$A$46,0)) -> 35 | H12: Raw Score = score of the single band whose condition the borrower value satisfies; 0 if none is breached. | I12: Normalised = Raw ÷ Max Score × 100 (0–100). Fed into the Overall Score Engine.
A13: EWS-009 | B13: Debtor days vs normal | C13: EWS | D13: Receivable days increasing sharply | E13: DebtorDaysDelta = DebtorDays - Normal | F13: Within normal = 0 | upto 10 days = 10 | 10-20 days = 20 | >20 days = 30 | G13: =INDEX('Indicator Master'!$N$4:$N$46,MATCH($A13,'Indicator Master'!$A$4:$A$46,0)) -> 30 | H13: Raw Score = score of the single band whose condition the borrower value satisfies; 0 if none is breached. | I13: Normalised = Raw ÷ Max Score × 100 (0–100). Fed into the Overall Score Engine.
A14: EWS-010 | B14: Inventory days vs normal | C14: EWS | D14: Inventory holding period increasing | E14: Compute Inventory days vs normal (delta days) then compare to threshold bands | F14: Within normal = 0 | +15-30 days = 10 | +30-60 days = 20 | +60 days = 30 | G14: =INDEX('Indicator Master'!$N$4:$N$46,MATCH($A14,'Indicator Master'!$A$4:$A$46,0)) -> 30 | H14: Raw Score = score of the single band whose condition the borrower value satisfies; 0 if none is breached. | I14: Normalised = Raw ÷ Max Score × 100 (0–100). Fed into the Overall Score Engine.
A15: EWS-011 | B15: Creditor days vs normal | C15: EWS | D15: Payables increasing beyond normal cycle | E15: Compute Creditor days vs normal (delta days) then compare to threshold bands | F15: Within normal = 0 | +15-30 days = 10 | +30-60 days = 20 | +60 days = 30 | G15: =INDEX('Indicator Master'!$N$4:$N$46,MATCH($A15,'Indicator Master'!$A$4:$A$46,0)) -> 30 | H15: Raw Score = score of the single band whose condition the borrower value satisfies; 0 if none is breached. | I15: Normalised = Raw ÷ Max Score × 100 (0–100). Fed into the Overall Score Engine.
A16: EWS-012 | B16: Provisions/write-offs change % | C16: EWS | D16: Increase in bad debts / provisions | E16: Compute Provisions/write-offs change % then compare to threshold bands | F16: ≤ 10% increase = 0 | >10% to 25% increase = 15 | >25% to 50% increase = 30 | >50% increase = 40 | G16: =INDEX('Indicator Master'!$N$4:$N$46,MATCH($A16,'Indicator Master'!$A$4:$A$46,0)) -> 40 | H16: Raw Score = score of the single band whose condition the borrower value satisfies; 0 if none is breached. | I16: Normalised = Raw ÷ Max Score × 100 (0–100). Fed into the Overall Score Engine.
... A47: EWS-043 | B47: Current Ratio | C47: EWS | D47: Current ratio | E47: Current Assets / Current Liabilities | F47: ≥1.33 = 0 | 1–1.33 = 10 | <1.00 = 40 | G47: =INDEX('Indicator Master'!$N$4:$N$46,MATCH($A47,'Indicator Master'!$A$4:$A$46,0)) -> 40 | H47: Raw Score = score of the single band whose condition the borrower value satisfies; 0 if none is breached. | I47: Normalised = Raw ÷ Max Score × 100 (0–100). Fed into the Overall Score Engine.

Sheet Scoring Engine (Rules)
A1: Threshold & Scoring Engine — Machine-Readable Rules + Remedial Playbook
A2: One row per band. Rule Type/Lower/Upper/Operator are data-type driven; Normalised@Band & Is-Max are live; key = UID|Raw.
A4: UID | B4: Indicator | C4: Module | D4: Metric / Input | E4: Band Order | F4: Condition (verbatim) | G4: Rule Type | H4: Lower Bound | I4: Upper Bound | J4: Operator | K4: Raw Score | L4: Normalised @ Band | M4: Is Max Band | N4: Critical Event Flag | O4: What it signals & likely drivers | P4: Remedial action plan (step-by-step) | Q4: Primary owner | R4: key (helper)
A5: EWS-001 | B5: Utilization % (outstanding / sanctioned) | C5: EWS | D5: CC/OD utilization above 85-90% continuously | E5: 1 | F5: <85% | G5: Percent Threshold | I5: 85 | J5: < upper | K5: 0 | L5: =$K5/INDEX('Indicator Master'!$N$4:$N$46,MATCH($A5,'Indicator Master'!$A$4:$A$46,0))*'Risk Bands (Config)'!$B$5 -> 0 | M5: =IF($K5=INDEX('Indicator Master'!$N$4:$N$46,MATCH($A5,'Indicator Master'!$A$4:$A$46,0)),1,0) -> 0 | O5: Normal — utilisation below 85%; comfortable headroom on working-capital limits. | P5: No remedial action required. Continue routine monitoring at the standard review cycle and record the reading. | Q5: RM (routine) | R5: =$A5&"|"&$K5 -> EWS-001|0
A6: EWS-001 | B6: Utilization % (outstanding / sanctioned) | C6: EWS | D6: CC/OD utilization above 85-90% continuously | E6: 2 | F6: 85-90% | G6: Percent Range | H6: 85 | I6: 90 | J6: ≥ lower & < upper | K6: 10 | L6: =$K6/INDEX('Indicator Master'!$N$4:$N$46,MATCH($A6,'Indicator Master'!$A$4:$A$46,0))*'Risk Bands (Config)'!$B$5 -> 33.333333 | M6: =IF($K6=INDEX('Indicator Master'!$N$4:$N$46,MATCH($A6,'Indicator Master'!$A$4:$A$46,0)),1,0) -> 0 | O6: Early warning — utilisation 85–90%; mild tightening, usually genuine sales/WC growth or a seasonal build-up. | P6: 1) RM to confirm the cause (seasonal vs structural). 2) Check stock/receivables statements support the drawings. 3) Flag for the next review. | Q6: RM + Credit Analyst | R6: =$A6&"|"&$K6 -> EWS-001|10
A7: EWS-001 | B7: Utilization % (outstanding / sanctioned) | C7: EWS | D7: CC/OD utilization above 85-90% continuously | E7: 3 | F7: 90-95% | G7: Percent Range | H7: 90 | I7: 95 | J7: ≥ lower & < upper | K7: 20 | L7: =$K7/INDEX('Indicator Master'!$N$4:$N$46,MATCH($A7,'Indicator Master'!$A$4:$A$46,0))*'Risk Bands (Config)'!$B$5 -> 66.666667 | M7: =IF($K7=INDEX('Indicator Master'!$N$4:$N$46,MATCH($A7,'Indicator Master'!$A$4:$A$46,0)),1,0) -> 0 | O7: Elevated concern — utilisation 90–95% sustained; limits may be inadequate or the WC cycle is stretching (slow debtors/inventory). | P7: 1) Reassess the WC assessment and drawing power on updated financials. 2) Verify no diversion via a turnover-routing check. 3) Move to monthly monitoring; consider a limit review. | Q7: Credit Committee / Zonal Credit | R7: =$A7&"|"&$K7 -> EWS-001|20
A8: EWS-001 | B8: Utilization % (outstanding / sanctioned) | C8: EWS | D8: CC/OD utilization above 85-90% continuously | E8: 4 | F8: >95% for 30+ days | G8: Percent Threshold | H8: 95 | J8: ≥ lower (sustained 30+ days) | K8: 30 | L8: =$K8/INDEX('Indicator Master'!$N$4:$N$46,MATCH($A8,'Indicator Master'!$A$4:$A$46,0))*'Risk Bands (Config)'!$B$5 -> 100 | M8: =IF($K8=INDEX('Indicator Master'!$N$4:$N$46,MATCH($A8,'Indicator Master'!$A$4:$A$46,0)),1,0) -> 1 | O8: Severe / critical — utilisation above 95% for 30+ days; chronic over-reliance — possible inability to rotate WC, or diversion/ever-greening. | P8: 1) Restrict fresh drawals pending review. 2) Investigate diversion (routing gaps, ad-hoc pattern). 3) Full viability / limit-rationalisation review; escalate to Credit. | Q8: Credit Head / Risk | R8: =$A8&"|"&$K8 -> EWS-001|30
A9: EWS-002 | B9: Count of ad-hoc limit requests (rolling 12m) | C9: EWS | D9: Temporary limit enhancement requests | E9: 1 | F9: 0-1 request/year | G9: Count Range | H9: 0 | I9: 1 | J9: ≥ lower & ≤ upper | K9: 0 | L9: =$K9/INDEX('Indicator Master'!$N$4:$N$46,MATCH($A9,'Indicator Master'!$A$4:$A$46,0))*'Risk Bands (Config)'!$B$5 -> 0 | M9: =IF($K9=INDEX('Indicator Master'!$N$4:$N$46,MATCH($A9,'Indicator Master'!$A$4:$A$46,0)),1,0) -> 0 | O9: Normal — at most one ad-hoc request in the year; no pattern. | P9: No remedial action required. Continue routine monitoring at the standard review cycle and record the reading. | Q9: RM (routine) | R9: =$A9&"|"&$K9 -> EWS-002|0
A10: EWS-002 | B10: Count of ad-hoc limit requests (rolling 12m) | C10: EWS | D10: Temporary limit enhancement requests | E10: 2 | F10: 2 | G10: Count Exact | H10: 2 | I10: 2 | J10: exactly = value | K10: 10 | L10: =$K10/INDEX('Indicator Master'!$N$4:$N$46,MATCH($A10,'Indicator Master'!$A$4:$A$46,0))*'Risk Bands (Config)'!$B$5 -> 33.333333 | M10: =IF($K10=INDEX('Indicator Master'!$N$4:$N$46,MATCH($A10,'Indicator Master'!$A$4:$A$46,0)),1,0) -> 0 | O10: Early warning — two ad-hoc requests; occasional cash-flow mismatch. | P10: 1) Ascertain the reason for each request. 2) Check whether permanent WC is under-assessed. 3) Grant only against a documented need. | Q10: RM + Credit Analyst | R10: =$A10&"|"&$K10 -> EWS-002|10
A11: EWS-002 | B11: Count of ad-hoc limit requests (rolling 12m) | C11: EWS | D11: Temporary limit enhancement requests | E11: 3 | F11: 3+ | G11: Count Threshold | H11: 3 | J11: ≥ lower | K11: 20 | L11: =$K11/INDEX('Indicator Master'!$N$4:$N$46,MATCH($A11,'Indicator Master'!$A$4:$A$46,0))*'Risk Bands (Config)'!$B$5 -> 66.666667 | M11: =IF($K11=INDEX('Indicator Master'!$N$4:$N$46,MATCH($A11,'Indicator Master'!$A$4:$A$46,0)),1,0) -> 0 | O11: Elevated concern — three or more ad-hoc requests; recurring liquidity gaps suggest a structural WC shortfall. | P11: 1) Reassess permanent WC limits versus turnover. 2) Decline routine ad-hocs; require promoter funds for genuine gaps. 3) Tighten conduct review. | Q11: Credit Committee / Zonal Credit | R11: =$A11&"|"&$K11 -> EWS-002|20
A12: EWS-002 | B12: Count of ad-hoc limit requests (rolling 12m) | C12: EWS | D12: Temporary limit enhancement requests | E12: 4 | F12: emergency request | G12: Event flag | J12: category | K12: 30 | L12: =$K12/INDEX('Indicator Master'!$N$4:$N$46,MATCH($A12,'Indicator Master'!$A$4:$A$46,0))*'Risk Bands (Config)'!$B$5 -> 100 | M12: =IF($K12=INDEX('Indicator Master'!$N$4:$N$46,MATCH($A12,'Indicator Master'!$A$4:$A$46,0)),1,0) -> 1 | O12: Severe / critical — an emergency / out-of-cycle request; acute liquidity stress. | P12: 1) Treat as a stress trigger; obtain an immediate cash-flow statement. 2) Do not fund without security/comfort. 3) Escalate to Credit. | Q12: Credit Head / Risk | R12: =$A12&"|"&$K12 -> EWS-002|30
A13: EWS-003 | B13: Monthly sales vs credit summation | C13: EWS | D13: Reduction in monthly credits in operating account | E13: 1 | F13: Stable/Variation upto 5% | G13: Percent Threshold | I13: 5 | J13: < upper | K13: 0 | L13: =$K13/INDEX('Indicator Master'!$N$4:$N$46,MATCH($A13,'Indicator Master'!$A$4:$A$46,0))*'Risk Bands (Config)'!$B$5 -> 0 | M13: =IF($K13=INDEX('Indicator Master'!$N$4:$N$46,MATCH($A13,'Indicator Master'!$A$4:$A$46,0)),1,0) -> 0 | O13: Normal — operating-account credits stable or rising; sales routing intact. | P13: No remedial action required. Continue routine monitoring at the standard review cycle and record the reading. | Q13: RM (routine) | R13: =$A13&"|"&$K13 -> EWS-003|0
A14: EWS-003 | B14: Monthly sales vs credit summation | C14: EWS | D14: Reduction in monthly credits in operating account | E14: 2 | F14: 5-10% decline | G14: Percent Range | H14: 5 | I14: 10 | J14: ≥ lower & < upper | K14: 10 | L14: =$K14/INDEX('Indicator Master'!$N$4:$N$46,MATCH($A14,'Indicator Master'!$A$4:$A$46,0))*'Risk Bands (Config)'!$B$5 -> 28.571429 | M14: =IF($K14=INDEX('Indicator Master'!$N$4:$N$46,MATCH($A14,'Indicator Master'!$A$4:$A$46,0)),1,0) -> 0 | O14: Early warning — credits down 10–20% vs baseline; early softening or partial routing to another bank. | P14: 1) Reconcile account credits to GST/sales. 2) Ask the RM whether routing has shifted. 3) Note the trend for next review. | Q14: Relationship Manager (Branch) | R14: =$A14&"|"&$K14 -> EWS-003|10
A15: EWS-003 | B15: Monthly sales vs credit summation | C15: EWS | D15: Reduction in monthly credits in operating account | E15: 3 | F15: 10-15% decline | G15: Percent Range | H15: 10 | I15: 15 | J15: ≥ lower & < upper | K15: 20 | L15: =$K15/INDEX('Indicator Master'!$N$4:$N$46,MATCH($A15,'Indicator Master'!$A$4:$A$46,0))*'Risk Bands (Config)'!$B$5 -> 57.142857 | M15: =IF($K15=INDEX('Indicator Master'!$N$4:$N$46,MATCH($A15,'Indicator Master'!$A$4:$A$46,0)),1,0) -> 0 | O15: Elevated concern — credits down 20–40%; material drop — genuine sales fall or turnover being diverted elsewhere. | P15: 1) Stipulate proportionate turnover routing through the bank. 2) Verify sales via GST returns. 3) Monitor monthly credits vs sales. | Q15: RM + Credit Analyst | R15: =$A15&"|"&$K15 -> EWS-003|20
A16: EWS-003 | B16: Monthly sales vs credit summation | C16: EWS | D16: Reduction in monthly credits in operating account | E16: 4 | F16: >15% decline | G16: Percent Threshold | H16: 15 | J16: > lower | K16: 35 | L16: =$K16/INDEX('Indicator Master'!$N$4:$N$46,MATCH($A16,'Indicator Master'!$A$4:$A$46,0))*'Risk Bands (Config)'!$B$5 -> 100 | M16: =IF($K16=INDEX('Indicator Master'!$N$4:$N$46,MATCH($A16,'Indicator Master'!$A$4:$A$46,0)),1,0) -> 1 | N16: CRITICAL EVENT | O16: Severe / critical — credits down >40%; severe — likely sales collapse or systematic diversion of turnover. | P16: 1) Investigate diversion to other lenders; consider an escrow / TRA mechanism. 2) Commission an end-use/turnover audit. 3) Escalate to Credit; recall if diversion confirmed. | Q16: Credit Head / Risk / Fraud | R16: =$A16&"|"&$K16 -> EWS-003|35
A17: EWS-004 | B17: Payment Default Frequency | C17: EWS | D17: Cheque returns, Cheque Bounce, ECS bounce, frequent TODs | E17: 1 | F17: 0 | G17: Count Exact | H17: 0 | I17: 0 | J17: exactly = value | K17: 0 | L17: =$K17/INDEX('Indicator Master'!$N$4:$N$46,MATCH($A17,'Indicator Master'!$A$4:$A$46,0))*'Risk Bands (Config)'!$B$5 -> 0 | M17: =IF($K17=INDEX('Indicator Master'!$N$4:$N$46,MATCH($A17,'Indicator Master'!$A$4:$A$46,0)),1,0) -> 0 | O17: Normal — no conduct events in the window; clean account behaviour. | P17: No remedial action required. Continue routine monitoring at the standard review cycle and record the reading. | Q17: RM (routine) | R17: =$A17&"|"&$K17 -> EWS-004|0
A18: EWS-004 | B18: Payment Default Frequency | C18: EWS | D18: Cheque returns, Cheque Bounce, ECS bounce, frequent TODs | E18: 2 | F18: 1 | G18: Count Exact | H18: 1 | I18: 1 | J18: exactly = value | K18: 5 | L18: =$K18/INDEX('Indicator Master'!$N$4:$N$46,MATCH($A18,'Indicator Master'!$A$4:$A$46,0))*'Risk Bands (Config)'!$B$5 -> 20 | M18: =IF($K18=INDEX('Indicator Master'!$N$4:$N$46,MATCH($A18,'Indicator Master'!$A$4:$A$46,0)),1,0) -> 0 | O18: Early warning — one conduct event; isolated slip, likely a timing mismatch. | P18: 1) Note the event and reason. 2) Caution the borrower informally. 3) Watch the next cycle. | Q18: Relationship Manager (Branch) | R18: =$A18&"|"&$K18 -> EWS-004|5
A19: EWS-004 | B19: Payment Default Frequency | C19: EWS | D19: Cheque returns, Cheque Bounce, ECS bounce, frequent TODs | E19: 3 | F19: 2 | G19: Count Exact | H19: 2 | I19: 2 | J19: exactly = value | K19: 15 | L19: =$K19/INDEX('Indicator Master'!$N$4:$N$46,MATCH($A19,'Indicator Master'!$A$4:$A$46,0))*'Risk Bands (Config)'!$B$5 -> 60 | M19: =IF($K19=INDEX('Indicator Master'!$N$4:$N$46,MATCH($A19,'Indicator Master'!$A$4:$A$46,0)),1,0) -> 0 | O19: Elevated concern — two conduct events; a pattern is forming — recurring liquidity or discipline issue. | P19: 1) Obtain a written explanation. 2) Enforce due-date discipline / standing instructions. 3) Place on the watch-list. | Q19: RM + Credit Analyst | R19: =$A19&"|"&$K19 -> EWS-004|15
A20: EWS-004 | B20: Payment Default Frequency | C20: EWS | D20: Cheque returns, Cheque Bounce, ECS bounce, frequent TODs | E20: 4 | F20: 3+ in 90 days | G20: Count Threshold | H20: 3 | J20: ≥ lower | K20: 25 | L20: =$K20/INDEX('Indicator Master'!$N$4:$N$46,MATCH($A20,'Indicator Master'!$A$4:$A$46,0))*'Risk Bands (Config)'!$B$5 -> 100 | M20: =IF($K20=INDEX('Indicator Master'!$N$4:$N$46,MATCH($A20,'Indicator Master'!$A$4:$A$46,0)),1,0) -> 1 | O20: Severe / critical — three or more events in 90 days; persistent irregularity signalling stress. | P20: 1) Treat as incipient stress; SMA tagging as per days. 2) Obtain a corrective cash-flow plan. 3) Escalate to Credit; review provisioning. | Q20: Credit Head / Risk | R20: =$A20&"|"&$K20 -> EWS-004|25
A21: EWS-005 | B21: Repayment source classification | C21: EWS | D21: Repayment from unrelated parties or group accounts | E21: 1 | F21: Own operating cash flow | G21: Ordinal Classification | J21: category | K21: 0 | L21: =$K21/INDEX('Indicator Master'!$N$4:$N$46,MATCH($A21,'Indicator Master'!$A$4:$A$46,0))*'Risk Bands (Config)'!$B$5 -> 0 | M21: =IF($K21=INDEX('Indicator Master'!$N$4:$N$46,MATCH($A21,'Indicator Master'!$A$4:$A$46,0)),1,0) -> 0 | O21: Normal — repayments from the borrower's own operating cash flows; healthy. | P21: No remedial action required. Continue routine monitoring at the standard review cycle and record the reading. | Q21: RM (routine) | R21: =$A21&"|"&$K21 -> EWS-005|0
A22: EWS-005 | B22: Repayment source classification | C22: EWS | D22: Repayment from unrelated parties or group accounts | E22: 2 | F22: group support | G22: Ordinal Classification | J22: category | K22: 15 | L22: =$K22/INDEX('Indicator Master'!$N$4:$N$46,MATCH($A22,'Indicator Master'!$A$4:$A$46,0))*'Risk Bands (Config)'!$B$5 -> 37.5 | M22: =IF($K22=INDEX('Indicator Master'!$N$4:$N$46,MATCH($A22,'Indicator Master'!$A$4:$A$46,0)),1,0) -> 0 | O22: Elevated concern — repayments supported by group funds; servicing not fully self-generated. | P22: 1) Question reliance on group support; assess standalone viability. 2) Seek an undertaking on the arrangement. 3) Monitor. | Q22: RM + Credit Analyst | R22: =$A22&"|"&$K22 -> EWS-005|15
A23: EWS-005 | B23: Repayment source classification | C23: EWS | D23: Repayment from unrelated parties or group accounts | E23: 3 | F23: unrelated source | G23: Ordinal Classification | J23: category | K23: 30 | L23: =$K23/INDEX('Indicator Master'!$N$4:$N$46,MATCH($A23,'Indicator Master'!$A$4:$A$46,0))*'Risk Bands (Config)'!$B$5 -> 75 | M23: =IF($K23=INDEX('Indicator Master'!$N$4:$N$46,MATCH($A23,'Indicator Master'!$A$4:$A$46,0)),1,0) -> 0 | O23: High concern — repayments from an unrelated/third-party source; questionable sustainability. | P23: 1) Investigate the third-party source and fund flow. 2) Reassess viability and repayment capacity. 3) Tighten; escalate to Credit. | Q23: Credit + Risk | R23: =$A23&"|"&$K23 -> EWS-005|30
A24: EWS-005 | B24: Repayment source classification | C24: EWS | D24: Repayment from unrelated parties or group accounts | E24: 4 | F24: repeated third-party payments | G24: Ordinal Classification | J24: category | K24: 40 | L24: =$K24/INDEX('Indicator Master'!$N$4:$N$46,MATCH($A24,'Indicator Master'!$A$4:$A$46,0))*'Risk Bands (Config)'!$B$5 -> 100 | M24: =IF($K24=INDEX('Indicator Master'!$N$4:$N$46,MATCH($A24,'Indicator Master'!$A$4:$A$46,0)),1,0) -> 1 | O24: Severe / critical — repeated third-party payments; classic ever-greening / round-tripping risk. | P24: 1) Treat as suspected ever-greening; order a fund-flow/forensic review. 2) Freeze incremental exposure. 3) Escalate for corrective / exit action. | Q24: Credit Head / Risk / Fraud | R24: =$A24&"|"&$K24 -> EWS-005|40
A25: EWS-006 | B25: Stock reported vs audited variance % | C25: EWS | D25: Difference between reported stock and audited numbers | E25: 1 | F25: 0% variance | G25: Percent Threshold | I25: 0 | J25: ≤ upper | K25: 0 | L25: =$K25/INDEX('Indicator Master'!$N$4:$N$46,MATCH($A25,'Indicator Master'!$A$4:$A$46,0))*'Risk Bands (Config)'!$B$5 -> 0 | M25: =IF($K25=INDEX('Indicator Master'!$N$4:$N$46,MATCH($A25,'Indicator Master'!$A$4:$A$46,0)),1,0) -> 0 | O25: Normal — no variance between reported and audited stock; reliable reporting. | P25: No remedial action required. Continue routine monitoring at the standard review cycle and record the reading. | Q25: RM (routine) | R25: =$A25&"|"&$K25 -> EWS-006|0
A26: EWS-006 | B26: Stock reported vs audited variance % | C26: EWS | D26: Difference between reported stock and audited numbers | E26: 2 | F26: upto 10% | G26: Percent Range | H26: 0 | I26: 10 | J26: > lower & ≤ upper | K26: 10 | L26: =$K26/INDEX('Indicator Master'!$N$4:$N$46,MATCH($A26,'Indicator Master'!$A$4:$A$46,0))*'Risk Bands (Config)'!$B$5 -> 33.333333 | M26: =IF($K26=INDEX('Indicator Master'!$N$4:$N$46,MATCH($A26,'Indicator Master'!$A$4:$A$46,0)),1,0) -> 0 | O26: Early warning — up to 10% variance; minor reconciliation gap, likely timing or method. | P26: 1) Reconcile the statement to audited figures. 2) Seek clarification on the small gap. | Q26: RM + Credit Analyst | R26: =$A26&"|"&$K26 -> EWS-006|10
A27: EWS-006 | B27: Stock reported vs audited variance % | C27: EWS | D27: Difference between reported stock and audited numbers | E27: 3 | F27: upto 20% | G27: Percent Range | H27: 10 | I27: 20 | J27: > lower & ≤ upper | K27: 20 | L27: =$K27/INDEX('Indicator Master'!$N$4:$N$46,MATCH($A27,'Indicator Master'!$A$4:$A$46,0))*'Risk Bands (Config)'!$B$5 -> 66.666667 | M27: =IF($K27=INDEX('Indicator Master'!$N$4:$N$46,MATCH($A27,'Indicator Master'!$A$4:$A$46,0)),1,0) -> 0 | O27: Elevated concern — 10–20% variance; material overstatement of DP securities emerging. | P27: 1) Order a stock/receivables audit. 2) Recompute drawing power on verified stock. 3) Monitor. | Q27: Credit Committee / Zonal Credit | R27: =$A27&"|"&$K27 -> EWS-006|20
A28: EWS-006 | B28: Stock reported vs audited variance % | C28: EWS | D28: Difference between reported stock and audited numbers | E28: 4 | F28: >20% | G28: Percent Threshold | H28: 20 | J28: > lower | K28: 30 | L28: =$K28/INDEX('Indicator Master'!$N$4:$N$46,MATCH($A28,'Indicator Master'!$A$4:$A$46,0))*'Risk Bands (Config)'!$B$5 -> 100 | M28: =IF($K28=INDEX('Indicator Master'!$N$4:$N$46,MATCH($A28,'Indicator Master'!$A$4:$A$46,0)),1,0) -> 1 | O28: Severe / critical — >20% variance; large overstatement — inflated drawing power / possible window-dressing. | P28: 1) Commission an independent stock audit; correct the DP. 2) Reduce limits to the corrected DP. 3) Treat inflated DP as diversion risk; escalate to Credit. | Q28: Credit Head / Risk | R28: =$A28&"|"&$K28 -> EWS-006|30
A29: EWS-007 | B29: Sales turnover YoY/QoQ change % | C29: EWS | D29: Monthly/quarterly sales drop | E29: 1 | F29: Stable/Variation upto 5% | G29: Percent Threshold | I29: 5 | J29: < upper | K29: 0 | L29: =$K29/INDEX('Indicator Master'!$N$4:$N$46,MATCH($A29,'Indicator Master'!$A$4:$A$46,0))*'Risk Bands (Config)'!$B$5 -> 0 | M29: =IF($K29=INDEX('Indicator Master'!$N$4:$N$46,MATCH($A29,'Indicator Master'!$A$4:$A$46,0)),1,0) -> 0 | O29: Normal — turnover stable or growing; demand intact. | P29: No remedial action required. Continue routine monitoring at the standard review cycle and record the reading. | Q29: RM (routine) | R29: =$A29&"|"&$K29 -> EWS-007|0
A30: EWS-007 | B30: Sales turnover YoY/QoQ change % | C30: EWS | D30: Monthly/quarterly sales drop | E30: 2 | F30: 5-10% decline | G30: Percent Range | H30: 5 | I30: 10 | J30: ≥ lower & < upper | K30: 10 | L30: =$K30/INDEX('Indicator Master'!$N$4:$N$46,MATCH($A30,'Indicator Master'!$A$4:$A$46,0))*'Risk Bands (Config)'!$B$5 -> 28.571429 | M30: =IF($K30=INDEX('Indicator Master'!$N$4:$N$46,MATCH($A30,'Indicator Master'!$A$4:$A$46,0)),1,0) -> 0 | O30: Early warning — turnover down 10–20%; early demand softening or a one-off. | P30: 1) Reassess projections and the WC cycle. 2) RM engagement; management action note. 3) Monthly review. | Q30: Relationship Manager (Branch) | R30: =$A30&"|"&$K30 -> EWS-007|10
A31: EWS-007 | B31: Sales turnover YoY/QoQ change % | C31: EWS | D31: Monthly/quarterly sales drop | E31: 3 | F31: 10-15% decline | G31: Percent Range | H31: 10 | I31: 15 | J31: ≥ lower & < upper | K31: 20 | L31: =$K31/INDEX('Indicator Master'!$N$4:$N$46,MATCH($A31,'Indicator Master'!$A$4:$A$46,0))*'Risk Bands (Config)'!$B$5 -> 57.142857 | M31: =IF($K31=INDEX('Indicator Master'!$N$4:$N$46,MATCH($A31,'Indicator Master'!$A$4:$A$46,0)),1,0) -> 0 | O31: Elevated concern — turnover down 20–40%; a genuine downturn or loss of key customers. | P31: 1) Reassess repayment capacity and viability with a sensitivity run. 2) Consider whether restructuring is needed. 3) Escalate to Credit. | Q31: RM + Credit Analyst | R31: =$A31&"|"&$K31 -> EWS-007|20
A32: EWS-007 | B32: Sales turnover YoY/QoQ change % | C32: EWS | D32: Monthly/quarterly sales drop | E32: 4 | F32: >15% decline | G32: Percent Threshold | H32: 15 | J32: > lower | K32: 35 | L32: =$K32/INDEX('Indicator Master'!$N$4:$N$46,MATCH($A32,'Indicator Master'!$A$4:$A$46,0))*'Risk Bands (Config)'!$B$5 -> 100 | M32: =IF($K32=INDEX('Indicator Master'!$N$4:$N$46,MATCH($A32,'Indicator Master'!$A$4:$A$46,0)),1,0) -> 1 | N32: CRITICAL EVENT | O32: Severe / critical — turnover down >40% or a loss; severe demand/operational deterioration. | P32: 1) Full viability / TEV review. 2) Assess restructuring / rephasement. 3) Provisioning review; escalate to Credit Committee. | Q32: Credit Head / Risk | R32: =$A32&"|"&$K32 -> EWS-007|35
A33: EWS-008 | B33: EBITDA margin change % | C33: EWS | D33: EBITDA margin falling over periods | E33: 1 | F33: Stable/Variation upto 5% | G33: Percent Threshold | I33: 5 | J33: < upper | K33: 0 | L33: =$K33/INDEX('Indicator Master'!$N$4:$N$46,MATCH($A33,'Indicator Master'!$A$4:$A$46,0))*'Risk Bands (Config)'!$B$5 -> 0 | M33: =IF($K33=INDEX('Indicator Master'!$N$4:$N$46,MATCH($A33,'Indicator Master'!$A$4:$A$46,0)),1,0) -> 0 | O33: Normal — EBITDA margin stable; profitability intact. | P33: No remedial action required. Continue routine monitoring at the standard review cycle and record the reading. | Q33: RM (routine) | R33: =$A33&"|"&$K33 -> EWS-008|0
A34: EWS-008 | B34: EBITDA margin change % | C34: EWS | D34: EBITDA margin falling over periods | E34: 2 | F34: 5-10% decline | G34: Percent Range | H34: 5 | I34: 10 | J34: ≥ lower & < upper | K34: 10 | L34: =$K34/INDEX('Indicator Master'!$N$4:$N$46,MATCH($A34,'Indicator Master'!$A$4:$A$46,0))*'Risk Bands (Config)'!$B$5 -> 28.571429 | M34: =IF($K34=INDEX('Indicator Master'!$N$4:$N$46,MATCH($A34,'Indicator Master'!$A$4:$A$46,0)),1,0) -> 0 | O34: Early warning — margin fell 10–20%; cost inflation or pricing pressure beginning. | P34: 1) Analyse cost vs price drivers. 2) Reassess DSCR on updated numbers. 3) Monitor. | Q34: Relationship Manager (Branch) | R34: =$A34&"|"&$K34 -> EWS-008|10
A35: EWS-008 | B35: EBITDA margin change % | C35: EWS | D35: EBITDA margin falling over periods | E35: 3 | F35: 10-15% decline | G35: Percent Range | H35: 10 | I35: 15 | J35: ≥ lower & < upper | K35: 20 | L35: =$K35/INDEX('Indicator Master'!$N$4:$N$46,MATCH($A35,'Indicator Master'!$A$4:$A$46,0))*'Risk Bands (Config)'!$B$5 -> 57.142857 | M35: =IF($K35=INDEX('Indicator Master'!$N$4:$N$46,MATCH($A35,'Indicator Master'!$A$4:$A$46,0)),1,0) -> 0 | O35: Elevated concern — margin fell 20–40%; material erosion of debt-servicing ability. | P35: 1) Reassess repayment capacity and viability. 2) Enhanced monitoring. 3) Escalate to Credit. | Q35: RM + Credit Analyst | R35: =$A35&"|"&$K35 -> EWS-008|20
A36: EWS-008 | B36: EBITDA margin change % | C36: EWS | D36: EBITDA margin falling over periods | E36: 4 | F36: >15% decline | G36: Percent Threshold | H36: 15 | J36: ≥ lower (or loss) | K36: 35 | L36: =$K36/INDEX('Indicator Master'!$N$4:$N$46,MATCH($A36,'Indicator Master'!$A$4:$A$46,0))*'Risk Bands (Config)'!$B$5 -> 100 | M36: =IF($K36=INDEX('Indicator Master'!$N$4:$N$46,MATCH($A36,'Indicator Master'!$A$4:$A$46,0)),1,0) -> 1 | O36: Severe / critical — margin fell >40% or turned to a loss; severe profitability collapse. | P36: 1) Full viability review; assess restructuring. 2) Provisioning review. 3) Escalate to Credit Committee. | Q36: Credit Head / Risk | R36: =$A36&"|"&$K36 -> EWS-008|35
A37: EWS-009 | B37: Debtor days vs normal | C37: EWS | D37: Receivable days increasing sharply | E37: 1 | F37: Within normal | G37: Delta Days Threshold | H37: 0 | I37: 0 | J37: exactly = value | K37: 0 | L37: =$K37/INDEX('Indicator Master'!$N$4:$N$46,MATCH($A37,'Indicator Master'!$A$4:$A$46,0))*'Risk Bands (Config)'!$B$5 -> 0 | M37: =IF($K37=INDEX('Indicator Master'!$N$4:$N$46,MATCH($A37,'Indicator Master'!$A$4:$A$46,0)),1,0) -> 0 | O37: Normal — debtor days within norm; receivables turning normally. | P37: No remedial action required. Continue routine monitoring at the standard review cycle and record the reading. | Q37: RM (routine) | R37: =$A37&"|"&$K37 -> EWS-009|0
A38: EWS-009 | B38: Debtor days vs normal | C38: EWS | D38: Receivable days increasing sharply | E38: 2 | F38: upto 10 days | G38: Delta Days Threshold | I38: 10 | J38: < upper | K38: 10 | L38: =$K38/INDEX('Indicator Master'!$N$4:$N$46,MATCH($A38,'Indicator Master'!$A$4:$A$46,0))*'Risk Bands (Config)'!$B$5 -> 33.333333 | M38: =IF($K38=INDEX('Indicator Master'!$N$4:$N$46,MATCH($A38,'Indicator Master'!$A$4:$A$46,0)),1,0) -> 0 | O38: Early warning — debtor days +15–30; early slowdown — collection lag or slow-moving receivables. | P38: 1) Review the debtor ageing. 2) Identify overdue/slow items. 3) Monitor. | Q38: RM + Credit Analyst | R38: =$A38&"|"&$K38 -> EWS-009|10
A39: EWS-009 | B39: Debtor days vs normal | C39: EWS | D39: Receivable days increasing sharply | E39: 3 | F39: 10-20 days | G39: Delta Days Range | H39: 10 | I39: 20 | J39: ≥ lower & < upper | K39: 20 | L39: =$K39/INDEX('Indicator Master'!$N$4:$N$46,MATCH($A39,'Indicator Master'!$A$4:$A$46,0))*'Risk Bands (Config)'!$B$5 -> 66.666667 | M39: =IF($K39=INDEX('Indicator Master'!$N$4:$N$46,MATCH($A39,'Indicator Master'!$A$4:$A$46,0)),1,0) -> 0 | O39: Elevated concern — debtor days +30–60; material tie-up of working capital in receivables. | P39: 1) Order a receivables audit. 2) Exclude >90-day receivables from DP. 3) Monitor monthly. | Q39: Credit Committee / Zonal Credit | R39: =$A39&"|"&$K39 -> EWS-009|20
A40: EWS-009 | B40: Debtor days vs normal | C40: EWS | D40: Receivable days increasing sharply | E40: 4 | F40: >20 days | G40: Delta Days Threshold | H40: 60 | J40: ≥ lower | K40: 30 | L40: =$K40/INDEX('Indicator Master'!$N$4:$N$46,MATCH($A40,'Indicator Master'!$A$4:$A$46,0))*'Risk Bands (Config)'!$B$5 -> 100 | M40: =IF($K40=INDEX('Indicator Master'!$N$4:$N$46,MATCH($A40,'Indicator Master'!$A$4:$A$46,0)),1,0) -> 1 | O40: Severe / critical — debtor days +60; severe — aged/blocked receivables, possible overstatement or non-moving stock. | P40: 1) Independent receivables audit; recompute DP. 2) Assess related-party / fictitious build-up. 3) Escalate to Credit; forensic if diversion suspected. | Q40: Credit Head / Risk | R40: =$A40&"|"&$K40 -> EWS-009|30
A41: EWS-010 | B41: Inventory days vs normal | C41: EWS | D41: Inventory holding period increasing | E41: 1 | F41: Within norm | G41: Delta Days Threshold | I41: 15 | J41: < upper | K41: 0 | L41: =$K41/INDEX('Indicator Master'!$N$4:$N$46,MATCH($A41,'Indicator Master'!$A$4:$A$46,0))*'Risk Bands (Config)'!$B$5 -> 0 | M41: =IF($K41=INDEX('Indicator Master'!$N$4:$N$46,MATCH($A41,'Indicator Master'!$A$4:$A$46,0)),1,0) -> 0 | O41: Normal — inventory days within norm; stock turning normally. | P41: No remedial action required. Continue routine monitoring at the standard review cycle and record the reading. | Q41: RM (routine) | R41: =$A41&"|"&$K41 -> EWS-010|0
A42: EWS-010 | B42: Inventory days vs normal | C42: EWS | D42: Inventory holding period increasing | E42: 2 | F42: +15-30 days | G42: Delta Days Range | H42: 15 | I42: 30 | J42: ≥ lower & < upper | K42: 10 | L42: =$K42/INDEX('Indicator Master'!$N$4:$N$46,MATCH($A42,'Indicator Master'!$A$4:$A$46,0))*'Risk Bands (Config)'!$B$5 -> 33.333333 | M42: =IF($K42=INDEX('Indicator Master'!$N$4:$N$46,MATCH($A42,'Indicator Master'!$A$4:$A$46,0)),1,0) -> 0 | O42: Early warning — inventory days +15–30; early slowdown — collection lag or slow-moving stock. | P42: 1) Review the inventory ageing. 2) Identify overdue/slow items. 3) Monitor. | Q42: RM + Credit Analyst | R42: =$A42&"|"&$K42 -> EWS-010|10
A43: EWS-010 | B43: Inventory days vs normal | C43: EWS | D43: Inventory holding period increasing | E43: 3 | F43: +30-60 days | G43: Delta Days Range | H43: 30 | I43: 60 | J43: ≥ lower & < upper | K43: 20 | L43: =$K43/INDEX('Indicator Master'!$N$4:$N$46,MATCH($A43,'Indicator Master'!$A$4:$A$46,0))*'Risk Bands (Config)'!$B$5 -> 66.666667 | M43: =IF($K43=INDEX('Indicator Master'!$N$4:$N$46,MATCH($A43,'Indicator Master'!$A$4:$A$46,0)),1,0) -> 0 | O43: Elevated concern — inventory days +30–60; material tie-up of working capital in stock. | P43: 1) Order a stock audit. 2) Exclude >90-day stock from DP. 3) Monitor monthly. | Q43: Credit Committee / Zonal Credit | R43: =$A43&"|"&$K43 -> EWS-010|20
A44: EWS-010 | B44: Inventory days vs normal | C44: EWS | D44: Inventory holding period increasing | E44: 4 | F44: +60 days | G44: Delta Days Threshold | H44: 60 | J44: ≥ lower | K44: 30 | L44: =$K44/INDEX('Indicator Master'!$N$4:$N$46,MATCH($A44,'Indicator Master'!$A$4:$A$46,0))*'Risk Bands (Config)'!$B$5 -> 100 | M44: =IF($K44=INDEX('Indicator Master'!$N$4:$N$46,MATCH($A44,'Indicator Master'!$A$4:$A$46,0)),1,0) -> 1 | O44: Severe / critical — inventory days +60; severe — aged/blocked stock, possible overstatement or non-moving stock. | P44: 1) Independent stock audit; recompute DP. 2) Assess related-party / fictitious build-up. 3) Escalate to Credit; forensic if diversion suspected. | Q44: Credit Head / Risk | R44: =$A44&"|"&$K44 -> EWS-010|30
A45: EWS-011 | B45: Creditor days vs normal | C45: EWS | D45: Payables increasing beyond normal cycle | E45: 1 | F45: Within norm | G45: Delta Days Threshold | I45: 15 | J45: < upper | K45: 0 | L45: =$K45/INDEX('Indicator Master'!$N$4:$N$46,MATCH($A45,'Indicator Master'!$A$4:$A$46,0))*'Risk Bands (Config)'!$B$5 -> 0 | M45: =IF($K45=INDEX('Indicator Master'!$N$4:$N$46,MATCH($A45,'Indicator Master'!$A$4:$A$46,0)),1,0) -> 0 | O45: Normal — creditor days within norm; supplier terms stable. | P45: No remedial action required. Continue routine monitoring at the standard review cycle and record the reading. | Q45: RM (routine) | R45: =$A45&"|"&$K45 -> EWS-011|0
A46: EWS-011 | B46: Creditor days vs normal | C46: EWS | D46: Payables increasing beyond normal cycle | E46: 2 | F46: +15-30 days | G46: Delta Days Range | H46: 15 | I46: 30 | J46: ≥ lower & < upper | K46: 10 | L46: =$K46/INDEX('Indicator Master'!$N$4:$N$46,MATCH($A46,'Indicator Master'!$A$4:$A$46,0))*'Risk Bands (Config)'!$B$5 -> 33.333333 | M46: =IF($K46=INDEX('Indicator Master'!$N$4:$N$46,MATCH($A46,'Indicator Master'!$A$4:$A$46,0)),1,0) -> 0 | O46: Early warning — creditor days +15–30; stretching payables — mild liquidity tightening or negotiated terms. | P46: 1) Review payables ageing and reason. 2) Check for supply-side disputes. 3) Monitor. | Q46: RM + Credit Analyst | R46: =$A46&"|"&$K46 -> EWS-011|10
A47: EWS-011 | B47: Creditor days vs normal | C47: EWS | D47: Payables increasing beyond normal cycle | E47: 3 | F47: +30-60 days | G47: Delta Days Range | H47: 30 | I47: 60 | J47: ≥ lower & < upper | K47: 20 | L47: =$K47/INDEX('Indicator Master'!$N$4:$N$46,MATCH($A47,'Indicator Master'!$A$4:$A$46,0))*'Risk Bands (Config)'!$B$5 -> 66.666667 | M47: =IF($K47=INDEX('Indicator Master'!$N$4:$N$46,MATCH($A47,'Indicator Master'!$A$4:$A$46,0)),1,0) -> 0 | O47: Elevated concern — creditor days +30–60; material stretch — supplier pressure / liquidity strain. | P47: 1) Assess liquidity behind the stretch. 2) Engage the borrower on supplier position. 3) Reassess WC cycle; monitor monthly. | Q47: Credit Committee / Zonal Credit | R47: =$A47&"|"&$K47 -> EWS-011|20
A48: EWS-011 | B48: Creditor days vs normal | C48: EWS | D48: Payables increasing beyond normal cycle | E48: 4 | F48: +60 days | G48: Delta Days Threshold | H48: 60 | J48: ≥ lower | K48: 30 | L48: =$K48/INDEX('Indicator Master'!$N$4:$N$46,MATCH($A48,'Indicator Master'!$A$4:$A$46,0))*'Risk Bands (Config)'!$B$5 -> 100 | M48: =IF($K48=INDEX('Indicator Master'!$N$4:$N$46,MATCH($A48,'Indicator Master'!$A$4:$A$46,0)),1,0) -> 1 | O48: Severe / critical — creditor days +60; severe — suppliers unpaid, risk of supply disruption. | P48: 1) Reassess viability and supply continuity. 2) Corrective cash-flow plan. 3) Escalate to Credit. | Q48: Credit Head / Risk | R48: =$A48&"|"&$K48 -> EWS-011|30
A49: EWS-012 | B49: Provisions/write-offs change % | C49: EWS | D49: Increase in bad debts / provisions | E49: 1 | F49: ≤ 10% increase | G49: Percent Threshold | I49: 10 | J49: ≤ upper | K49: 0 | L49: =$K49/INDEX('Indicator Master'!$N$4:$N$46,MATCH($A49,'Indicator Master'!$A$4:$A$46,0))*'Risk Bands (Config)'!$B$5 -> 0 | M49: =IF($K49=INDEX('Indicator Master'!$N$4:$N$46,MATCH($A49,'Indicator Master'!$A$4:$A$46,0)),1,0) -> 0 | O49: Normal — provisions/write-offs increased ≤10%; within the normal range. | P49: No remedial action required. Continue routine monitoring at the standard review cycle and record the reading. | Q49: RM (routine) | R49: =$A49&"|"&$K49 -> EWS-012|0
A50: EWS-012 | B50: Provisions/write-offs change % | C50: EWS | D50: Increase in bad debts / provisions | E50: 2 | F50: >10% to 25% increase | G50: Percent Range | H50: 10 | I50: 25 | J50: > lower & ≤ upper | K50: 15 | L50: =$K50/INDEX('Indicator Master'!$N$4:$N$46,MATCH($A50,'Indicator Master'!$A$4:$A$46,0))*'Risk Bands (Config)'!$B$5 -> 37.5 | M50: =IF($K50=INDEX('Indicator Master'!$N$4:$N$46,MATCH($A50,'Indicator Master'!$A$4:$A$46,0)),1,0) -> 0 | O50: Elevated concern — provisions up >10–25%; early rise in credit costs / doubtful items. | P50: 1) Analyse what is being provided for. 2) Reassess recoverability. 3) Monitor. | Q50: RM + Credit Analyst | R50: =$A50&"|"&$K50 -> EWS-012|15
A51: EWS-012 | B51: Provisions/write-offs change % | C51: EWS | D51: Increase in bad debts / provisions | E51: 3 | F51: >25% to 50% increase | G51: Percent Range | H51: 25 | I51: 50 | J51: > lower & ≤ upper | K51: 30 | L51: =$K51/INDEX('Indicator Master'!$N$4:$N$46,MATCH($A51,'Indicator Master'!$A$4:$A$46,0))*'Risk Bands (Config)'!$B$5 -> 75 | M51: =IF($K51=INDEX('Indicator Master'!$N$4:$N$46,MATCH($A51,'Indicator Master'!$A$4:$A$46,0)),1,0) -> 0 | O51: High concern — provisions up >25–50%; material deterioration in asset quality. | P51: 1) Reassess viability given the losses. 2) Enhanced monitoring. 3) Escalate to Credit. | Q51: Credit Committee / Zonal Credit | R51: =$A51&"|"&$K51 -> EWS-012|30
A52: EWS-012 | B52: Provisions/write-offs change % | C52: EWS | D52: Increase in bad debts / provisions | E52: 4 | F52: >50% increase | G52: Percent Threshold | H52: 50 | J52: > lower | K52: 40 | L52: =$K52/INDEX('Indicator Master'!$N$4:$N$46,MATCH($A52,'Indicator Master'!$A$4:$A$46,0))*'Risk Bands (Config)'!$B$5 -> 100 | M52: =IF($K52=INDEX('Indicator Master'!$N$4:$N$46,MATCH($A52,'Indicator Master'!$A$4:$A$46,0)),1,0) -> 1 | O52: Severe / critical — provisions up >50%; severe — large recognised losses/write-offs. | P52: 1) Full reassessment; likely restructuring/recovery track. 2) Provisioning review. 3) Escalate to Credit Committee. | Q52: Credit Head / Risk | R52: =$A52&"|"&$K52 -> EWS-012|40
A53: EWS-013 | B53: Actual vs CMA projection variance % | C53: EWS | D53: Actual sales/profit/cash flow lower than CMA projections | E53: 1 | F53: <5% | G53: Percent Threshold | I53: 5 | J53: < upper | K53: 0 | L53: =$K53/INDEX('Indicator Master'!$N$4:$N$46,MATCH($A53,'Indicator Master'!$A$4:$A$46,0))*'Risk Bands (Config)'!$B$5 -> 0 | M53: =IF($K53=INDEX('Indicator Master'!$N$4:$N$46,MATCH($A53,'Indicator Master'!$A$4:$A$46,0)),1,0) -> 0 | O53: Normal — actuals within 5% of CMA projections; performing to plan. | P53: No remedial action required. Continue routine monitoring at the standard review cycle and record the reading. | Q53: RM (routine) | R53: =$A53&"|"&$K53 -> EWS-013|0
A54: EWS-013 | B54: Actual vs CMA projection variance % | C54: EWS | D54: Actual sales/profit/cash flow lower than CMA projections | E54: 2 | F54: 5-10% | G54: Percent Range | H54: 5 | I54: 10 | J54: ≥ lower & < upper | K54: 10 | L54: =$K54/INDEX('Indicator Master'!$N$4:$N$46,MATCH($A54,'Indicator Master'!$A$4:$A$46,0))*'Risk Bands (Config)'!$B$5 -> 28.571429 | M54: =IF($K54=INDEX('Indicator Master'!$N$4:$N$46,MATCH($A54,'Indicator Master'!$A$4:$A$46,0)),1,0) -> 0 | O54: Early warning — 5–15% variance; mild under-performance vs projections. | P54: 1) Analyse the variance. 2) Revisit assumptions with the RM. 3) Monitor. | Q54: Relationship Manager (Branch) | R54: =$A54&"|"&$K54 -> EWS-013|10
A55: EWS-013 | B55: Actual vs CMA projection variance % | C55: EWS | D55: Actual sales/profit/cash flow lower than CMA projections | E55: 3 | F55: 10-15% | G55: Percent Range | H55: 10 | I55: 15 | J55: ≥ lower & < upper | K55: 20 | L55: =$K55/INDEX('Indicator Master'!$N$4:$N$46,MATCH($A55,'Indicator Master'!$A$4:$A$46,0))*'Risk Bands (Config)'!$B$5 -> 57.142857 | M55: =IF($K55=INDEX('Indicator Master'!$N$4:$N$46,MATCH($A55,'Indicator Master'!$A$4:$A$46,0)),1,0) -> 0 | O55: Elevated concern — 15–30% variance; material deviation — projections likely optimistic or performance slipping. | P55: 1) Reassess limits/viability on realistic numbers. 2) Enhanced monitoring. 3) Escalate to Credit. | Q55: RM + Credit Analyst | R55: =$A55&"|"&$K55 -> EWS-013|20
A56: EWS-013 | B56: Actual vs CMA projection variance % | C56: EWS | D56: Actual sales/profit/cash flow lower than CMA projections | E56: 4 | F56: >15% | G56: Percent Threshold | H56: 15 | J56: > lower | K56: 35 | L56: =$K56/INDEX('Indicator Master'!$N$4:$N$46,MATCH($A56,'Indicator Master'!$A$4:$A$46,0))*'Risk Bands (Config)'!$B$5 -> 100 | M56: =IF($K56=INDEX('Indicator Master'!$N$4:$N$46,MATCH($A56,'Indicator Master'!$A$4:$A$46,0)),1,0) -> 1 | O56: Severe / critical — >30% variance; severe deviation from the sanctioned plan. | P56: 1) Full reassessment on actuals. 2) Corrective plan. 3) Escalate to Credit Committee. | Q56: Credit Head / Risk | R56: =$A56&"|"&$K56 -> EWS-013|35
A57: EWS-014 | B57: Unsecured loans change % | C57: EWS | D57: Increase in loans from promoters/group/private lenders | E57: 1 | F57: ≤ 10% increase | G57: Percent Threshold | I57: 10 | J57: ≤ upper | K57: 0 | L57: =$K57/INDEX('Indicator Master'!$N$4:$N$46,MATCH($A57,'Indicator Master'!$A$4:$A$46,0))*'Risk Bands (Config)'!$B$5 -> 0 | M57: =IF($K57=INDEX('Indicator Master'!$N$4:$N$46,MATCH($A57,'Indicator Master'!$A$4:$A$46,0)),1,0) -> 0 | O57: Normal — unsecured/related-party borrowings up ≤10%; not material. | P57: No remedial action required. Continue routine monitoring at the standard review cycle and record the reading. | Q57: RM (routine) | R57: =$A57&"|"&$K57 -> EWS-014|0
A58: EWS-014 | B58: Unsecured loans change % | C58: EWS | D58: Increase in loans from promoters/group/private lenders | E58: 2 | F58: >10% to 25% increase | G58: Percent Range | H58: 10 | I58: 25 | J58: > lower & ≤ upper | K58: 10 | L58: =$K58/INDEX('Indicator Master'!$N$4:$N$46,MATCH($A58,'Indicator Master'!$A$4:$A$46,0))*'Risk Bands (Config)'!$B$5 -> 28.571429 | M58: =IF($K58=INDEX('Indicator Master'!$N$4:$N$46,MATCH($A58,'Indicator Master'!$A$4:$A$46,0)),1,0) -> 0 | O58: Early warning — up >10–25%; some reliance on unsecured funds — check purpose. | P58: 1) Assess whether these are quasi-equity or a diversion. 2) Seek subordination/NDU. 3) Monitor. | Q58: Relationship Manager (Branch) | R58: =$A58&"|"&$K58 -> EWS-014|10
A59: EWS-014 | B59: Unsecured loans change % | C59: EWS | D59: Increase in loans from promoters/group/private lenders | E59: 3 | F59: >25% to 50% increase | G59: Percent Range | H59: 25 | I59: 50 | J59: > lower & ≤ upper | K59: 25 | L59: =$K59/INDEX('Indicator Master'!$N$4:$N$46,MATCH($A59,'Indicator Master'!$A$4:$A$46,0))*'Risk Bands (Config)'!$B$5 -> 71.428571 | M59: =IF($K59=INDEX('Indicator Master'!$N$4:$N$46,MATCH($A59,'Indicator Master'!$A$4:$A$46,0)),1,0) -> 0 | O59: High concern — up >25–50%; material rise — hidden leverage or quasi-equity substituting for capital. | P59: 1) Stipulate subordination of unsecured loans; reassess leverage. 2) Tighten terms. 3) Escalate to Credit. | Q59: Credit + Risk | R59: =$A59&"|"&$K59 -> EWS-014|25
A60: EWS-014 | B60: Unsecured loans change % | C60: EWS | D60: Increase in loans from promoters/group/private lenders | E60: 4 | F60: >50% increase | G60: Percent Threshold | H60: 50 | J60: > lower | K60: 35 | L60: =$K60/INDEX('Indicator Master'!$N$4:$N$46,MATCH($A60,'Indicator Master'!$A$4:$A$46,0))*'Risk Bands (Config)'!$B$5 -> 100 | M60: =IF($K60=INDEX('Indicator Master'!$N$4:$N$46,MATCH($A60,'Indicator Master'!$A$4:$A$46,0)),1,0) -> 1 | N60: CRITICAL EVENT | O60: Severe / critical — up >50%; severe — heavy high-cost/unsecured borrowing indicating funding stress or diversion. | P60: [CRITICAL] 1) Treat as a material adverse change; forensic review of fund flow. 2) Immediate escalation to Credit Committee. 3) Corrective / possible recall. NOTE: CRITICAL indicator — worst band fires the Critical Override; final status escalates to Critical regardless of the average. | Q60: Credit Head / Risk (immediate) | R60: =$A60&"|"&$K60 -> EWS-014|35
A61: EWS-015 | B61: Finance cost growth vs sales growth % | C61: EWS | D61: Interest cost rising faster than sales/profit | E61: 1 | F61: Stable | G61: Percent Threshold | I61: 10 | J61: < upper | K61: 0 | L61: =$K61/INDEX('Indicator Master'!$N$4:$N$46,MATCH($A61,'Indicator Master'!$A$4:$A$46,0))*'Risk Bands (Config)'!$B$5 -> 0 | M61: =IF($K61=INDEX('Indicator Master'!$N$4:$N$46,MATCH($A61,'Indicator Master'!$A$4:$A$46,0)),1,0) -> 0 | O61: Normal — finance cost growing in line with sales; leverage stable. | P61: No remedial action required. Continue routine monitoring at the standard review cycle and record the reading. | Q61: RM (routine) | R61: =$A61&"|"&$K61 -> EWS-015|0
A62: EWS-015 | B62: Finance cost growth vs sales growth % | C62: EWS | D62: Interest cost rising faster than sales/profit | E62: 2 | F62: deterioration 10-20% | G62: Percent Range | H62: 10 | I62: 20 | J62: ≥ lower & < upper | K62: 10 | L62: =$K62/INDEX('Indicator Master'!$N$4:$N$46,MATCH($A62,'Indicator Master'!$A$4:$A$46,0))*'Risk Bands (Config)'!$B$5 -> 25 | M62: =IF($K62=INDEX('Indicator Master'!$N$4:$N$46,MATCH($A62,'Indicator Master'!$A$4:$A$46,0)),1,0) -> 0 | O62: Early warning — finance cost outpacing sales by 10–20%; early over-leverage. | P62: 1) Analyse debt build-up vs sales. 2) Reassess DSCR. 3) Monitor. | Q62: Relationship Manager (Branch) | R62: =$A62&"|"&$K62 -> EWS-015|10
A63: EWS-015 | B63: Finance cost growth vs sales growth % | C63: EWS | D63: Interest cost rising faster than sales/profit | E63: 3 | F63: 20-40% | G63: Percent Range | H63: 20 | I63: 40 | J63: ≥ lower & < upper | K63: 20 | L63: =$K63/INDEX('Indicator Master'!$N$4:$N$46,MATCH($A63,'Indicator Master'!$A$4:$A$46,0))*'Risk Bands (Config)'!$B$5 -> 50 | M63: =IF($K63=INDEX('Indicator Master'!$N$4:$N$46,MATCH($A63,'Indicator Master'!$A$4:$A$46,0)),1,0) -> 0 | O63: Elevated concern — outpacing by 20–40%; material — debt/interest rising faster than the business can carry. | P63: 1) Reassess leverage and repayment capacity. 2) Enhanced monitoring. 3) Escalate to Credit. | Q63: RM + Credit Analyst | R63: =$A63&"|"&$K63 -> EWS-015|20
A64: EWS-015 | B64: Finance cost growth vs sales growth % | C64: EWS | D64: Interest cost rising faster than sales/profit | E64: 4 | F64: >40% or negative net worth | G64: Percent Threshold | H64: 40 | J64: ≥ lower (or negative net worth) | K64: 40 | L64: =$K64/INDEX('Indicator Master'!$N$4:$N$46,MATCH($A64,'Indicator Master'!$A$4:$A$46,0))*'Risk Bands (Config)'!$B$5 -> 100 | M64: =IF($K64=INDEX('Indicator Master'!$N$4:$N$46,MATCH($A64,'Indicator Master'!$A$4:$A$46,0)),1,0) -> 1 | O64: Severe / critical — >40% gap or negative net worth; severe over-leverage / capital erosion. | P64: 1) Full viability review; capital/net-worth check. 2) Restructuring assessment. 3) Escalate to Credit Committee. | Q64: Credit Head / Risk | R64: =$A64&"|"&$K64 -> EWS-015|40
A65: EWS-016 | B65: LC devolvement events | C65: EWS | D65: Letter of credit not honoured by borrower | E65: 1 | F65: No event | G65: Ordinal Classification | J65: category | K65: 0 | L65: =$K65/INDEX('Indicator Master'!$N$4:$N$46,MATCH($A65,'Indicator Master'!$A$4:$A$46,0))*'Risk Bands (Config)'!$B$5 -> 0 | M65: =IF($K65=INDEX('Indicator Master'!$N$4:$N$46,MATCH($A65,'Indicator Master'!$A$4:$A$46,0)),1,0) -> 0 | O65: Normal — no LC devolvement; trade obligations honoured. | P65: No remedial action required. Continue routine monitoring at the standard review cycle and record the reading. | Q65: RM (routine) | R65: =$A65&"|"&$K65 -> EWS-016|0
A66: EWS-016 | B66: LC devolvement events | C66: EWS | D66: Letter of credit not honoured by borrower | E66: 2 | F66: one event | G66: Ordinal Classification | J66: category | K66: 15 | L66: =$K66/INDEX('Indicator Master'!$N$4:$N$46,MATCH($A66,'Indicator Master'!$A$4:$A$46,0))*'Risk Bands (Config)'!$B$5 -> 30 | M66: =IF($K66=INDEX('Indicator Master'!$N$4:$N$46,MATCH($A66,'Indicator Master'!$A$4:$A$46,0)),1,0) -> 0 | O66: Early warning — one minor devolvement; isolated timing issue. | P66: 1) Ascertain the reason; regularise promptly. 2) Review LC limits and margin. 3) Monitor. | Q66: Relationship Manager (Branch) | R66: =$A66&"|"&$K66 -> EWS-016|15
A67: EWS-016 | B67: LC devolvement events | C67: EWS | D67: Letter of credit not honoured by borrower | E67: 3 | F67: repeated events | G67: Ordinal Classification | J67: category | K67: 50 | L67: =$K67/INDEX('Indicator Master'!$N$4:$N$46,MATCH($A67,'Indicator Master'!$A$4:$A$46,0))*'Risk Bands (Config)'!$B$5 -> 100 | M67: =IF($K67=INDEX('Indicator Master'!$N$4:$N$46,MATCH($A67,'Indicator Master'!$A$4:$A$46,0)),1,0) -> 1 | O67: Severe / critical — repeated devolvement/invocation; the borrower cannot honour trade commitments — clear liquidity distress. | P67: 1) Treat as stress; reduce non-fund exposure, seek cash margin. 2) Reassess WC. 3) Escalate to Credit; provisioning review. | Q67: Credit Head / Risk | R67: =$A67&"|"&$K67 -> EWS-016|50
A68: EWS-017 | B68: BG invocation events | C68: EWS | D68: BG invoked by beneficiary | E68: 1 | F68: No event | G68: Ordinal Classification | J68: category (analyst-selected) | K68: 0 | L68: =$K68/INDEX('Indicator Master'!$N$4:$N$46,MATCH($A68,'Indicator Master'!$A$4:$A$46,0))*'Risk Bands (Config)'!$B$5 -> 0 | M68: =IF($K68=INDEX('Indicator Master'!$N$4:$N$46,MATCH($A68,'Indicator Master'!$A$4:$A$46,0)),1,0) -> 0 | O68: Normal — no BG invocation; guarantees performing. | P68: No remedial action required. Continue routine monitoring at the standard review cycle and record the reading. | Q68: RM (routine) | R68: =$A68&"|"&$K68 -> EWS-017|0
A69: EWS-017 | B69: BG invocation events | C69: EWS | D69: BG invoked by beneficiary | E69: 2 | F69: one event | G69: Ordinal Classification | J69: category (analyst-selected) | K69: 15 | L69: =$K69/INDEX('Indicator Master'!$N$4:$N$46,MATCH($A69,'Indicator Master'!$A$4:$A$46,0))*'Risk Bands (Config)'!$B$5 -> 30 | M69: =IF($K69=INDEX('Indicator Master'!$N$4:$N$46,MATCH($A69,'Indicator Master'!$A$4:$A$46,0)),1,0) -> 0 | O69: Early warning — a single BG invocation; the borrower failed to honour one guarantee obligation. | P69: 1) Ascertain the reason and regularise; assess the underlying contract risk. 2) Tighten margin/monitoring. 3) Monitor. | Q69: Relationship Manager (Branch) | R69: =$A69&"|"&$K69 -> EWS-017|15
A70: EWS-017 | B70: BG invocation events | C70: EWS | D70: BG invoked by beneficiary | E70: 3 | F70: repeated events | G70: Ordinal Classification | J70: category (analyst-selected) | K70: 50 | L70: =$K70/INDEX('Indicator Master'!$N$4:$N$46,MATCH($A70,'Indicator Master'!$A$4:$A$46,0))*'Risk Bands (Config)'!$B$5 -> 100 | M70: =IF($K70=INDEX('Indicator Master'!$N$4:$N$46,MATCH($A70,'Indicator Master'!$A$4:$A$46,0)),1,0) -> 1 | O70: Severe / critical — repeated BG invocations; recurring failure to honour guarantees, a serious performance/financial default. | P70: 1) Treat crystallised liabilities as stress; reduce non-fund exposure and seek cash margin. 2) Reassess WC and viability. 3) Escalate to Credit; provisioning review. | Q70: Credit Head / Risk | R70: =$A70&"|"&$K70 -> EWS-017|50
A71: EWS-018 | B71: Rating notch movement | C71: EWS | D71: Internal credit rating downgrade | E71: 1 | F71: No change | G71: Ordinal Classification | J71: category | K71: 0 | L71: =$K71/INDEX('Indicator Master'!$N$4:$N$46,MATCH($A71,'Indicator Master'!$A$4:$A$46,0))*'Risk Bands (Config)'!$B$5 -> 0 | M71: =IF($K71=INDEX('Indicator Master'!$N$4:$N$46,MATCH($A71,'Indicator Master'!$A$4:$A$46,0)),1,0) -> 0 | O71: Normal — no rating change; credit profile stable. | P71: No remedial action required. Continue routine monitoring at the standard review cycle and record the reading. | Q71: RM (routine) | R71: =$A71&"|"&$K71 -> EWS-018|0
A72: EWS-018 | B72: Rating notch movement | C72: EWS | D72: Internal credit rating downgrade | E72: 2 | F72: one-notch downgrade | G72: Ordinal Classification | J72: category | K72: 15 | L72: =$K72/INDEX('Indicator Master'!$N$4:$N$46,MATCH($A72,'Indicator Master'!$A$4:$A$46,0))*'Risk Bands (Config)'!$B$5 -> 37.5 | M72: =IF($K72=INDEX('Indicator Master'!$N$4:$N$46,MATCH($A72,'Indicator Master'!$A$4:$A$46,0)),1,0) -> 0 | O72: Elevated concern — one-notch downgrade; mild deterioration perceived by the agency. | P72: 1) Obtain the rating rationale. 2) Reassess pricing/covenants. 3) Enhanced monitoring. | Q72: RM + Credit Analyst | R72: =$A72&"|"&$K72 -> EWS-018|15
A73: EWS-018 | B73: Rating notch movement | C73: EWS | D73: Internal credit rating downgrade | E73: 3 | F73: multi-notch/watchlist | G73: Ordinal Classification | J73: category | K73: 25 | L73: =$K73/INDEX('Indicator Master'!$N$4:$N$46,MATCH($A73,'Indicator Master'!$A$4:$A$46,0))*'Risk Bands (Config)'!$B$5 -> 62.5 | M73: =IF($K73=INDEX('Indicator Master'!$N$4:$N$46,MATCH($A73,'Indicator Master'!$A$4:$A$46,0)),1,0) -> 0 | O73: Elevated concern — multi-notch downgrade or watchlist; material weakening of the credit profile. | P73: 1) Reassess exposure and security. 2) Consider a limit review. 3) Escalate to Credit. | Q73: Credit Committee / Zonal Credit | R73: =$A73&"|"&$K73 -> EWS-018|25
A74: EWS-018 | B74: Rating notch movement | C74: EWS | D74: Internal credit rating downgrade | E74: 4 | F74: below investment grade | G74: Ordinal Classification | J74: category | K74: 40 | L74: =$K74/INDEX('Indicator Master'!$N$4:$N$46,MATCH($A74,'Indicator Master'!$A$4:$A$46,0))*'Risk Bands (Config)'!$B$5 -> 100 | M74: =IF($K74=INDEX('Indicator Master'!$N$4:$N$46,MATCH($A74,'Indicator Master'!$A$4:$A$46,0)),1,0) -> 1 | O74: Severe / critical — downgraded below investment grade; severe — market view of default risk. | P74: 1) Full review; corrective / exit plan. 2) Reprice/secure as feasible. 3) Escalate to Credit Committee. | Q74: Credit Head / Risk | R74: =$A74&"|"&$K74 -> EWS-018|40
A75: EWS-019 | B75: Frequent change in Financial year/Accounting period | C75: EWS | D75: Change in Financial year, unusual extension or shortening of financial year | E75: 1 | F75: No change/irregularity | G75: Ordinal Classification | J75: category | K75: 0 | L75: =$K75/INDEX('Indicator Master'!$N$4:$N$46,MATCH($A75,'Indicator Master'!$A$4:$A$46,0))*'Risk Bands (Config)'!$B$5 -> 0 | M75: =IF($K75=INDEX('Indicator Master'!$N$4:$N$46,MATCH($A75,'Indicator Master'!$A$4:$A$46,0)),1,0) -> 0 | O75: Normal — no change in financial year/auditor; reporting stable. | P75: No remedial action required. Continue routine monitoring at the standard review cycle and record the reading. | Q75: RM (routine) | R75: =$A75&"|"&$K75 -> EWS-019|0
A76: EWS-019 | B76: Frequent change in Financial year/Accounting period | C76: EWS | D76: Change in Financial year, unusual extension or shortening of financial year | E76: 2 | F76: Change in FY | G76: Ordinal Classification | J76: category | K76: 10 | L76: =$K76/INDEX('Indicator Master'!$N$4:$N$46,MATCH($A76,'Indicator Master'!$A$4:$A$46,0))*'Risk Bands (Config)'!$B$5 -> 25 | M76: =IF($K76=INDEX('Indicator Master'!$N$4:$N$46,MATCH($A76,'Indicator Master'!$A$4:$A$46,0)),1,0) -> 0 | O76: Early warning — a single change with no adverse observation; likely benign. | P76: 1) Confirm the reason is benign. 2) Ensure comparability of periods. 3) Monitor. | Q76: Relationship Manager (Branch) | R76: =$A76&"|"&$K76 -> EWS-019|10
... A86: EWS-021 | B86: Key management change events | C86: EWS | D86: Key promoter/director/CFO exit | E86: 4 | F86: control issue | G86: Ordinal Classification | J86: category | K86: 40 | L86: =$K86/INDEX('Indicator Master'!$N$4:$N$46,MATCH($A86,'Indicator Master'!$A$4:$A$46,0))*'Risk Bands (Config)'!$B$5 -> 100 | M86: =IF($K86=INDEX('Indicator Master'!$N$4:$N$46,MATCH($A86,'Indicator Master'!$A$4:$A$46,0)),1,0) -> 1 | O86: Severe / critical — a control issue (dispute/loss of control); severe governance red flag. | P86: 1) Treat as a material adverse change. 2) Reassess exposure. 3) Escalate to Credit Committee. | Q86: Credit Head / Risk | R86: =$A86&"|"&$K86 -> EWS-021|40
A87: EWS-022 | B87: % promoter shares pledged | C87: EWS | D87: Higher pledged promoter shares | E87: 1 | F87: ≤0% | G87: Percent Threshold | I87: 0 | J87: ≤ upper | K87: 0 | L87: =$K87/INDEX('Indicator Master'!$N$4:$N$46,MATCH($A87,'Indicator Master'!$A$4:$A$46,0))*'Risk Bands (Config)'!$B$5 -> 0 | M87: =IF($K87=INDEX('Indicator Master'!$N$4:$N$46,MATCH($A87,'Indicator Master'!$A$4:$A$46,0)),1,0) -> 0 | O87: Normal — no promoter pledge; promoter capital unencumbered. | P87: No remedial action required. Continue routine monitoring at the standard review cycle and record the reading. | Q87: RM (routine) | R87: =$A87&"|"&$K87 -> EWS-022|0
A88: EWS-022 | B88: % promoter shares pledged | C88: EWS | D88: Higher pledged promoter shares | E88: 2 | F88: >0% to ≤5% | G88: Percent Range | H88: 0 | I88: 5 | J88: > lower & ≤ upper | K88: 10 | L88: =$K88/INDEX('Indicator Master'!$N$4:$N$46,MATCH($A88,'Indicator Master'!$A$4:$A$46,0))*'Risk Bands (Config)'!$B$5 -> 25 | M88: =IF($K88=INDEX('Indicator Master'!$N$4:$N$46,MATCH($A88,'Indicator Master'!$A$4:$A$46,0)),1,0) -> 0 | O88: Early warning — >0–5% pledged; minimal, typically routine. | P88: 1) Obtain pledge details and purpose. 2) Monitor the trend. | Q88: Relationship Manager (Branch) | R88: =$A88&"|"&$K88 -> EWS-022|10
A89: EWS-022 | B89: % promoter shares pledged | C89: EWS | D89: Higher pledged promoter shares | E89: 3 | F89: >5% to ≤10% | G89: Percent Range | H89: 5 | I89: 10 | J89: > lower & ≤ upper | K89: 20 | L89: =$K89/INDEX('Indicator Master'!$N$4:$N$46,MATCH($A89,'Indicator Master'!$A$4:$A$46,0))*'Risk Bands (Config)'!$B$5 -> 50 | M89: =IF($K89=INDEX('Indicator Master'!$N$4:$N$46,MATCH($A89,'Indicator Master'!$A$4:$A$46,0)),1,0) -> 0 | O89: Elevated concern — >5–10% pledged; rising promoter leverage — monitor. | P89: 1) Assess promoter leverage; seek an NDU/comfort. 2) Monitor market price. 3) Note for review. | Q89: RM + Credit Analyst | R89: =$A89&"|"&$K89 -> EWS-022|20
A90: EWS-022 | B90: % promoter shares pledged | C90: EWS | D90: Higher pledged promoter shares | E90: 4 | F90: >10% to ≤20% | G90: Percent Range | H90: 10 | I90: 20 | J90: > lower & ≤ upper | K90: 30 | L90: =$K90/INDEX('Indicator Master'!$N$4:$N$46,MATCH($A90,'Indicator Master'!$A$4:$A$46,0))*'Risk Bands (Config)'!$B$5 -> 75 | M90: =IF($K90=INDEX('Indicator Master'!$N$4:$N$46,MATCH($A90,'Indicator Master'!$A$4:$A$46,0)),1,0) -> 0 | O90: High concern — >10–20% pledged; material — promoter financial stress / loss-of-control risk building. | P90: 1) Reassess promoter support; tighten terms. 2) Seek additional comfort/security. 3) Escalate to Credit. | Q90: Credit + Risk | R90: =$A90&"|"&$K90 -> EWS-022|30
A91: EWS-022 | B91: % promoter shares pledged | C91: EWS | D91: Higher pledged promoter shares | E91: 5 | F91: >20% | G91: Percent Threshold | H91: 20 | J91: > lower | K91: 40 | L91: =$K91/INDEX('Indicator Master'!$N$4:$N$46,MATCH($A91,'Indicator Master'!$A$4:$A$46,0))*'Risk Bands (Config)'!$B$5 -> 100 | M91: =IF($K91=INDEX('Indicator Master'!$N$4:$N$46,MATCH($A91,'Indicator Master'!$A$4:$A$46,0)),1,0) -> 1 | O91: Severe / critical — >20% pledged; high — significant promoter distress, risk of forced sale/control change. | P91: 1) Treat as a material adverse change. 2) Reassess exposure and control risk. 3) Escalate to Credit Committee. | Q91: Credit Head / Risk | R91: =$A91&"|"&$K91 -> EWS-022|40
A92: EWS-023 | B92: Decline in promoter holding % | C92: EWS | D92: Significant reduction in promoter stake | E92: 1 | F92: ≤0% | G92: Percent Threshold | I92: 0 | J92: ≤ upper | K92: 0 | L92: =$K92/INDEX('Indicator Master'!$N$4:$N$46,MATCH($A92,'Indicator Master'!$A$4:$A$46,0))*'Risk Bands (Config)'!$B$5 -> 0 | M92: =IF($K92=INDEX('Indicator Master'!$N$4:$N$46,MATCH($A92,'Indicator Master'!$A$4:$A$46,0)),1,0) -> 0 | O92: Normal — no decline in promoter holding; skin-in-the-game intact. | P92: No remedial action required. Continue routine monitoring at the standard review cycle and record the reading. | Q92: RM (routine) | R92: =$A92&"|"&$K92 -> EWS-023|0
A93: EWS-023 | B93: Decline in promoter holding % | C93: EWS | D93: Significant reduction in promoter stake | E93: 2 | F93: >0% to ≤5% | G93: Percent Range | H93: 0 | I93: 5 | J93: > lower & ≤ upper | K93: 10 | L93: =$K93/INDEX('Indicator Master'!$N$4:$N$46,MATCH($A93,'Indicator Master'!$A$4:$A$46,0))*'Risk Bands (Config)'!$B$5 -> 25 | M93: =IF($K93=INDEX('Indicator Master'!$N$4:$N$46,MATCH($A93,'Indicator Master'!$A$4:$A$46,0)),1,0) -> 0 | O93: Early warning — holding down >0–5%; marginal dilution, usually benign. | P93: 1) Obtain the reason for the reduction. 2) Monitor. | Q93: Relationship Manager (Branch) | R93: =$A93&"|"&$K93 -> EWS-023|10
A94: EWS-023 | B94: Decline in promoter holding % | C94: EWS | D94: Significant reduction in promoter stake | E94: 3 | F94: >5% to ≤10% | G94: Percent Range | H94: 5 | I94: 10 | J94: > lower & ≤ upper | K94: 20 | L94: =$K94/INDEX('Indicator Master'!$N$4:$N$46,MATCH($A94,'Indicator Master'!$A$4:$A$46,0))*'Risk Bands (Config)'!$B$5 -> 50 | M94: =IF($K94=INDEX('Indicator Master'!$N$4:$N$46,MATCH($A94,'Indicator Master'!$A$4:$A$46,0)),1,0) -> 0 | O94: Elevated concern — down >5–10%; noticeable reduction — check intent. | P94: 1) Assess promoter commitment; seek comfort. 2) Monitor developments. 3) Note for review. | Q94: RM + Credit Analyst | R94: =$A94&"|"&$K94 -> EWS-023|20
A95: EWS-023 | B95: Decline in promoter holding % | C95: EWS | D95: Significant reduction in promoter stake | E95: 4 | F95: >10% to ≤20% | G95: Percent Range | H95: 10 | I95: 20 | J95: > lower & ≤ upper | K95: 30 | L95: =$K95/INDEX('Indicator Master'!$N$4:$N$46,MATCH($A95,'Indicator Master'!$A$4:$A$46,0))*'Risk Bands (Config)'!$B$5 -> 75 | M95: =IF($K95=INDEX('Indicator Master'!$N$4:$N$46,MATCH($A95,'Indicator Master'!$A$4:$A$46,0)),1,0) -> 0 | O95: High concern — down >10–20%; material dilution — weakening promoter commitment. | P95: 1) Reassess promoter support and control. 2) Tighten terms. 3) Escalate to Credit. | Q95: Credit + Risk | R95: =$A95&"|"&$K95 -> EWS-023|30
A96: EWS-023 | B96: Decline in promoter holding % | C96: EWS | D96: Significant reduction in promoter stake | E96: 5 | F96: >20% | G96: Percent Threshold | H96: 20 | J96: > lower | K96: 40 | L96: =$K96/INDEX('Indicator Master'!$N$4:$N$46,MATCH($A96,'Indicator Master'!$A$4:$A$46,0))*'Risk Bands (Config)'!$B$5 -> 100 | M96: =IF($K96=INDEX('Indicator Master'!$N$4:$N$46,MATCH($A96,'Indicator Master'!$A$4:$A$46,0)),1,0) -> 1 | O96: Severe / critical — down >20%; severe — possible promoter exit / loss of control. | P96: 1) Treat as a material adverse change; reassess exposure. 2) Seek comfort/security. 3) Escalate to Credit Committee. | Q96: Credit Head / Risk | R96: =$A96&"|"&$K96 -> EWS-023|40
A97: EWS-024 | B97: RPT value/share change % | C97: EWS | D97: Large group-company transactions | E97: 1 | F97: ≤0% | G97: Percent Threshold | I97: 0 | J97: ≤ upper | K97: 0 | L97: =$K97/INDEX('Indicator Master'!$N$4:$N$46,MATCH($A97,'Indicator Master'!$A$4:$A$46,0))*'Risk Bands (Config)'!$B$5 -> 0 | M97: =IF($K97=INDEX('Indicator Master'!$N$4:$N$46,MATCH($A97,'Indicator Master'!$A$4:$A$46,0)),1,0) -> 0 | O97: Normal — no rise in related-party transactions; arm's-length maintained. | P97: No remedial action required. Continue routine monitoring at the standard review cycle and record the reading. | Q97: RM (routine) | R97: =$A97&"|"&$K97 -> EWS-024|0
A98: EWS-024 | B98: RPT value/share change % | C98: EWS | D98: Large group-company transactions | E98: 2 | F98: >0% to ≤10% | G98: Percent Range | H98: 0 | I98: 10 | J98: > lower & ≤ upper | K98: 10 | L98: =$K98/INDEX('Indicator Master'!$N$4:$N$46,MATCH($A98,'Indicator Master'!$A$4:$A$46,0))*'Risk Bands (Config)'!$B$5 -> 25 | M98: =IF($K98=INDEX('Indicator Master'!$N$4:$N$46,MATCH($A98,'Indicator Master'!$A$4:$A$46,0)),1,0) -> 0 | O98: Early warning — RPT up >0–10%; modest — verify arm's-length basis. | P98: 1) Obtain RPT details; verify arm's-length. 2) Monitor. | Q98: Relationship Manager (Branch) | R98: =$A98&"|"&$K98 -> EWS-024|10
A99: EWS-024 | B99: RPT value/share change % | C99: EWS | D99: Large group-company transactions | E99: 3 | F99: >10% to ≤25% | G99: Percent Range | H99: 10 | I99: 25 | J99: > lower & ≤ upper | K99: 25 | L99: =$K99/INDEX('Indicator Master'!$N$4:$N$46,MATCH($A99,'Indicator Master'!$A$4:$A$46,0))*'Risk Bands (Config)'!$B$5 -> 62.5 | M99: =IF($K99=INDEX('Indicator Master'!$N$4:$N$46,MATCH($A99,'Indicator Master'!$A$4:$A$46,0)),1,0) -> 0 | O99: Elevated concern — up >10–25%; material rise — possible fund routing to related parties. | P99: 1) Scrutinise for diversion; seek disclosures. 2) Special review. 3) Escalate to Credit. | Q99: Credit + Risk | R99: =$A99&"|"&$K99 -> EWS-024|25
A100: EWS-024 | B100: RPT value/share change % | C100: EWS | D100: Large group-company transactions | E100: 4 | F100: >25% | G100: Percent Threshold | H100: 25 | J100: > lower | K100: 40 | L100: =$K100/INDEX('Indicator Master'!$N$4:$N$46,MATCH($A100,'Indicator Master'!$A$4:$A$46,0))*'Risk Bands (Config)'!$B$5 -> 100 | M100: =IF($K100=INDEX('Indicator Master'!$N$4:$N$46,MATCH($A100,'Indicator Master'!$A$4:$A$46,0)),1,0) -> 1 | O100: Severe / critical — up >25%; severe — significant RPT exposure / siphoning risk. | P100: 1) Forensic audit of RPTs and fund flow. 2) Freeze incremental exposure. 3) Escalate to Credit Committee. | Q100: Credit Head / Risk | R100: =$A100&"|"&$K100 -> EWS-024|40
A101: EWS-025 | B101: Group-entity stress classification | C101: EWS | D101: Default, downgrade, insolvency, or stress in related/group company | E101: 1 | F101: No group stress | G101: Ordinal Classification | J101: category | K101: 0 | L101: =$K101/INDEX('Indicator Master'!$N$4:$N$46,MATCH($A101,'Indicator Master'!$A$4:$A$46,0))*'Risk Bands (Config)'!$B$5 -> 0 | M101: =IF($K101=INDEX('Indicator Master'!$N$4:$N$46,MATCH($A101,'Indicator Master'!$A$4:$A$46,0)),1,0) -> 0 | O101: Normal — no group stress; group profile stable. | P101: No remedial action required. Continue routine monitoring at the standard review cycle and record the reading. | Q101: RM (routine) | R101: =$A101&"|"&$K101 -> EWS-025|0
A102: EWS-025 | B102: Group-entity stress classification | C102: EWS | D102: Default, downgrade, insolvency, or stress in related/group company | E102: 2 | F102: downgrade/legal event | G102: Ordinal Classification | J102: category | K102: 20 | L102: =$K102/INDEX('Indicator Master'!$N$4:$N$46,MATCH($A102,'Indicator Master'!$A$4:$A$46,0))*'Risk Bands (Config)'!$B$5 -> 50 | M102: =IF($K102=INDEX('Indicator Master'!$N$4:$N$46,MATCH($A102,'Indicator Master'!$A$4:$A$46,0)),1,0) -> 0 | O102: Elevated concern — a downgrade or legal event in the group; contagion risk emerging. | P102: 1) Map group exposure and linkages. 2) Ring-fence cash flows; seek an NDU. 3) Escalate to Credit. | Q102: RM + Credit Analyst | R102: =$A102&"|"&$K102 -> EWS-025|20
A103: EWS-025 | B103: Group-entity stress classification | C103: EWS | D103: Default, downgrade, insolvency, or stress in related/group company | E103: 3 | F103: default/IBC in group | G103: Ordinal Classification | J103: category | K103: 40 | L103: =$K103/INDEX('Indicator Master'!$N$4:$N$46,MATCH($A103,'Indicator Master'!$A$4:$A$46,0))*'Risk Bands (Config)'!$B$5 -> 100 | M103: =IF($K103=INDEX('Indicator Master'!$N$4:$N$46,MATCH($A103,'Indicator Master'!$A$4:$A$46,0)),1,0) -> 1 | O103: Severe / critical — default/IBC in a group entity; severe — direct contagion and cross-default risk. | P103: 1) Treat as a material adverse change; reassess consolidated risk. 2) Enforce ring-fencing/escrow. 3) Escalate to Credit Committee. | Q103: Credit Head / Risk | R103: =$A103&"|"&$K103 -> EWS-025|40
A104: EWS-026 | B104: Statutory overdues | C104: EWS | D104: Delay in GST, PF, TDS, income tax payment | E104: 1 | F104: On time | G104: Count Exact | H104: 0 | I104: 0 | J104: exactly = value | K104: 0 | L104: =$K104/INDEX('Indicator Master'!$N$4:$N$46,MATCH($A104,'Indicator Master'!$A$4:$A$46,0))*'Risk Bands (Config)'!$B$5 -> 0 | M104: =IF($K104=INDEX('Indicator Master'!$N$4:$N$46,MATCH($A104,'Indicator Master'!$A$4:$A$46,0)),1,0) -> 0 | O104: Normal — statutory dues paid on time; no first-charge arrears. | P104: No remedial action required. Continue routine monitoring at the standard review cycle and record the reading. | Q104: RM (routine) | R104: =$A104&"|"&$K104 -> EWS-026|0
A105: EWS-026 | B105: Statutory overdues | C105: EWS | D105: Delay in GST, PF, TDS, income tax payment | E105: 2 | F105: 1 month delayed | G105: Count Exact | H105: 1 | I105: 1 | J105: exactly = value | K105: 10 | L105: =$K105/INDEX('Indicator Master'!$N$4:$N$46,MATCH($A105,'Indicator Master'!$A$4:$A$46,0))*'Risk Bands (Config)'!$B$5 -> 28.571429 | M105: =IF($K105=INDEX('Indicator Master'!$N$4:$N$46,MATCH($A105,'Indicator Master'!$A$4:$A$46,0)),1,0) -> 0 | O105: Early warning — one month delayed; early liquidity pinch on statutory payments. | P105: 1) Obtain challans; seek immediate clearance. 2) Assess the cash-flow reason. 3) Monitor. | Q105: Relationship Manager (Branch) | R105: =$A105&"|"&$K105 -> EWS-026|10
A106: EWS-026 | B106: Statutory overdues | C106: EWS | D106: Delay in GST, PF, TDS, income tax payment | E106: 3 | F106: 2 months delayed | G106: Count Exact | H106: 2 | I106: 2 | J106: exactly = value | K106: 20 | L106: =$K106/INDEX('Indicator Master'!$N$4:$N$46,MATCH($A106,'Indicator Master'!$A$4:$A$46,0))*'Risk Bands (Config)'!$B$5 -> 57.142857 | M106: =IF($K106=INDEX('Indicator Master'!$N$4:$N$46,MATCH($A106,'Indicator Master'!$A$4:$A$46,0)),1,0) -> 0 | O106: Elevated concern — two months delayed; deepening liquidity stress — statutory dues (first charge) accumulating. | P106: 1) Stipulate a clearance timeline; verify no charge/attachment on assets. 2) Investigate the liquidity stress. 3) Escalate to Credit. | Q106: RM + Credit Analyst | R106: =$A106&"|"&$K106 -> EWS-026|20
A107: EWS-026 | B107: Statutory overdues | C107: EWS | D107: Delay in GST, PF, TDS, income tax payment | E107: 4 | F107: 3+ months | G107: Count Threshold | H107: 3 | J107: ≥ lower | K107: 35 | L107: =$K107/INDEX('Indicator Master'!$N$4:$N$46,MATCH($A107,'Indicator Master'!$A$4:$A$46,0))*'Risk Bands (Config)'!$B$5 -> 100 | M107: =IF($K107=INDEX('Indicator Master'!$N$4:$N$46,MATCH($A107,'Indicator Master'!$A$4:$A$46,0)),1,0) -> 1 | N107: CRITICAL EVENT | O107: Severe / critical — 3+ months overdue; severe — large statutory arrears ranking ahead of the bank, attachment risk. | P107: [CRITICAL] 1) Treat as serious stress — statutory dues rank ahead of the bank. 2) Verify no attachment/first-charge; liquidity/forensic review. 3) Corrective / recovery plan; escalate immediately. NOTE: CRITICAL indicator — statutory dues rank ahead of the bank; worst band fires the Critical Override → final status escalates to Critical. | Q107: Credit Head / Risk (immediate) | R107: =$A107&"|"&$K107 -> EWS-026|35
A108: EWS-027 | B108: Regulatory event severity | C108: EWS | D108: Tax notices, GST/Income tax/SEBI/RBI/NCLT actions | E108: 1 | F108: No notice | G108: Ordinal Classification | J108: category | K108: 0 | L108: =$K108/INDEX('Indicator Master'!$N$4:$N$46,MATCH($A108,'Indicator Master'!$A$4:$A$46,0))*'Risk Bands (Config)'!$B$5 -> 0 | M108: =IF($K108=INDEX('Indicator Master'!$N$4:$N$46,MATCH($A108,'Indicator Master'!$A$4:$A$46,0)),1,0) -> 0 | O108: Normal — no regulatory notice; clean compliance record. | P108: No remedial action required. Continue routine monitoring at the standard review cycle and record the reading. | Q108: RM (routine) | R108: =$A108&"|"&$K108 -> EWS-027|0
A109: EWS-027 | B109: Regulatory event severity | C109: EWS | D109: Tax notices, GST/Income tax/SEBI/RBI/NCLT actions | E109: 2 | F109: regulatory notice | G109: Ordinal Classification | J109: category | K109: 15 | L109: =$K109/INDEX('Indicator Master'!$N$4:$N$46,MATCH($A109,'Indicator Master'!$A$4:$A$46,0))*'Risk Bands (Config)'!$B$5 -> 30 | M109: =IF($K109=INDEX('Indicator Master'!$N$4:$N$46,MATCH($A109,'Indicator Master'!$A$4:$A$46,0)),1,0) -> 0 | O109: Early warning — a regulatory notice received; early compliance concern. | P109: 1) Obtain notice details; assess materiality. 2) Legal opinion if needed. 3) Monitor. | Q109: Relationship Manager (Branch) | R109: =$A109&"|"&$K109 -> EWS-027|15
A110: EWS-027 | B110: Regulatory event severity | C110: EWS | D110: Tax notices, GST/Income tax/SEBI/RBI/NCLT actions | E110: 3 | F110: multiple/material notice | G110: Ordinal Classification | J110: category | K110: 30 | L110: =$K110/INDEX('Indicator Master'!$N$4:$N$46,MATCH($A110,'Indicator Master'!$A$4:$A$46,0))*'Risk Bands (Config)'!$B$5 -> 60 | M110: =IF($K110=INDEX('Indicator Master'!$N$4:$N$46,MATCH($A110,'Indicator Master'!$A$4:$A$46,0)),1,0) -> 0 | O110: Elevated concern — multiple/material notices; escalating regulatory exposure. | P110: 1) Reassess exposure and security; provision if material. 2) Protect the bank's charge. 3) Escalate to Credit/Legal. | Q110: RM + Credit Analyst | R110: =$A110&"|"&$K110 -> EWS-027|30
...

Sheet Overall Score Engine
A1: Overall Score Engine (Live Calculator)
A2: Yellow cells are inputs. Overall = average of normalised scores of applicable indicators with valid data. Critical Override fires on (a) any Critical indicator at its trigger OR (b) any Critical Combination pair co-occurring (block below).
A4: Borrower Name | B4: Acme Textiles Pvt Ltd
A5: Assessment Date | B5: 31-Aug-2026
A7: Total Indicators | B7: =COUNTA($A$23:$A$65) -> 43
A8: Applicable Indicators | B8: =COUNTIF($F$23:$F$65,"Y") -> 39 | C8: Indicators relevant to this borrower (N/A excluded).
A9: Scored (valid data) | B9: =SUM($J$23:$J$65) -> 36 | C9: Applicable AND data available AND a raw score entered.
A10: Missing Data (applicable) | B10: =COUNTIFS($F$23:$F$65,"Y",$G$23:$G$65,"N") -> 3 | C10: Applicable but no data — EXCLUDED from the average (not treated as zero).
A11: Not Applicable (N/A) | B11: =COUNTIF($F$23:$F$65,"N") -> 4
A12: Data Coverage % | B12: =IF(B8=0,0,B9/B8*100) -> 92.307692 | C12: Reported separately; does NOT affect the Overall Score.
A13: Sum of Normalised (scored) | B13: =SUM($K$23:$K$65) -> 1020.8333
A14: Overall EWS Score | B14: =IF(B9=0,0,B13/B9) -> 28.356481 | C14: Average of normalised scores of applicable indicators with valid data.
A15: Numeric Risk Band | B15: =INDEX('Risk Bands (Config)'!$A$9:$A$13,MATCH(B14,'Risk Bands (Config)'!$D$9:$D$13,1)) -> Yellow | C15: Band implied by the Overall Score alone (before critical override).
A16: Critical Override Triggered? | B16: =IF(SUM($L$23:$L$65)+SUM($F$74:$F$76)>0,"YES","NO") -> YES | C16: YES if any CRITICAL indicator reaches the override trigger ('6. Risk Bands (Config)'!$B$6).
A17: Critical Indicators Fired | B17: =$M$65 -> EWS-026
A18: FINAL STATUS | B18: =IF(B16="YES","CRITICAL (Override)",IF(B12<'Risk Bands (Config)'!$B$16,"INSUFFICIENT DATA (band: "&B15&")",B15)) -> CRITICAL (Override)
A19: Final Interpretation | B19: =IF(B16="YES",INDEX('Risk Bands (Config)'!$E$9:$E$13,5),IF(B12<'Risk Bands (Config)'!$B$16,"Low data coverage — treat score as low-confidence; obtain missing data before acting.",INDEX('Risk Bands (Config)'!$E$9:$E$13,MATCH(B14,'Risk Bands (Config)'!$D$9:$D$13,1)))) -> Severe EWS / Immediate Intervention
A20: Traceability: FINAL STATUS ← Overall Score / Critical Override ← per-indicator Normalised ← Raw Score ← borrower Observed Value ← applicable threshold band.
A22: UID | B22: Indicator | C22: Module | D22: Critical | E22: Max Score | F22: Applicable (Y/N) | G22: Data Available (Y/N) | H22: Observed Value / Note | I22: Raw Score | J22: Scored Flag | K22: Normalised Score | L22: Critical Fire | M22: Crit Fire UID (helper) | N22: What it signals & likely drivers | O22: Remedial action plan (step-by-step) | P22: Primary owner
A23: EWS-001 | B23: Utilization % (outstanding / sanctioned) | C23: EWS | D23: =INDEX('Indicator Master'!$F$4:$F$46,MATCH($A23,'Indicator Master'!$A$4:$A$46,0)) -> No | E23: =INDEX('Indicator Master'!$N$4:$N$46,MATCH($A23,'Indicator Master'!$A$4:$A$46,0)) -> 30 | F23: Y | G23: Y | H23: CC utilisation >95% sustained for 30+ days → band '>95% for 30+ days' | I23: 30 | J23: =IF(AND($F23="Y",$G23="Y",ISNUMBER($I23)),1,0) -> 1 | K23: =IF($J23=1,$I23/$E23*'Risk Bands (Config)'!$B$5,"") -> 100 | L23: =IF(AND($D23="Yes",$J23=1,$I23/$E23*'Risk Bands (Config)'!$B$5>='Risk Bands (Config)'!$B$6),1,0) -> 0 | M23: =IF($L23=1,$A23,"") | N23: =IF($J23=1,IFERROR(INDEX('Scoring Engine (Rules)'!$O$5:$O$163,MATCH($A23&"|"&$I23,'Scoring Engine (Rules)'!$R$5:$R$163,0)),""),"") -> Severe / critical — utilisation above 95% for 30+ days; chronic over-reliance — possible inability to rotate WC, or diversion/ever-greening. | O23: =IF($J23=1,IFERROR(INDEX('Scoring Engine (Rules)'!$P$5:$P$163,MATCH($A23&"|"&$I23,'Scoring Engine (Rules)'!$R$5:$R$163,0)),""),"") -> 1) Restrict fresh drawals pending review. 2) Investigate diversion (routing gaps, ad-hoc pattern). 3) Full viability / limit-rationalisation review; escalate to Credit. | P23: =IF($J23=1,IFERROR(INDEX('Scoring Engine (Rules)'!$Q$5:$Q$163,MATCH($A23&"|"&$I23,'Scoring Engine (Rules)'!$R$5:$R$163,0)),""),"") -> Credit Head / Risk
A24: EWS-002 | B24: Count of ad-hoc limit requests (rolling 12m) | C24: EWS | D24: =INDEX('Indicator Master'!$F$4:$F$46,MATCH($A24,'Indicator Master'!$A$4:$A$46,0)) -> No | E24: =INDEX('Indicator Master'!$N$4:$N$46,MATCH($A24,'Indicator Master'!$A$4:$A$46,0)) -> 30 | F24: Y | G24: Y | H24: Matches band: 2 → band '2' | I24: 10 | J24: =IF(AND($F24="Y",$G24="Y",ISNUMBER($I24)),1,0) -> 1 | K24: =IF($J24=1,$I24/$E24*'Risk Bands (Config)'!$B$5,"") -> 33.333333 | L24: =IF(AND($D24="Yes",$J24=1,$I24/$E24*'Risk Bands (Config)'!$B$5>='Risk Bands (Config)'!$B$6),1,0) -> 0 | M24: =$M23&IF($L24=1,IF($M23="","",", ")&$A24,"") | N24: =IF($J24=1,IFERROR(INDEX('Scoring Engine (Rules)'!$O$5:$O$163,MATCH($A24&"|"&$I24,'Scoring Engine (Rules)'!$R$5:$R$163,0)),""),"") -> Early warning — two ad-hoc requests; occasional cash-flow mismatch. | O24: =IF($J24=1,IFERROR(INDEX('Scoring Engine (Rules)'!$P$5:$P$163,MATCH($A24&"|"&$I24,'Scoring Engine (Rules)'!$R$5:$R$163,0)),""),"") -> 1) Ascertain the reason for each request. 2) Check whether permanent WC is under-assessed. 3) Grant only against a documented need. | P24: =IF($J24=1,IFERROR(INDEX('Scoring Engine (Rules)'!$Q$5:$Q$163,MATCH($A24&"|"&$I24,'Scoring Engine (Rules)'!$R$5:$R$163,0)),""),"") -> RM + Credit Analyst
A25: EWS-003 | B25: Monthly sales vs credit summation | C25: EWS | D25: =INDEX('Indicator Master'!$F$4:$F$46,MATCH($A25,'Indicator Master'!$A$4:$A$46,0)) -> Yes | E25: =INDEX('Indicator Master'!$N$4:$N$46,MATCH($A25,'Indicator Master'!$A$4:$A$46,0)) -> 35 | F25: Y | G25: Y | H25: Operating-account credits down ~28% vs baseline → band '20-40% decline' | I25: 20 | J25: =IF(AND($F25="Y",$G25="Y",ISNUMBER($I25)),1,0) -> 1 | K25: =IF($J25=1,$I25/$E25*'Risk Bands (Config)'!$B$5,"") -> 57.142857 | L25: =IF(AND($D25="Yes",$J25=1,$I25/$E25*'Risk Bands (Config)'!$B$5>='Risk Bands (Config)'!$B$6),1,0) -> 0 | M25: =$M24&IF($L25=1,IF($M24="","",", ")&$A25,"") | N25: =IF($J25=1,IFERROR(INDEX('Scoring Engine (Rules)'!$O$5:$O$163,MATCH($A25&"|"&$I25,'Scoring Engine (Rules)'!$R$5:$R$163,0)),""),"") -> Elevated concern — credits down 20–40%; material drop — genuine sales fall or turnover being diverted elsewhere. | O25: =IF($J25=1,IFERROR(INDEX('Scoring Engine (Rules)'!$P$5:$P$163,MATCH($A25&"|"&$I25,'Scoring Engine (Rules)'!$R$5:$R$163,0)),""),"") -> 1) Stipulate proportionate turnover routing through the bank. 2) Verify sales via GST returns. 3) Monitor monthly credits vs sales. | P25: =IF($J25=1,IFERROR(INDEX('Scoring Engine (Rules)'!$Q$5:$Q$163,MATCH($A25&"|"&$I25,'Scoring Engine (Rules)'!$R$5:$R$163,0)),""),"") -> RM + Credit Analyst
A26: EWS-004 | B26: Payment Default Frequency | C26: EWS | D26: =INDEX('Indicator Master'!$F$4:$F$46,MATCH($A26,'Indicator Master'!$A$4:$A$46,0)) -> No | E26: =INDEX('Indicator Master'!$N$4:$N$46,MATCH($A26,'Indicator Master'!$A$4:$A$46,0)) -> 25 | F26: Y | G26: Y | H26: Matches band: 1 → band '1' | I26: 5 | J26: =IF(AND($F26="Y",$G26="Y",ISNUMBER($I26)),1,0) -> 1 | K26: =IF($J26=1,$I26/$E26*'Risk Bands (Config)'!$B$5,"") -> 20 | L26: =IF(AND($D26="Yes",$J26=1,$I26/$E26*'Risk Bands (Config)'!$B$5>='Risk Bands (Config)'!$B$6),1,0) -> 0 | M26: =$M25&IF($L26=1,IF($M25="","",", ")&$A26,"") | N26: =IF($J26=1,IFERROR(INDEX('Scoring Engine (Rules)'!$O$5:$O$163,MATCH($A26&"|"&$I26,'Scoring Engine (Rules)'!$R$5:$R$163,0)),""),"") -> Early warning — one conduct event; isolated slip, likely a timing mismatch. | O26: =IF($J26=1,IFERROR(INDEX('Scoring Engine (Rules)'!$P$5:$P$163,MATCH($A26&"|"&$I26,'Scoring Engine (Rules)'!$R$5:$R$163,0)),""),"") -> 1) Note the event and reason. 2) Caution the borrower informally. 3) Watch the next cycle. | P26: =IF($J26=1,IFERROR(INDEX('Scoring Engine (Rules)'!$Q$5:$Q$163,MATCH($A26&"|"&$I26,'Scoring Engine (Rules)'!$R$5:$R$163,0)),""),"") -> Relationship Manager (Branch)
A27: EWS-005 | B27: Repayment source classification | C27: EWS | D27: =INDEX('Indicator Master'!$F$4:$F$46,MATCH($A27,'Indicator Master'!$A$4:$A$46,0)) -> No | E27: =INDEX('Indicator Master'!$N$4:$N$46,MATCH($A27,'Indicator Master'!$A$4:$A$46,0)) -> 40 | F27: Y | G27: Y | H27: Matches band: Own operating cash flow → band 'Own operating cash flow' | I27: 0 | J27: =IF(AND($F27="Y",$G27="Y",ISNUMBER($I27)),1,0) -> 1 | K27: =IF($J27=1,$I27/$E27*'Risk Bands (Config)'!$B$5,"") -> 0 | L27: =IF(AND($D27="Yes",$J27=1,$I27/$E27*'Risk Bands (Config)'!$B$5>='Risk Bands (Config)'!$B$6),1,0) -> 0 | M27: =$M26&IF($L27=1,IF($M26="","",", ")&$A27,"") | N27: =IF($J27=1,IFERROR(INDEX('Scoring Engine (Rules)'!$O$5:$O$163,MATCH($A27&"|"&$I27,'Scoring Engine (Rules)'!$R$5:$R$163,0)),""),"") -> Normal — repayments from the borrower's own operating cash flows; healthy. | O27: =IF($J27=1,IFERROR(INDEX('Scoring Engine (Rules)'!$P$5:$P$163,MATCH($A27&"|"&$I27,'Scoring Engine (Rules)'!$R$5:$R$163,0)),""),"") -> No remedial action required. Continue routine monitoring at the standard review cycle and record the reading. | P27: =IF($J27=1,IFERROR(INDEX('Scoring Engine (Rules)'!$Q$5:$Q$163,MATCH($A27&"|"&$I27,'Scoring Engine (Rules)'!$R$5:$R$163,0)),""),"") -> RM (routine)
A28: EWS-006 | B28: Stock reported vs audited variance % | C28: EWS | D28: =INDEX('Indicator Master'!$F$4:$F$46,MATCH($A28,'Indicator Master'!$A$4:$A$46,0)) -> No | E28: =INDEX('Indicator Master'!$N$4:$N$46,MATCH($A28,'Indicator Master'!$A$4:$A$46,0)) -> 30 | F28: Y | G28: Y | H28: Matches band: upto 10% → band 'upto 10%' | I28: 10 | J28: =IF(AND($F28="Y",$G28="Y",ISNUMBER($I28)),1,0) -> 1 | K28: =IF($J28=1,$I28/$E28*'Risk Bands (Config)'!$B$5,"") -> 33.333333 | L28: =IF(AND($D28="Yes",$J28=1,$I28/$E28*'Risk Bands (Config)'!$B$5>='Risk Bands (Config)'!$B$6),1,0) -> 0 | M28: =$M27&IF($L28=1,IF($M27="","",", ")&$A28,"") | N28: =IF($J28=1,IFERROR(INDEX('Scoring Engine (Rules)'!$O$5:$O$163,MATCH($A28&"|"&$I28,'Scoring Engine (Rules)'!$R$5:$R$163,0)),""),"") -> Early warning — up to 10% variance; minor reconciliation gap, likely timing or method. | O28: =IF($J28=1,IFERROR(INDEX('Scoring Engine (Rules)'!$P$5:$P$163,MATCH($A28&"|"&$I28,'Scoring Engine (Rules)'!$R$5:$R$163,0)),""),"") -> 1) Reconcile the statement to audited figures. 2) Seek clarification on the small gap. | P28: =IF($J28=1,IFERROR(INDEX('Scoring Engine (Rules)'!$Q$5:$Q$163,MATCH($A28&"|"&$I28,'Scoring Engine (Rules)'!$R$5:$R$163,0)),""),"") -> RM + Credit Analyst
A29: EWS-007 | B29: Sales turnover YoY/QoQ change % | C29: EWS | D29: =INDEX('Indicator Master'!$F$4:$F$46,MATCH($A29,'Indicator Master'!$A$4:$A$46,0)) -> Yes | E29: =INDEX('Indicator Master'!$N$4:$N$46,MATCH($A29,'Indicator Master'!$A$4:$A$46,0)) -> 35 | F29: Y | G29: Y | H29: Sales turnover down ~30% YoY → band '20-40% decline' | I29: 20 | J29: =IF(AND($F29="Y",$G29="Y",ISNUMBER($I29)),1,0) -> 1 | K29: =IF($J29=1,$I29/$E29*'Risk Bands (Config)'!$B$5,"") -> 57.142857 | L29: =IF(AND($D29="Yes",$J29=1,$I29/$E29*'Risk Bands (Config)'!$B$5>='Risk Bands (Config)'!$B$6),1,0) -> 0 | M29: =$M28&IF($L29=1,IF($M28="","",", ")&$A29,"") | N29: =IF($J29=1,IFERROR(INDEX('Scoring Engine (Rules)'!$O$5:$O$163,MATCH($A29&"|"&$I29,'Scoring Engine (Rules)'!$R$5:$R$163,0)),""),"") -> Elevated concern — turnover down 20–40%; a genuine downturn or loss of key customers. | O29: =IF($J29=1,IFERROR(INDEX('Scoring Engine (Rules)'!$P$5:$P$163,MATCH($A29&"|"&$I29,'Scoring Engine (Rules)'!$R$5:$R$163,0)),""),"") -> 1) Reassess repayment capacity and viability with a sensitivity run. 2) Consider whether restructuring is needed. 3) Escalate to Credit. | P29: =IF($J29=1,IFERROR(INDEX('Scoring Engine (Rules)'!$Q$5:$Q$163,MATCH($A29&"|"&$I29,'Scoring Engine (Rules)'!$R$5:$R$163,0)),""),"") -> RM + Credit Analyst
A30: EWS-008 | B30: EBITDA margin change % | C30: EWS | D30: =INDEX('Indicator Master'!$F$4:$F$46,MATCH($A30,'Indicator Master'!$A$4:$A$46,0)) -> No | E30: =INDEX('Indicator Master'!$N$4:$N$46,MATCH($A30,'Indicator Master'!$A$4:$A$46,0)) -> 35 | F30: Y | G30: Y | H30: Matches band: margin fall 10-20% → band 'margin fall 10-20%' | I30: 10 | J30: =IF(AND($F30="Y",$G30="Y",ISNUMBER($I30)),1,0) -> 1 | K30: =IF($J30=1,$I30/$E30*'Risk Bands (Config)'!$B$5,"") -> 28.571429 | L30: =IF(AND($D30="Yes",$J30=1,$I30/$E30*'Risk Bands (Config)'!$B$5>='Risk Bands (Config)'!$B$6),1,0) -> 0 | M30: =$M29&IF($L30=1,IF($M29="","",", ")&$A30,"") | N30: =IF($J30=1,IFERROR(INDEX('Scoring Engine (Rules)'!$O$5:$O$163,MATCH($A30&"|"&$I30,'Scoring Engine (Rules)'!$R$5:$R$163,0)),""),"") -> Early warning — margin fell 10–20%; cost inflation or pricing pressure beginning. | O30: =IF($J30=1,IFERROR(INDEX('Scoring Engine (Rules)'!$P$5:$P$163,MATCH($A30&"|"&$I30,'Scoring Engine (Rules)'!$R$5:$R$163,0)),""),"") -> 1) Analyse cost vs price drivers. 2) Reassess DSCR on updated numbers. 3) Monitor. | P30: =IF($J30=1,IFERROR(INDEX('Scoring Engine (Rules)'!$Q$5:$Q$163,MATCH($A30&"|"&$I30,'Scoring Engine (Rules)'!$R$5:$R$163,0)),""),"") -> Relationship Manager (Branch)
A31: EWS-009 | B31: Debtor days vs normal | C31: EWS | D31: =INDEX('Indicator Master'!$F$4:$F$46,MATCH($A31,'Indicator Master'!$A$4:$A$46,0)) -> No | E31: =INDEX('Indicator Master'!$N$4:$N$46,MATCH($A31,'Indicator Master'!$A$4:$A$46,0)) -> 30 | F31: Y | G31: Y | H31: Observed breach (combination demo) | I31: 20 | J31: =IF(AND($F31="Y",$G31="Y",ISNUMBER($I31)),1,0) -> 1 | K31: =IF($J31=1,$I31/$E31*'Risk Bands (Config)'!$B$5,"") -> 66.666667 | L31: =IF(AND($D31="Yes",$J31=1,$I31/$E31*'Risk Bands (Config)'!$B$5>='Risk Bands (Config)'!$B$6),1,0) -> 0 | M31: =$M30&IF($L31=1,IF($M30="","",", ")&$A31,"") | N31: =IF($J31=1,IFERROR(INDEX('Scoring Engine (Rules)'!$O$5:$O$163,MATCH($A31&"|"&$I31,'Scoring Engine (Rules)'!$R$5:$R$163,0)),""),"") -> Elevated concern — debtor days +30–60; material tie-up of working capital in receivables. | O31: =IF($J31=1,IFERROR(INDEX('Scoring Engine (Rules)'!$P$5:$P$163,MATCH($A31&"|"&$I31,'Scoring Engine (Rules)'!$R$5:$R$163,0)),""),"") -> 1) Order a receivables audit. 2) Exclude >90-day receivables from DP. 3) Monitor monthly. | P31: =IF($J31=1,IFERROR(INDEX('Scoring Engine (Rules)'!$Q$5:$Q$163,MATCH($A31&"|"&$I31,'Scoring Engine (Rules)'!$R$5:$R$163,0)),""),"") -> Credit Committee / Zonal Credit
A32: EWS-010 | B32: Inventory days vs normal | C32: EWS | D32: =INDEX('Indicator Master'!$F$4:$F$46,MATCH($A32,'Indicator Master'!$A$4:$A$46,0)) -> No | E32: =INDEX('Indicator Master'!$N$4:$N$46,MATCH($A32,'Indicator Master'!$A$4:$A$46,0)) -> 30 | F32: Y | G32: Y | H32: Matches band: +15-30 days → band '+15-30 days' | I32: 10 | J32: =IF(AND($F32="Y",$G32="Y",ISNUMBER($I32)),1,0) -> 1 | K32: =IF($J32=1,$I32/$E32*'Risk Bands (Config)'!$B$5,"") -> 33.333333 | L32: =IF(AND($D32="Yes",$J32=1,$I32/$E32*'Risk Bands (Config)'!$B$5>='Risk Bands (Config)'!$B$6),1,0) -> 0 | M32: =$M31&IF($L32=1,IF($M31="","",", ")&$A32,"") | N32: =IF($J32=1,IFERROR(INDEX('Scoring Engine (Rules)'!$O$5:$O$163,MATCH($A32&"|"&$I32,'Scoring Engine (Rules)'!$R$5:$R$163,0)),""),"") -> Early warning — inventory days +15–30; early slowdown — collection lag or slow-moving stock. | O32: =IF($J32=1,IFERROR(INDEX('Scoring Engine (Rules)'!$P$5:$P$163,MATCH($A32&"|"&$I32,'Scoring Engine (Rules)'!$R$5:$R$163,0)),""),"") -> 1) Review the inventory ageing. 2) Identify overdue/slow items. 3) Monitor. | P32: =IF($J32=1,IFERROR(INDEX('Scoring Engine (Rules)'!$Q$5:$Q$163,MATCH($A32&"|"&$I32,'Scoring Engine (Rules)'!$R$5:$R$163,0)),""),"") -> RM + Credit Analyst
A33: EWS-011 | B33: Creditor days vs normal | C33: EWS | D33: =INDEX('Indicator Master'!$F$4:$F$46,MATCH($A33,'Indicator Master'!$A$4:$A$46,0)) -> No | E33: =INDEX('Indicator Master'!$N$4:$N$46,MATCH($A33,'Indicator Master'!$A$4:$A$46,0)) -> 30 | F33: Y | G33: Y | H33: Matches band: +15-30 days → band '+15-30 days' | I33: 10 | J33: =IF(AND($F33="Y",$G33="Y",ISNUMBER($I33)),1,0) -> 1 | K33: =IF($J33=1,$I33/$E33*'Risk Bands (Config)'!$B$5,"") -> 33.333333 | L33: =IF(AND($D33="Yes",$J33=1,$I33/$E33*'Risk Bands (Config)'!$B$5>='Risk Bands (Config)'!$B$6),1,0) -> 0 | M33: =$M32&IF($L33=1,IF($M32="","",", ")&$A33,"") | N33: =IF($J33=1,IFERROR(INDEX('Scoring Engine (Rules)'!$O$5:$O$163,MATCH($A33&"|"&$I33,'Scoring Engine (Rules)'!$R$5:$R$163,0)),""),"") -> Early warning — creditor days +15–30; stretching payables — mild liquidity tightening or negotiated terms. | O33: =IF($J33=1,IFERROR(INDEX('Scoring Engine (Rules)'!$P$5:$P$163,MATCH($A33&"|"&$I33,'Scoring Engine (Rules)'!$R$5:$R$163,0)),""),"") -> 1) Review payables ageing and reason. 2) Check for supply-side disputes. 3) Monitor. | P33: =IF($J33=1,IFERROR(INDEX('Scoring Engine (Rules)'!$Q$5:$Q$163,MATCH($A33&"|"&$I33,'Scoring Engine (Rules)'!$R$5:$R$163,0)),""),"") -> RM + Credit Analyst
A34: EWS-012 | B34: Provisions/write-offs change % | C34: EWS | D34: =INDEX('Indicator Master'!$F$4:$F$46,MATCH($A34,'Indicator Master'!$A$4:$A$46,0)) -> No | E34: =INDEX('Indicator Master'!$N$4:$N$46,MATCH($A34,'Indicator Master'!$A$4:$A$46,0)) -> 40 | F34: Y | G34: Y | H34: Observed breach (combination demo) | I34: 30 | J34: =IF(AND($F34="Y",$G34="Y",ISNUMBER($I34)),1,0) -> 1 | K34: =IF($J34=1,$I34/$E34*'Risk Bands (Config)'!$B$5,"") -> 75 | L34: =IF(AND($D34="Yes",$J34=1,$I34/$E34*'Risk Bands (Config)'!$B$5>='Risk Bands (Config)'!$B$6),1,0) -> 0 | M34: =$M33&IF($L34=1,IF($M33="","",", ")&$A34,"") | N34: =IF($J34=1,IFERROR(INDEX('Scoring Engine (Rules)'!$O$5:$O$163,MATCH($A34&"|"&$I34,'Scoring Engine (Rules)'!$R$5:$R$163,0)),""),"") -> High concern — provisions up >25–50%; material deterioration in asset quality. | O34: =IF($J34=1,IFERROR(INDEX('Scoring Engine (Rules)'!$P$5:$P$163,MATCH($A34&"|"&$I34,'Scoring Engine (Rules)'!$R$5:$R$163,0)),""),"") -> 1) Reassess viability given the losses. 2) Enhanced monitoring. 3) Escalate to Credit. | P34: =IF($J34=1,IFERROR(INDEX('Scoring Engine (Rules)'!$Q$5:$Q$163,MATCH($A34&"|"&$I34,'Scoring Engine (Rules)'!$R$5:$R$163,0)),""),"") -> Credit Committee / Zonal Credit
A35: EWS-013 | B35: Actual vs CMA projection variance % | C35: EWS | D35: =INDEX('Indicator Master'!$F$4:$F$46,MATCH($A35,'Indicator Master'!$A$4:$A$46,0)) -> No | E35: =INDEX('Indicator Master'!$N$4:$N$46,MATCH($A35,'Indicator Master'!$A$4:$A$46,0)) -> 35 | F35: Y | G35: Y | H35: Matches band: 5-15% → band '5-15%' | I35: 10 | J35: =IF(AND($F35="Y",$G35="Y",ISNUMBER($I35)),1,0) -> 1 | K35: =IF($J35=1,$I35/$E35*'Risk Bands (Config)'!$B$5,"") -> 28.571429 | L35: =IF(AND($D35="Yes",$J35=1,$I35/$E35*'Risk Bands (Config)'!$B$5>='Risk Bands (Config)'!$B$6),1,0) -> 0 | M35: =$M34&IF($L35=1,IF($M34="","",", ")&$A35,"") | N35: =IF($J35=1,IFERROR(INDEX('Scoring Engine (Rules)'!$O$5:$O$163,MATCH($A35&"|"&$I35,'Scoring Engine (Rules)'!$R$5:$R$163,0)),""),"") -> Early warning — 5–15% variance; mild under-performance vs projections. | O35: =IF($J35=1,IFERROR(INDEX('Scoring Engine (Rules)'!$P$5:$P$163,MATCH($A35&"|"&$I35,'Scoring Engine (Rules)'!$R$5:$R$163,0)),""),"") -> 1) Analyse the variance. 2) Revisit assumptions with the RM. 3) Monitor. | P35: =IF($J35=1,IFERROR(INDEX('Scoring Engine (Rules)'!$Q$5:$Q$163,MATCH($A35&"|"&$I35,'Scoring Engine (Rules)'!$R$5:$R$163,0)),""),"") -> Relationship Manager (Branch)
... A37: EWS-015 | B37: Finance cost growth vs sales growth % | C37: EWS | D37: =INDEX('Indicator Master'!$F$4:$F$46,MATCH($A37,'Indicator Master'!$A$4:$A$46,0)) -> No | E37: =INDEX('Indicator Master'!$N$4:$N$46,MATCH($A37,'Indicator Master'!$A$4:$A$46,0)) -> 40 | F37: Y | G37: Y | H37: Matches band: Stable → band 'Stable' | I37: 0 | J37: =IF(AND($F37="Y",$G37="Y",ISNUMBER($I37)),1,0) -> 1 | K37: =IF($J37=1,$I37/$E37*'Risk Bands (Config)'!$B$5,"") -> 0 | L37: =IF(AND($D37="Yes",$J37=1,$I37/$E37*'Risk Bands (Config)'!$B$5>='Risk Bands (Config)'!$B$6),1,0) -> 0 | M37: =$M36&IF($L37=1,IF($M36="","",", ")&$A37,"") | N37: =IF($J37=1,IFERROR(INDEX('Scoring Engine (Rules)'!$O$5:$O$163,MATCH($A37&"|"&$I37,'Scoring Engine (Rules)'!$R$5:$R$163,0)),""),"") -> Normal — finance cost growing in line with sales; leverage stable. | O37: =IF($J37=1,IFERROR(INDEX('Scoring Engine (Rules)'!$P$5:$P$163,MATCH($A37&"|"&$I37,'Scoring Engine (Rules)'!$R$5:$R$163,0)),""),"") -> No remedial action required. Continue routine monitoring at the standard review cycle and record the reading. | P37: =IF($J37=1,IFERROR(INDEX('Scoring Engine (Rules)'!$Q$5:$Q$163,MATCH($A37&"|"&$I37,'Scoring Engine (Rules)'!$R$5:$R$163,0)),""),"") -> RM (routine)
A38: EWS-016 | B38: LC devolvement events | C38: EWS | D38: =INDEX('Indicator Master'!$F$4:$F$46,MATCH($A38,'Indicator Master'!$A$4:$A$46,0)) -> No | E38: =INDEX('Indicator Master'!$N$4:$N$46,MATCH($A38,'Indicator Master'!$A$4:$A$46,0)) -> 50 | F38: N | H38: Not applicable to this borrower | J38: =IF(AND($F38="Y",$G38="Y",ISNUMBER($I38)),1,0) -> 0 | K38: =IF($J38=1,$I38/$E38*'Risk Bands (Config)'!$B$5,"") | L38: =IF(AND($D38="Yes",$J38=1,$I38/$E38*'Risk Bands (Config)'!$B$5>='Risk Bands (Config)'!$B$6),1,0) -> 0 | M38: =$M37&IF($L38=1,IF($M37="","",", ")&$A38,"") | N38: =IF($J38=1,IFERROR(INDEX('Scoring Engine (Rules)'!$O$5:$O$163,MATCH($A38&"|"&$I38,'Scoring Engine (Rules)'!$R$5:$R$163,0)),""),"") | O38: =IF($J38=1,IFERROR(INDEX('Scoring Engine (Rules)'!$P$5:$P$163,MATCH($A38&"|"&$I38,'Scoring Engine (Rules)'!$R$5:$R$163,0)),""),"") | P38: =IF($J38=1,IFERROR(INDEX('Scoring Engine (Rules)'!$Q$5:$Q$163,MATCH($A38&"|"&$I38,'Scoring Engine (Rules)'!$R$5:$R$163,0)),""),"")
A39: EWS-017 | B39: BG invocation events | C39: EWS | D39: =INDEX('Indicator Master'!$F$4:$F$46,MATCH($A39,'Indicator Master'!$A$4:$A$46,0)) -> No | E39: =INDEX('Indicator Master'!$N$4:$N$46,MATCH($A39,'Indicator Master'!$A$4:$A$46,0)) -> 50 | F39: N | H39: Not applicable to this borrower | J39: =IF(AND($F39="Y",$G39="Y",ISNUMBER($I39)),1,0) -> 0 | K39: =IF($J39=1,$I39/$E39*'Risk Bands (Config)'!$B$5,"") | L39: =IF(AND($D39="Yes",$J39=1,$I39/$E39*'Risk Bands (Config)'!$B$5>='Risk Bands (Config)'!$B$6),1,0) -> 0 | M39: =$M38&IF($L39=1,IF($M38="","",", ")&$A39,"") | N39: =IF($J39=1,IFERROR(INDEX('Scoring Engine (Rules)'!$O$5:$O$163,MATCH($A39&"|"&$I39,'Scoring Engine (Rules)'!$R$5:$R$163,0)),""),"") | O39: =IF($J39=1,IFERROR(INDEX('Scoring Engine (Rules)'!$P$5:$P$163,MATCH($A39&"|"&$I39,'Scoring Engine (Rules)'!$R$5:$R$163,0)),""),"") | P39: =IF($J39=1,IFERROR(INDEX('Scoring Engine (Rules)'!$Q$5:$Q$163,MATCH($A39&"|"&$I39,'Scoring Engine (Rules)'!$R$5:$R$163,0)),""),"")
A40: EWS-018 | B40: Rating notch movement | C40: EWS | D40: =INDEX('Indicator Master'!$F$4:$F$46,MATCH($A40,'Indicator Master'!$A$4:$A$46,0)) -> No | E40: =INDEX('Indicator Master'!$N$4:$N$46,MATCH($A40,'Indicator Master'!$A$4:$A$46,0)) -> 40 | F40: Y | G40: N | H40: Applicable but data not available (excluded, not zero) | J40: =IF(AND($F40="Y",$G40="Y",ISNUMBER($I40)),1,0) -> 0 | K40: =IF($J40=1,$I40/$E40*'Risk Bands (Config)'!$B$5,"") | L40: =IF(AND($D40="Yes",$J40=1,$I40/$E40*'Risk Bands (Config)'!$B$5>='Risk Bands (Config)'!$B$6),1,0) -> 0 | M40: =$M39&IF($L40=1,IF($M39="","",", ")&$A40,"") | N40: =IF($J40=1,IFERROR(INDEX('Scoring Engine (Rules)'!$O$5:$O$163,MATCH($A40&"|"&$I40,'Scoring Engine (Rules)'!$R$5:$R$163,0)),""),"") | O40: =IF($J40=1,IFERROR(INDEX('Scoring Engine (Rules)'!$P$5:$P$163,MATCH($A40&"|"&$I40,'Scoring Engine (Rules)'!$R$5:$R$163,0)),""),"") | P40: =IF($J40=1,IFERROR(INDEX('Scoring Engine (Rules)'!$Q$5:$Q$163,MATCH($A40&"|"&$I40,'Scoring Engine (Rules)'!$R$5:$R$163,0)),""),"")
A41: EWS-019 | B41: Frequent change in Financial year/Accounting period | C41: EWS | D41: =INDEX('Indicator Master'!$F$4:$F$46,MATCH($A41,'Indicator Master'!$A$4:$A$46,0)) -> No | E41: =INDEX('Indicator Master'!$N$4:$N$46,MATCH($A41,'Indicator Master'!$A$4:$A$46,0)) -> 40 | F41: Y | G41: Y | H41: Matches band: No significant change/irregularity → band 'No significant change/irregularity' | I41: 0 | J41: =IF(AND($F41="Y",$G41="Y",ISNUMBER($I41)),1,0) -> 1 | K41: =IF($J41=1,$I41/$E41*'Risk Bands (Config)'!$B$5,"") -> 0 | L41: =IF(AND($D41="Yes",$J41=1,$I41/$E41*'Risk Bands (Config)'!$B$5>='Risk Bands (Config)'!$B$6),1,0) -> 0 | M41: =$M40&IF($L41=1,IF($M40="","",", ")&$A41,"") | N41: =IF($J41=1,IFERROR(INDEX('Scoring Engine (Rules)'!$O$5:$O$163,MATCH($A41&"|"&$I41,'Scoring Engine (Rules)'!$R$5:$R$163,0)),""),"") -> Normal — no change in financial year/auditor; reporting stable. | O41: =IF($J41=1,IFERROR(INDEX('Scoring Engine (Rules)'!$P$5:$P$163,MATCH($A41&"|"&$I41,'Scoring Engine (Rules)'!$R$5:$R$163,0)),""),"") -> No remedial action required. Continue routine monitoring at the standard review cycle and record the reading. | P41: =IF($J41=1,IFERROR(INDEX('Scoring Engine (Rules)'!$Q$5:$Q$163,MATCH($A41&"|"&$I41,'Scoring Engine (Rules)'!$R$5:$R$163,0)),""),"") -> RM (routine)
A42: EWS-020 | B42: Auditor change events | C42: EWS | D42: =INDEX('Indicator Master'!$F$4:$F$46,MATCH($A42,'Indicator Master'!$A$4:$A$46,0)) -> No | E42: =INDEX('Indicator Master'!$N$4:$N$46,MATCH($A42,'Indicator Master'!$A$4:$A$46,0)) -> 40 | F42: Y | G42: Y | H42: Matches band: No issue → band 'No issue' | I42: 0 | J42: =IF(AND($F42="Y",$G42="Y",ISNUMBER($I42)),1,0) -> 1 | K42: =IF($J42=1,$I42/$E42*'Risk Bands (Config)'!$B$5,"") -> 0 | L42: =IF(AND($D42="Yes",$J42=1,$I42/$E42*'Risk Bands (Config)'!$B$5>='Risk Bands (Config)'!$B$6),1,0) -> 0 | M42: =$M41&IF($L42=1,IF($M41="","",", ")&$A42,"") | N42: =IF($J42=1,IFERROR(INDEX('Scoring Engine (Rules)'!$O$5:$O$163,MATCH($A42&"|"&$I42,'Scoring Engine (Rules)'!$R$5:$R$163,0)),""),"") -> Normal — clean audit, no issue; reliable reporting. | O42: =IF($J42=1,IFERROR(INDEX('Scoring Engine (Rules)'!$P$5:$P$163,MATCH($A42&"|"&$I42,'Scoring Engine (Rules)'!$R$5:$R$163,0)),""),"") -> No remedial action required. Continue routine monitoring at the standard review cycle and record the reading. | P42: =IF($J42=1,IFERROR(INDEX('Scoring Engine (Rules)'!$Q$5:$Q$163,MATCH($A42&"|"&$I42,'Scoring Engine (Rules)'!$R$5:$R$163,0)),""),"") -> RM (routine)
A43: EWS-021 | B43: Key management change events | C43: EWS | D43: =INDEX('Indicator Master'!$F$4:$F$46,MATCH($A43,'Indicator Master'!$A$4:$A$46,0)) -> No | E43: =INDEX('Indicator Master'!$N$4:$N$46,MATCH($A43,'Indicator Master'!$A$4:$A$46,0)) -> 40 | F43: Y | G43: Y | H43: Matches band: No adverse change → band 'No adverse change' | I43: 0 | J43: =IF(AND($F43="Y",$G43="Y",ISNUMBER($I43)),1,0) -> 1 | K43: =IF($J43=1,$I43/$E43*'Risk Bands (Config)'!$B$5,"") -> 0 | L43: =IF(AND($D43="Yes",$J43=1,$I43/$E43*'Risk Bands (Config)'!$B$5>='Risk Bands (Config)'!$B$6),1,0) -> 0 | M43: =$M42&IF($L43=1,IF($M42="","",", ")&$A43,"") | N43: =IF($J43=1,IFERROR(INDEX('Scoring Engine (Rules)'!$O$5:$O$163,MATCH($A43&"|"&$I43,'Scoring Engine (Rules)'!$R$5:$R$163,0)),""),"") -> Normal — no adverse management change; continuity intact. | O43: =IF($J43=1,IFERROR(INDEX('Scoring Engine (Rules)'!$P$5:$P$163,MATCH($A43&"|"&$I43,'Scoring Engine (Rules)'!$R$5:$R$163,0)),""),"") -> No remedial action required. Continue routine monitoring at the standard review cycle and record the reading. | P43: =IF($J43=1,IFERROR(INDEX('Scoring Engine (Rules)'!$Q$5:$Q$163,MATCH($A43&"|"&$I43,'Scoring Engine (Rules)'!$R$5:$R$163,0)),""),"") -> RM (routine)
A44: EWS-022 | B44: % promoter shares pledged | C44: EWS | D44: =INDEX('Indicator Master'!$F$4:$F$46,MATCH($A44,'Indicator Master'!$A$4:$A$46,0)) -> No | E44: =INDEX('Indicator Master'!$N$4:$N$46,MATCH($A44,'Indicator Master'!$A$4:$A$46,0)) -> 40 | F44: N | H44: Not applicable to this borrower | J44: =IF(AND($F44="Y",$G44="Y",ISNUMBER($I44)),1,0) -> 0 | K44: =IF($J44=1,$I44/$E44*'Risk Bands (Config)'!$B$5,"") | L44: =IF(AND($D44="Yes",$J44=1,$I44/$E44*'Risk Bands (Config)'!$B$5>='Risk Bands (Config)'!$B$6),1,0) -> 0 | M44: =$M43&IF($L44=1,IF($M43="","",", ")&$A44,"") | N44: =IF($J44=1,IFERROR(INDEX('Scoring Engine (Rules)'!$O$5:$O$163,MATCH($A44&"|"&$I44,'Scoring Engine (Rules)'!$R$5:$R$163,0)),""),"") | O44: =IF($J44=1,IFERROR(INDEX('Scoring Engine (Rules)'!$P$5:$P$163,MATCH($A44&"|"&$I44,'Scoring Engine (Rules)'!$R$5:$R$163,0)),""),"") | P44: =IF($J44=1,IFERROR(INDEX('Scoring Engine (Rules)'!$Q$5:$Q$163,MATCH($A44&"|"&$I44,'Scoring Engine (Rules)'!$R$5:$R$163,0)),""),"")
A45: EWS-023 | B45: Decline in promoter holding % | C45: EWS | D45: =INDEX('Indicator Master'!$F$4:$F$46,MATCH($A45,'Indicator Master'!$A$4:$A$46,0)) -> No | E45: =INDEX('Indicator Master'!$N$4:$N$46,MATCH($A45,'Indicator Master'!$A$4:$A$46,0)) -> 40 | F45: N | H45: Not applicable to this borrower | J45: =IF(AND($F45="Y",$G45="Y",ISNUMBER($I45)),1,0) -> 0 | K45: =IF($J45=1,$I45/$E45*'Risk Bands (Config)'!$B$5,"") | L45: =IF(AND($D45="Yes",$J45=1,$I45/$E45*'Risk Bands (Config)'!$B$5>='Risk Bands (Config)'!$B$6),1,0) -> 0 | M45: =$M44&IF($L45=1,IF($M44="","",", ")&$A45,"") | N45: =IF($J45=1,IFERROR(INDEX('Scoring Engine (Rules)'!$O$5:$O$163,MATCH($A45&"|"&$I45,'Scoring Engine (Rules)'!$R$5:$R$163,0)),""),"") | O45: =IF($J45=1,IFERROR(INDEX('Scoring Engine (Rules)'!$P$5:$P$163,MATCH($A45&"|"&$I45,'Scoring Engine (Rules)'!$R$5:$R$163,0)),""),"") | P45: =IF($J45=1,IFERROR(INDEX('Scoring Engine (Rules)'!$Q$5:$Q$163,MATCH($A45&"|"&$I45,'Scoring Engine (Rules)'!$R$5:$R$163,0)),""),"")
A46: EWS-024 | B46: RPT value/share change % | C46: EWS | D46: =INDEX('Indicator Master'!$F$4:$F$46,MATCH($A46,'Indicator Master'!$A$4:$A$46,0)) -> No | E46: =INDEX('Indicator Master'!$N$4:$N$46,MATCH($A46,'Indicator Master'!$A$4:$A$46,0)) -> 40 | F46: Y | G46: N | H46: Applicable but data not available (excluded, not zero) | J46: =IF(AND($F46="Y",$G46="Y",ISNUMBER($I46)),1,0) -> 0 | K46: =IF($J46=1,$I46/$E46*'Risk Bands (Config)'!$B$5,"") | L46: =IF(AND($D46="Yes",$J46=1,$I46/$E46*'Risk Bands (Config)'!$B$5>='Risk Bands (Config)'!$B$6),1,0) -> 0 | M46: =$M45&IF($L46=1,IF($M45="","",", ")&$A46,"") | N46: =IF($J46=1,IFERROR(INDEX('Scoring Engine (Rules)'!$O$5:$O$163,MATCH($A46&"|"&$I46,'Scoring Engine (Rules)'!$R$5:$R$163,0)),""),"") | O46: =IF($J46=1,IFERROR(INDEX('Scoring Engine (Rules)'!$P$5:$P$163,MATCH($A46&"|"&$I46,'Scoring Engine (Rules)'!$R$5:$R$163,0)),""),"") | P46: =IF($J46=1,IFERROR(INDEX('Scoring Engine (Rules)'!$Q$5:$Q$163,MATCH($A46&"|"&$I46,'Scoring Engine (Rules)'!$R$5:$R$163,0)),""),"")
A47: EWS-025 | B47: Group-entity stress classification | C47: EWS | D47: =INDEX('Indicator Master'!$F$4:$F$46,MATCH($A47,'Indicator Master'!$A$4:$A$46,0)) -> No | E47: =INDEX('Indicator Master'!$N$4:$N$46,MATCH($A47,'Indicator Master'!$A$4:$A$46,0)) -> 40 | F47: Y | G47: Y | H47: Matches band: No group stress → band 'No group stress' | I47: 0 | J47: =IF(AND($F47="Y",$G47="Y",ISNUMBER($I47)),1,0) -> 1 | K47: =IF($J47=1,$I47/$E47*'Risk Bands (Config)'!$B$5,"") -> 0 | L47: =IF(AND($D47="Yes",$J47=1,$I47/$E47*'Risk Bands (Config)'!$B$5>='Risk Bands (Config)'!$B$6),1,0) -> 0 | M47: =$M46&IF($L47=1,IF($M46="","",", ")&$A47,"") | N47: =IF($J47=1,IFERROR(INDEX('Scoring Engine (Rules)'!$O$5:$O$163,MATCH($A47&"|"&$I47,'Scoring Engine (Rules)'!$R$5:$R$163,0)),""),"") -> Normal — no group stress; group profile stable. | O47: =IF($J47=1,IFERROR(INDEX('Scoring Engine (Rules)'!$P$5:$P$163,MATCH($A47&"|"&$I47,'Scoring Engine (Rules)'!$R$5:$R$163,0)),""),"") -> No remedial action required. Continue routine monitoring at the standard review cycle and record the reading. | P47: =IF($J47=1,IFERROR(INDEX('Scoring Engine (Rules)'!$Q$5:$Q$163,MATCH($A47&"|"&$I47,'Scoring Engine (Rules)'!$R$5:$R$163,0)),""),"") -> RM (routine)
A48: EWS-026 | B48: Statutory overdues | C48: EWS | D48: =INDEX('Indicator Master'!$F$4:$F$46,MATCH($A48,'Indicator Master'!$A$4:$A$46,0)) -> Yes | E48: =INDEX('Indicator Master'!$N$4:$N$46,MATCH($A48,'Indicator Master'!$A$4:$A$46,0)) -> 35 | F48: Y | G48: Y | H48: GST/PF/TDS dues overdue 3+ months → band '3+ months' | I48: 35 | J48: =IF(AND($F48="Y",$G48="Y",ISNUMBER($I48)),1,0) -> 1 | K48: =IF($J48=1,$I48/$E48*'Risk Bands (Config)'!$B$5,"") -> 100 | L48: =IF(AND($D48="Yes",$J48=1,$I48/$E48*'Risk Bands (Config)'!$B$5>='Risk Bands (Config)'!$B$6),1,0) -> 1 | M48: =$M47&IF($L48=1,IF($M47="","",", ")&$A48,"") -> EWS-026 | N48: =IF($J48=1,IFERROR(INDEX('Scoring Engine (Rules)'!$O$5:$O$163,MATCH($A48&"|"&$I48,'Scoring Engine (Rules)'!$R$5:$R$163,0)),""),"") -> Severe / critical — 3+ months overdue; severe — large statutory arrears ranking ahead of the bank, attachment risk. | O48: =IF($J48=1,IFERROR(INDEX('Scoring Engine (Rules)'!$P$5:$P$163,MATCH($A48&"|"&$I48,'Scoring Engine (Rules)'!$R$5:$R$163,0)),""),"") -> [CRITICAL] 1) Treat as serious stress — statutory dues rank ahead of the bank. 2) Verify no attachment/first-charge; liquidity/forensic review. 3) Corrective / recovery plan; escalate immediately. NOTE: CRITICAL indicator — statutory dues rank ahead of the bank; worst band fires the Critical Override → final status escalates to Critical. | P48: =IF($J48=1,IFERROR(INDEX('Scoring Engine (Rules)'!$Q$5:$Q$163,MATCH($A48&"|"&$I48,'Scoring Engine (Rules)'!$R$5:$R$163,0)),""),"") -> Credit Head / Risk (immediate)
A49: EWS-027 | B49: Regulatory event severity | C49: EWS | D49: =INDEX('Indicator Master'!$F$4:$F$46,MATCH($A49,'Indicator Master'!$A$4:$A$46,0)) -> No | E49: =INDEX('Indicator Master'!$N$4:$N$46,MATCH($A49,'Indicator Master'!$A$4:$A$46,0)) -> 50 | F49: Y | G49: Y | H49: One civil/regulatory notice on record → band 'regulatory notice' | I49: 15 | J49: =IF(AND($F49="Y",$G49="Y",ISNUMBER($I49)),1,0) -> 1 | K49: =IF($J49=1,$I49/$E49*'Risk Bands (Config)'!$B$5,"") -> 30 | L49: =IF(AND($D49="Yes",$J49=1,$I49/$E49*'Risk Bands (Config)'!$B$5>='Risk Bands (Config)'!$B$6),1,0) -> 0 | M49: =$M48&IF($L49=1,IF($M48="","",", ")&$A49,"") -> EWS-026 | N49: =IF($J49=1,IFERROR(INDEX('Scoring Engine (Rules)'!$O$5:$O$163,MATCH($A49&"|"&$I49,'Scoring Engine (Rules)'!$R$5:$R$163,0)),""),"") -> Early warning — a regulatory notice received; early compliance concern. | O49: =IF($J49=1,IFERROR(INDEX('Scoring Engine (Rules)'!$P$5:$P$163,MATCH($A49&"|"&$I49,'Scoring Engine (Rules)'!$R$5:$R$163,0)),""),"") -> 1) Obtain notice details; assess materiality. 2) Legal opinion if needed. 3) Monitor. | P49: =IF($J49=1,IFERROR(INDEX('Scoring Engine (Rules)'!$Q$5:$Q$163,MATCH($A49&"|"&$I49,'Scoring Engine (Rules)'!$R$5:$R$163,0)),""),"") -> Relationship Manager (Branch)
A50: EWS-028 | B50: Increasing litigation exposure | C50: EWS | D50: =INDEX('Indicator Master'!$F$4:$F$46,MATCH($A50,'Indicator Master'!$A$4:$A$46,0)) -> No | E50: =INDEX('Indicator Master'!$N$4:$N$46,MATCH($A50,'Indicator Master'!$A$4:$A$46,0)) -> 40 | F50: Y | G50: Y | H50: Matches band: Moderate increase → band 'Moderate increase' | I50: 15 | J50: =IF(AND($F50="Y",$G50="Y",ISNUMBER($I50)),1,0) -> 1 | K50: =IF($J50=1,$I50/$E50*'Risk Bands (Config)'!$B$5,"") -> 37.5 | L50: =IF(AND($D50="Yes",$J50=1,$I50/$E50*'Risk Bands (Config)'!$B$5>='Risk Bands (Config)'!$B$6),1,0) -> 0 | M50: =$M49&IF($L50=1,IF($M49="","",", ")&$A50,"") -> EWS-026 | N50: =IF($J50=1,IFERROR(INDEX('Scoring Engine (Rules)'!$O$5:$O$163,MATCH($A50&"|"&$I50,'Scoring Engine (Rules)'!$R$5:$R$163,0)),""),"") -> Elevated concern — case count up >10–25% with no material case; rising but immaterial litigation. | O50: =IF($J50=1,IFERROR(INDEX('Scoring Engine (Rules)'!$P$5:$P$163,MATCH($A50&"|"&$I50,'Scoring Engine (Rules)'!$R$5:$R$163,0)),""),"") -> 1) Review the nature of new cases. 2) Legal opinion on aggregate exposure. 3) Monitor. | P50: =IF($J50=1,IFERROR(INDEX('Scoring Engine (Rules)'!$Q$5:$Q$163,MATCH($A50&"|"&$I50,'Scoring Engine (Rules)'!$R$5:$R$163,0)),""),"") -> RM + Credit Analyst
A51: EWS-029 | B51: Business-model change classification | C51: EWS | D51: =INDEX('Indicator Master'!$F$4:$F$46,MATCH($A51,'Indicator Master'!$A$4:$A$46,0)) -> No | E51: =INDEX('Indicator Master'!$N$4:$N$46,MATCH($A51,'Indicator Master'!$A$4:$A$46,0)) -> 40 | F51: Y | G51: Y | H51: Matches band: No trigger → band 'No trigger' | I51: 0 | J51: =IF(AND($F51="Y",$G51="Y",ISNUMBER($I51)),1,0) -> 1 | K51: =IF($J51=1,$I51/$E51*'Risk Bands (Config)'!$B$5,"") -> 0 | L51: =IF(AND($D51="Yes",$J51=1,$I51/$E51*'Risk Bands (Config)'!$B$5>='Risk Bands (Config)'!$B$6),1,0) -> 0 | M51: =$M50&IF($L51=1,IF($M50="","",", ")&$A51,"") -> EWS-026 | N51: =IF($J51=1,IFERROR(INDEX('Scoring Engine (Rules)'!$O$5:$O$163,MATCH($A51&"|"&$I51,'Scoring Engine (Rules)'!$R$5:$R$163,0)),""),"") -> Normal — no change in business model; risk profile stable. | O51: =IF($J51=1,IFERROR(INDEX('Scoring Engine (Rules)'!$P$5:$P$163,MATCH($A51&"|"&$I51,'Scoring Engine (Rules)'!$R$5:$R$163,0)),""),"") -> No remedial action required. Continue routine monitoring at the standard review cycle and record the reading. | P51: =IF($J51=1,IFERROR(INDEX('Scoring Engine (Rules)'!$Q$5:$Q$163,MATCH($A51&"|"&$I51,'Scoring Engine (Rules)'!$R$5:$R$163,0)),""),"") -> RM (routine)
A52: EWS-030 | B52: Borrower vs sector growth gap | C52: EWS | D52: =INDEX('Indicator Master'!$F$4:$F$46,MATCH($A52,'Indicator Master'!$A$4:$A$46,0)) -> No | E52: =INDEX('Indicator Master'!$N$4:$N$46,MATCH($A52,'Indicator Master'!$A$4:$A$46,0)) -> 40 | F52: Y | G52: N | H52: Applicable but data not available (excluded, not zero) | J52: =IF(AND($F52="Y",$G52="Y",ISNUMBER($I52)),1,0) -> 0 | K52: =IF($J52=1,$I52/$E52*'Risk Bands (Config)'!$B$5,"") | L52: =IF(AND($D52="Yes",$J52=1,$I52/$E52*'Risk Bands (Config)'!$B$5>='Risk Bands (Config)'!$B$6),1,0) -> 0 | M52: =$M51&IF($L52=1,IF($M51="","",", ")&$A52,"") -> EWS-026 | N52: =IF($J52=1,IFERROR(INDEX('Scoring Engine (Rules)'!$O$5:$O$163,MATCH($A52&"|"&$I52,'Scoring Engine (Rules)'!$R$5:$R$163,0)),""),"") | O52: =IF($J52=1,IFERROR(INDEX('Scoring Engine (Rules)'!$P$5:$P$163,MATCH($A52&"|"&$I52,'Scoring Engine (Rules)'!$R$5:$R$163,0)),""),"") | P52: =IF($J52=1,IFERROR(INDEX('Scoring Engine (Rules)'!$Q$5:$Q$163,MATCH($A52&"|"&$I52,'Scoring Engine (Rules)'!$R$5:$R$163,0)),""),"")
A53: EWS-031 | B53: News severity classification | C53: EWS | D53: =INDEX('Indicator Master'!$F$4:$F$46,MATCH($A53,'Indicator Master'!$A$4:$A$46,0)) -> No | E53: =INDEX('Indicator Master'!$N$4:$N$46,MATCH($A53,'Indicator Master'!$A$4:$A$46,0)) -> 50 | F53: Y | G53: Y | H53: Matches band: No adverse news → band 'No adverse news' | I53: 0 | J53: =IF(AND($F53="Y",$G53="Y",ISNUMBER($I53)),1,0) -> 1 | K53: =IF($J53=1,$I53/$E53*'Risk Bands (Config)'!$B$5,"") -> 0 | L53: =IF(AND($D53="Yes",$J53=1,$I53/$E53*'Risk Bands (Config)'!$B$5>='Risk Bands (Config)'!$B$6),1,0) -> 0 | M53: =$M52&IF($L53=1,IF($M52="","",", ")&$A53,"") -> EWS-026 | N53: =IF($J53=1,IFERROR(INDEX('Scoring Engine (Rules)'!$O$5:$O$163,MATCH($A53&"|"&$I53,'Scoring Engine (Rules)'!$R$5:$R$163,0)),""),"") -> Normal — no adverse news; reputation intact. | O53: =IF($J53=1,IFERROR(INDEX('Scoring Engine (Rules)'!$P$5:$P$163,MATCH($A53&"|"&$I53,'Scoring Engine (Rules)'!$R$5:$R$163,0)),""),"") -> No remedial action required. Continue routine monitoring at the standard review cycle and record the reading. | P53: =IF($J53=1,IFERROR(INDEX('Scoring Engine (Rules)'!$Q$5:$Q$163,MATCH($A53&"|"&$I53,'Scoring Engine (Rules)'!$R$5:$R$163,0)),""),"") -> RM (routine)
A54: EWS-032 | B54: Complaint severity classification | C54: EWS | D54: =INDEX('Indicator Master'!$F$4:$F$46,MATCH($A54,'Indicator Master'!$A$4:$A$46,0)) -> Yes | E54: =INDEX('Indicator Master'!$N$4:$N$46,MATCH($A54,'Indicator Master'!$A$4:$A$46,0)) -> 40 | F54: Y | G54: Y | H54: Matches band: No/minor complaint → band 'No/minor complaint' | I54: 0 | J54: =IF(AND($F54="Y",$G54="Y",ISNUMBER($I54)),1,0) -> 1 | K54: =IF($J54=1,$I54/$E54*'Risk Bands (Config)'!$B$5,"") -> 0 | L54: =IF(AND($D54="Yes",$J54=1,$I54/$E54*'Risk Bands (Config)'!$B$5>='Risk Bands (Config)'!$B$6),1,0) -> 0 | M54: =$M53&IF($L54=1,IF($M53="","",", ")&$A54,"") -> EWS-026 | N54: =IF($J54=1,IFERROR(INDEX('Scoring Engine (Rules)'!$O$5:$O$163,MATCH($A54&"|"&$I54,'Scoring Engine (Rules)'!$R$5:$R$163,0)),""),"") -> Normal — no/minor complaints; normal counterparty relations. | O54: =IF($J54=1,IFERROR(INDEX('Scoring Engine (Rules)'!$P$5:$P$163,MATCH($A54&"|"&$I54,'Scoring Engine (Rules)'!$R$5:$R$163,0)),""),"") -> No remedial action required. Continue routine monitoring at the standard review cycle and record the reading. | P54: =IF($J54=1,IFERROR(INDEX('Scoring Engine (Rules)'!$Q$5:$Q$163,MATCH($A54&"|"&$I54,'Scoring Engine (Rules)'!$R$5:$R$163,0)),""),"") -> RM (routine)
A55: EWS-033 | B55: Workforce disruption classification | C55: EWS | D55: =INDEX('Indicator Master'!$F$4:$F$46,MATCH($A55,'Indicator Master'!$A$4:$A$46,0)) -> No | E55: =INDEX('Indicator Master'!$N$4:$N$46,MATCH($A55,'Indicator Master'!$A$4:$A$46,0)) -> 40 | F55: Y | G55: Y | H55: Matches band: Normal operations → band 'Normal operations' | I55: 0 | J55: =IF(AND($F55="Y",$G55="Y",ISNUMBER($I55)),1,0) -> 1 | K55: =IF($J55=1,$I55/$E55*'Risk Bands (Config)'!$B$5,"") -> 0 | L55: =IF(AND($D55="Yes",$J55=1,$I55/$E55*'Risk Bands (Config)'!$B$5>='Risk Bands (Config)'!$B$6),1,0) -> 0 | M55: =$M54&IF($L55=1,IF($M54="","",", ")&$A55,"") -> EWS-026 | N55: =IF($J55=1,IFERROR(INDEX('Scoring Engine (Rules)'!$O$5:$O$163,MATCH($A55&"|"&$I55,'Scoring Engine (Rules)'!$R$5:$R$163,0)),""),"") -> Normal — normal operations; no workforce disruption. | O55: =IF($J55=1,IFERROR(INDEX('Scoring Engine (Rules)'!$P$5:$P$163,MATCH($A55&"|"&$I55,'Scoring Engine (Rules)'!$R$5:$R$163,0)),""),"") -> No remedial action required. Continue routine monitoring at the standard review cycle and record the reading. | P55: =IF($J55=1,IFERROR(INDEX('Scoring Engine (Rules)'!$Q$5:$Q$163,MATCH($A55&"|"&$I55,'Scoring Engine (Rules)'!$R$5:$R$163,0)),""),"") -> RM (routine)
A56: EWS-034 | B56: Capacity utilization % | C56: EWS | D56: =INDEX('Indicator Master'!$F$4:$F$46,MATCH($A56,'Indicator Master'!$A$4:$A$46,0)) -> No | E56: =INDEX('Indicator Master'!$N$4:$N$46,MATCH($A56,'Indicator Master'!$A$4:$A$46,0)) -> 30 | F56: Y | G56: Y | H56: Matches band: 85-90% → band '85-90%' | I56: 10 | J56: =IF(AND($F56="Y",$G56="Y",ISNUMBER($I56)),1,0) -> 1 | K56: =IF($J56=1,$I56/$E56*'Risk Bands (Config)'!$B$5,"") -> 33.333333 | L56: =IF(AND($D56="Yes",$J56=1,$I56/$E56*'Risk Bands (Config)'!$B$5>='Risk Bands (Config)'!$B$6),1,0) -> 0 | M56: =$M55&IF($L56=1,IF($M55="","",", ")&$A56,"") -> EWS-026 | N56: =IF($J56=1,IFERROR(INDEX('Scoring Engine (Rules)'!$O$5:$O$163,MATCH($A56&"|"&$I56,'Scoring Engine (Rules)'!$R$5:$R$163,0)),""),"") -> Early warning — utilisation 85–90%; slight easing of throughput. | O56: =IF($J56=1,IFERROR(INDEX('Scoring Engine (Rules)'!$P$5:$P$163,MATCH($A56&"|"&$I56,'Scoring Engine (Rules)'!$R$5:$R$163,0)),""),"") -> 1) Note the dip; confirm the cause. 2) Watch next cycle. | P56: =IF($J56=1,IFERROR(INDEX('Scoring Engine (Rules)'!$Q$5:$Q$163,MATCH($A56&"|"&$I56,'Scoring Engine (Rules)'!$R$5:$R$163,0)),""),"") -> RM + Credit Analyst
A57: EWS-035 | B57: Adverse Site Visit Observation | C57: EWS | D57: =INDEX('Indicator Master'!$F$4:$F$46,MATCH($A57,'Indicator Master'!$A$4:$A$46,0)) -> Yes | E57: =INDEX('Indicator Master'!$N$4:$N$46,MATCH($A57,'Indicator Master'!$A$4:$A$46,0)) -> 50 | F57: Y | G57: Y | H57: Site visit satisfactory; no adverse observation | I57: 0 | J57: =IF(AND($F57="Y",$G57="Y",ISNUMBER($I57)),1,0) -> 1 | K57: =IF($J57=1,$I57/$E57*'Risk Bands (Config)'!$B$5,"") -> 0 | L57: =IF(AND($D57="Yes",$J57=1,$I57/$E57*'Risk Bands (Config)'!$B$5>='Risk Bands (Config)'!$B$6),1,0) -> 0 | M57: =$M56&IF($L57=1,IF($M56="","",", ")&$A57,"") -> EWS-026 | N57: =IF($J57=1,IFERROR(INDEX('Scoring Engine (Rules)'!$O$5:$O$163,MATCH($A57&"|"&$I57,'Scoring Engine (Rules)'!$R$5:$R$163,0)),""),"") -> Normal — site visit satisfactory; unit operating normally. | O57: =IF($J57=1,IFERROR(INDEX('Scoring Engine (Rules)'!$P$5:$P$163,MATCH($A57&"|"&$I57,'Scoring Engine (Rules)'!$R$5:$R$163,0)),""),"") -> No remedial action required. Continue routine monitoring at the standard review cycle and record the reading. | P57: =IF($J57=1,IFERROR(INDEX('Scoring Engine (Rules)'!$Q$5:$Q$163,MATCH($A57&"|"&$I57,'Scoring Engine (Rules)'!$R$5:$R$163,0)),""),"") -> RM (routine)
A58: EWS-036 | B58: Round-tripping status (none/suspected/confirmed) | C58: EWS | D58: =INDEX('Indicator Master'!$F$4:$F$46,MATCH($A58,'Indicator Master'!$A$4:$A$46,0)) -> No | E58: =INDEX('Indicator Master'!$N$4:$N$46,MATCH($A58,'Indicator Master'!$A$4:$A$46,0)) -> 50 | F58: Y | G58: Y | H58: Matches band: None → band 'None' | I58: 0 | J58: =IF(AND($F58="Y",$G58="Y",ISNUMBER($I58)),1,0) -> 1 | K58: =IF($J58=1,$I58/$E58*'Risk Bands (Config)'!$B$5,"") -> 0 | L58: =IF(AND($D58="Yes",$J58=1,$I58/$E58*'Risk Bands (Config)'!$B$5>='Risk Bands (Config)'!$B$6),1,0) -> 0 | M58: =$M57&IF($L58=1,IF($M57="","",", ")&$A58,"") -> EWS-026 | N58: =IF($J58=1,IFERROR(INDEX('Scoring Engine (Rules)'!$O$5:$O$163,MATCH($A58&"|"&$I58,'Scoring Engine (Rules)'!$R$5:$R$163,0)),""),"") -> Normal — no round-tripping indicators; clean fund flow. | O58: =IF($J58=1,IFERROR(INDEX('Scoring Engine (Rules)'!$P$5:$P$163,MATCH($A58&"|"&$I58,'Scoring Engine (Rules)'!$R$5:$R$163,0)),""),"") -> No remedial action required. Continue routine monitoring at the standard review cycle and record the reading. | P58: =IF($J58=1,IFERROR(INDEX('Scoring Engine (Rules)'!$Q$5:$Q$163,MATCH($A58&"|"&$I58,'Scoring Engine (Rules)'!$R$5:$R$163,0)),""),"") -> RM (routine)
A59: EWS-037 | B59: ESG/environmental action classification | C59: EWS | D59: =INDEX('Indicator Master'!$F$4:$F$46,MATCH($A59,'Indicator Master'!$A$4:$A$46,0)) -> No | E59: =INDEX('Indicator Master'!$N$4:$N$46,MATCH($A59,'Indicator Master'!$A$4:$A$46,0)) -> 50 | F59: Y | G59: Y | H59: Matches band: No issue → band 'No issue' | I59: 0 | J59: =IF(AND($F59="Y",$G59="Y",ISNUMBER($I59)),1,0) -> 1 | K59: =IF($J59=1,$I59/$E59*'Risk Bands (Config)'!$B$5,"") -> 0 | L59: =IF(AND($D59="Yes",$J59=1,$I59/$E59*'Risk Bands (Config)'!$B$5>='Risk Bands (Config)'!$B$6),1,0) -> 0 | M59: =$M58&IF($L59=1,IF($M58="","",", ")&$A59,"") -> EWS-026 | N59: =IF($J59=1,IFERROR(INDEX('Scoring Engine (Rules)'!$O$5:$O$163,MATCH($A59&"|"&$I59,'Scoring Engine (Rules)'!$R$5:$R$163,0)),""),"") -> Normal — no ESG/environmental issue; compliant operations. | O59: =IF($J59=1,IFERROR(INDEX('Scoring Engine (Rules)'!$P$5:$P$163,MATCH($A59&"|"&$I59,'Scoring Engine (Rules)'!$R$5:$R$163,0)),""),"") -> No remedial action required. Continue routine monitoring at the standard review cycle and record the reading. | P59: =IF($J59=1,IFERROR(INDEX('Scoring Engine (Rules)'!$Q$5:$Q$163,MATCH($A59&"|"&$I59,'Scoring Engine (Rules)'!$R$5:$R$163,0)),""),"") -> RM (routine)
A60: EWS-038 | B60: Carbon Emission | C60: EWS | D60: =INDEX('Indicator Master'!$F$4:$F$46,MATCH($A60,'Indicator Master'!$A$4:$A$46,0)) -> No | E60: =INDEX('Indicator Master'!$N$4:$N$46,MATCH($A60,'Indicator Master'!$A$4:$A$46,0)) -> 40 | F60: Y | G60: Y | H60: Observed reading (remapped to new bands) | I60: 0 | J60: =IF(AND($F60="Y",$G60="Y",ISNUMBER($I60)),1,0) -> 1 | K60: =IF($J60=1,$I60/$E60*'Risk Bands (Config)'!$B$5,"") -> 0 | L60: =IF(AND($D60="Yes",$J60=1,$I60/$E60*'Risk Bands (Config)'!$B$5>='Risk Bands (Config)'!$B$6),1,0) -> 0 | M60: =$M59&IF($L60=1,IF($M59="","",", ")&$A60,"") -> EWS-026 | N60: =IF($J60=1,IFERROR(INDEX('Scoring Engine (Rules)'!$O$5:$O$163,MATCH($A60&"|"&$I60,'Scoring Engine (Rules)'!$R$5:$R$163,0)),""),"") -> Normal — carbon/emission within norms; no transition-risk concern. | O60: =IF($J60=1,IFERROR(INDEX('Scoring Engine (Rules)'!$P$5:$P$163,MATCH($A60&"|"&$I60,'Scoring Engine (Rules)'!$R$5:$R$163,0)),""),"") -> No remedial action required. Continue routine monitoring at the standard review cycle and record the reading. | P60: =IF($J60=1,IFERROR(INDEX('Scoring Engine (Rules)'!$Q$5:$Q$163,MATCH($A60&"|"&$I60,'Scoring Engine (Rules)'!$R$5:$R$163,0)),""),"") -> RM (routine)
A61: EWS-039 | B61: Change in Depreciation method | C61: EWS | D61: =INDEX('Indicator Master'!$F$4:$F$46,MATCH($A61,'Indicator Master'!$A$4:$A$46,0)) -> No | E61: =INDEX('Indicator Master'!$N$4:$N$46,MATCH($A61,'Indicator Master'!$A$4:$A$46,0)) -> 50 | F61: Y | G61: Y | H61: Observed reading | I61: 0 | J61: =IF(AND($F61="Y",$G61="Y",ISNUMBER($I61)),1,0) -> 1 | K61: =IF($J61=1,$I61/$E61*'Risk Bands (Config)'!$B$5,"") -> 0 | L61: =IF(AND($D61="Yes",$J61=1,$I61/$E61*'Risk Bands (Config)'!$B$5>='Risk Bands (Config)'!$B$6),1,0) -> 0 | M61: =$M60&IF($L61=1,IF($M60="","",", ")&$A61,"") -> EWS-026 | N61: =IF($J61=1,IFERROR(INDEX('Scoring Engine (Rules)'!$O$5:$O$163,MATCH($A61&"|"&$I61,'Scoring Engine (Rules)'!$R$5:$R$163,0)),""),"") -> Normal — no change in depreciation method; reporting consistent. | O61: =IF($J61=1,IFERROR(INDEX('Scoring Engine (Rules)'!$P$5:$P$163,MATCH($A61&"|"&$I61,'Scoring Engine (Rules)'!$R$5:$R$163,0)),""),"") -> No remedial action required. Continue routine monitoring at the standard review cycle and record the reading. | P61: =IF($J61=1,IFERROR(INDEX('Scoring Engine (Rules)'!$Q$5:$Q$163,MATCH($A61&"|"&$I61,'Scoring Engine (Rules)'!$R$5:$R$163,0)),""),"") -> RM (routine)
A62: EWS-040 | B62: Change in Inventory valuation | C62: EWS | D62: =INDEX('Indicator Master'!$F$4:$F$46,MATCH($A62,'Indicator Master'!$A$4:$A$46,0)) -> No | E62: =INDEX('Indicator Master'!$N$4:$N$46,MATCH($A62,'Indicator Master'!$A$4:$A$46,0)) -> 50 | F62: Y | G62: Y | H62: Observed reading | I62: 0 | J62: =IF(AND($F62="Y",$G62="Y",ISNUMBER($I62)),1,0) -> 1 | K62: =IF($J62=1,$I62/$E62*'Risk Bands (Config)'!$B$5,"") -> 0 | L62: =IF(AND($D62="Yes",$J62=1,$I62/$E62*'Risk Bands (Config)'!$B$5>='Risk Bands (Config)'!$B$6),1,0) -> 0 | M62: =$M61&IF($L62=1,IF($M61="","",", ")&$A62,"") -> EWS-026 | N62: =IF($J62=1,IFERROR(INDEX('Scoring Engine (Rules)'!$O$5:$O$163,MATCH($A62&"|"&$I62,'Scoring Engine (Rules)'!$R$5:$R$163,0)),""),"") -> Normal — no change in inventory-valuation method; reporting consistent. | O62: =IF($J62=1,IFERROR(INDEX('Scoring Engine (Rules)'!$P$5:$P$163,MATCH($A62&"|"&$I62,'Scoring Engine (Rules)'!$R$5:$R$163,0)),""),"") -> No remedial action required. Continue routine monitoring at the standard review cycle and record the reading. | P62: =IF($J62=1,IFERROR(INDEX('Scoring Engine (Rules)'!$Q$5:$Q$163,MATCH($A62&"|"&$I62,'Scoring Engine (Rules)'!$R$5:$R$163,0)),""),"") -> RM (routine)
A63: EWS-041 | B63: DSCR | C63: EWS | D63: =INDEX('Indicator Master'!$F$4:$F$46,MATCH($A63,'Indicator Master'!$A$4:$A$46,0)) -> No | E63: =INDEX('Indicator Master'!$N$4:$N$46,MATCH($A63,'Indicator Master'!$A$4:$A$46,0)) -> 40 | F63: Y | G63: Y | H63: Observed reading (remapped to new bands) | I63: 40 | J63: =IF(AND($F63="Y",$G63="Y",ISNUMBER($I63)),1,0) -> 1 | K63: =IF($J63=1,$I63/$E63*'Risk Bands (Config)'!$B$5,"") -> 100 | L63: =IF(AND($D63="Yes",$J63=1,$I63/$E63*'Risk Bands (Config)'!$B$5>='Risk Bands (Config)'!$B$6),1,0) -> 0 | M63: =$M62&IF($L63=1,IF($M62="","",", ")&$A63,"") -> EWS-026 | N63: =IF($J63=1,IFERROR(INDEX('Scoring Engine (Rules)'!$O$5:$O$163,MATCH($A63&"|"&$I63,'Scoring Engine (Rules)'!$R$5:$R$163,0)),""),"") -> Severe / critical — DSCR below 1.25; thin-to-inadequate coverage, cash accruals may not comfortably cover debt service. | O63: =IF($J63=1,IFERROR(INDEX('Scoring Engine (Rules)'!$P$5:$P$163,MATCH($A63&"|"&$I63,'Scoring Engine (Rules)'!$R$5:$R$163,0)),""),"") -> 1) Reassess repayment capacity, refinancing risk and viability. 2) Corrective / restructuring assessment. 3) Escalate to Credit. | P63: =IF($J63=1,IFERROR(INDEX('Scoring Engine (Rules)'!$Q$5:$Q$163,MATCH($A63&"|"&$I63,'Scoring Engine (Rules)'!$R$5:$R$163,0)),""),"") -> Credit Head / Risk
A64: EWS-042 | B64: Leverage Ratio | C64: EWS | D64: =INDEX('Indicator Master'!$F$4:$F$46,MATCH($A64,'Indicator Master'!$A$4:$A$46,0)) -> No | E64: =INDEX('Indicator Master'!$N$4:$N$46,MATCH($A64,'Indicator Master'!$A$4:$A$46,0)) -> 40 | F64: Y | G64: Y | H64: Observed reading (remapped to new bands) | I64: 40 | J64: =IF(AND($F64="Y",$G64="Y",ISNUMBER($I64)),1,0) -> 1 | K64: =IF($J64=1,$I64/$E64*'Risk Bands (Config)'!$B$5,"") -> 100 | L64: =IF(AND($D64="Yes",$J64=1,$I64/$E64*'Risk Bands (Config)'!$B$5>='Risk Bands (Config)'!$B$6),1,0) -> 0 | M64: =$M63&IF($L64=1,IF($M63="","",", ")&$A64,"") -> EWS-026 | N64: =IF($J64=1,IFERROR(INDEX('Scoring Engine (Rules)'!$O$5:$O$163,MATCH($A64&"|"&$I64,'Scoring Engine (Rules)'!$R$5:$R$163,0)),""),"") -> Severe / critical — leverage above 3.0; high/severe, thin net worth relative to debt and over-leverage risk. | O64: =IF($J64=1,IFERROR(INDEX('Scoring Engine (Rules)'!$P$5:$P$163,MATCH($A64&"|"&$I64,'Scoring Engine (Rules)'!$R$5:$R$163,0)),""),"") -> 1) Reassess leverage and net-worth adequacy; seek promoter infusion. 2) Corrective / viability review. 3) Escalate to Credit. | P64: =IF($J64=1,IFERROR(INDEX('Scoring Engine (Rules)'!$Q$5:$Q$163,MATCH($A64&"|"&$I64,'Scoring Engine (Rules)'!$R$5:$R$163,0)),""),"") -> Credit Head / Risk
A65: EWS-043 | B65: Current Ratio | C65: EWS | D65: =INDEX('Indicator Master'!$F$4:$F$46,MATCH($A65,'Indicator Master'!$A$4:$A$46,0)) -> No | E65: =INDEX('Indicator Master'!$N$4:$N$46,MATCH($A65,'Indicator Master'!$A$4:$A$46,0)) -> 40 | F65: Y | G65: Y | H65: Observed reading (remapped to new bands) | I65: 10 | J65: =IF(AND($F65="Y",$G65="Y",ISNUMBER($I65)),1,0) -> 1 | K65: =IF($J65=1,$I65/$E65*'Risk Bands (Config)'!$B$5,"") -> 25 | L65: =IF(AND($D65="Yes",$J65=1,$I65/$E65*'Risk Bands (Config)'!$B$5>='Risk Bands (Config)'!$B$6),1,0) -> 0 | M65: =$M64&IF($L65=1,IF($M64="","",", ")&$A65,"") -> EWS-026 | N65: =IF($J65=1,IFERROR(INDEX('Scoring Engine (Rules)'!$O$5:$O$163,MATCH($A65&"|"&$I65,'Scoring Engine (Rules)'!$R$5:$R$163,0)),""),"") -> Early warning — current ratio 1.00–1.33; adequate but easing liquidity buffer. | O65: =IF($J65=1,IFERROR(INDEX('Scoring Engine (Rules)'!$P$5:$P$163,MATCH($A65&"|"&$I65,'Scoring Engine (Rules)'!$R$5:$R$163,0)),""),"") -> 1) Review the working-capital position and NWC adequacy. 2) Watch next statement. | P65: =IF($J65=1,IFERROR(INDEX('Scoring Engine (Rules)'!$Q$5:$Q$163,MATCH($A65&"|"&$I65,'Scoring Engine (Rules)'!$R$5:$R$163,0)),""),"") -> Relationship Manager (Branch)
A67: Additional risk controls
A68: Previous Overall Score (last review) | C68: Optional input for band-transition alerts.
A69: Score movement vs last review | B69: =IF($B$68="","(enter previous score)",$B$14-$B$68) -> (enter previous score) | C69: Positive = deterioration.
A70: Data Sufficiency / Confidence | B70: =IF($B$12>='Risk Bands (Config)'!$B$16,"Adequate","LOW — insufficient data; treat score as low-confidence") -> Adequate | C70: Compares Data Coverage % to the floor.
A72: Critical Combination Rules (co-occurrence → immediate Critical)
A73: Rule | B73: Indicator A | C73: Indicator B | D73: A flagged? | E73: B flagged? | F73: Combination fires?
A74: Pair 1: Payment defaults + stretched creditors | B74: ="EWS-004"&" — "&INDEX($B$23:$B$65,MATCH("EWS-004",$A$23:$A$65,0)) -> EWS-004 — Payment Default Frequency | C74: ="EWS-011"&" — "&INDEX($B$23:$B$65,MATCH("EWS-011",$A$23:$A$65,0)) -> EWS-011 — Creditor days vs normal | D74: =IF(AND($J$26=1,$I$26/$E$26*'Risk Bands (Config)'!$B$5>='Risk Bands (Config)'!$B$23),"YES","NO") -> YES | E74: =IF(AND($J$33=1,$I$33/$E$33*'Risk Bands (Config)'!$B$5>='Risk Bands (Config)'!$B$23),"YES","NO") -> YES | F74: =IF(AND($D74="YES",$E74="YES"),1,0) -> 1
A75: Pair 2: Non-core repayment source + rising unsecured loans | B75: ="EWS-005"&" — "&INDEX($B$23:$B$65,MATCH("EWS-005",$A$23:$A$65,0)) -> EWS-005 — Repayment source classification | C75: ="EWS-014"&" — "&INDEX($B$23:$B$65,MATCH("EWS-014",$A$23:$A$65,0)) -> EWS-014 — Unsecured loans change % | D75: =IF(AND($J$27=1,$I$27/$E$27*'Risk Bands (Config)'!$B$5>='Risk Bands (Config)'!$B$23),"YES","NO") -> NO | E75: =IF(AND($J$36=1,$I$36/$E$36*'Risk Bands (Config)'!$B$5>='Risk Bands (Config)'!$B$23),"YES","NO") -> YES | F75: =IF(AND($D75="YES",$E75="YES"),1,0) -> 0
A76: Pair 3: Stretched debtors + rising provisions | B76: ="EWS-009"&" — "&INDEX($B$23:$B$65,MATCH("EWS-009",$A$23:$A$65,0)) -> EWS-009 — Debtor days vs normal | C76: ="EWS-012"&" — "&INDEX($B$23:$B$65,MATCH("EWS-012",$A$23:$A$65,0)) -> EWS-012 — Provisions/write-offs change % | D76: =IF(AND($J$31=1,$I$31/$E$31*'Risk Bands (Config)'!$B$5>='Risk Bands (Config)'!$B$23),"YES","NO") -> YES | E76: =IF(AND($J$34=1,$I$34/$E$34*'Risk Bands (Config)'!$B$5>='Risk Bands (Config)'!$B$23),"YES","NO") -> YES | F76: =IF(AND($D76="YES",$E76="YES"),1,0) -> 1
A77: Combination Critical Triggered? | B77: =IF(SUM($F$74:$F$76)>0,"YES","NO") -> YES | C77: If YES, the Critical Override fires and FINAL STATUS = Critical immediately, regardless of the average.
A78: Combination pairs fired | B78: =IF(LEN(IF($F$74=1,"Pair 1; ","")&IF($F$75=1,"Pair 2; ","")&IF($F$76=1,"Pair 3; ",""))=0,"None",LEFT(IF($F$74=1,"Pair 1; ","")&IF($F$75=1,"Pair 2; ","")&IF($F$76=1,"Pair 3; ",""),LEN(IF($F$74=1,"Pair 1; ","")&IF($F$75=1,"Pair 2; ","")&IF($F$76=1,"Pair 3; ",""))-2)) -> Pair 1; Pair 3

Sheet Borrower Example
A1: Borrower Example — End-to-End Worked Trace
A2: Hypothetical borrower. Live links to the Overall Score Engine. Demonstrates the Critical Combination rule firing.
A4: Profile: Acme Textiles Pvt Ltd — unlisted MSME under stress. Co-occurring signals form Critical Combination pairs (payment defaults + stretched creditors; stretched debtors + rising provisions), and statutory dues are overdue. Numerically the average is only "Yellow", but the co-occurring pairs (and the statutory-overdue critical) escalate the borrower to CRITICAL.
A6: Overall Score | B6: Numeric Risk Band | C6: Data Coverage % | D6: Critical Override? | E6: Critical Fired | F6: FINAL STATUS
A7: ='Overall Score Engine'!$B$14 -> 28.356481 | B7: ='Overall Score Engine'!$B$15 -> Yellow | C7: ='Overall Score Engine'!$B$12 -> 92.307692 | D7: ='Overall Score Engine'!$B$16 -> YES | E7: ='Overall Score Engine'!$B$17 -> EWS-026 | F7: ='Overall Score Engine'!$B$18 -> CRITICAL (Override)
A9: Critical Combination trace — the co-occurring pairs (live from the engine):
A10: Pair | B10: Indicator A | C10: Indicator B | D10: A flagged? | E10: B flagged? | F10: Combination fires? | G10: Notes
A11: ='Overall Score Engine'!$A$74 -> Pair 1: Payment defaults + stretched creditors | B11: ='Overall Score Engine'!$B$74 -> EWS-004 — Payment Default Frequency | C11: ='Overall Score Engine'!$C$74 -> EWS-011 — Creditor days vs normal | D11: ='Overall Score Engine'!$D$74 -> YES | E11: ='Overall Score Engine'!$E$74 -> YES | F11: ='Overall Score Engine'!$F$74 -> 1 | G11: Both flagged → Critical Combination fires → override
A12: ='Overall Score Engine'!$A$75 -> Pair 2: Non-core repayment source + rising unsecured loans | B12: ='Overall Score Engine'!$B$75 -> EWS-005 — Repayment source classification | C12: ='Overall Score Engine'!$C$75 -> EWS-014 — Unsecured loans change % | D12: ='Overall Score Engine'!$D$75 -> NO | E12: ='Overall Score Engine'!$E$75 -> YES | F12: ='Overall Score Engine'!$F$75 -> 0 | G12: Both flagged → Critical Combination fires → override
A13: ='Overall Score Engine'!$A$76 -> Pair 3: Stretched debtors + rising provisions | B13: ='Overall Score Engine'!$B$76 -> EWS-009 — Debtor days vs normal | C13: ='Overall Score Engine'!$C$76 -> EWS-012 — Provisions/write-offs change % | D13: ='Overall Score Engine'!$D$76 -> YES | E13: ='Overall Score Engine'!$E$76 -> YES | F13: ='Overall Score Engine'!$F$76 -> 1 | G13: Both flagged → Critical Combination fires → override
A15: Result: the Overall Score is only ~Yellow, but Critical Combination pair(s) co-occur, so the Critical Override fires and FINAL STATUS = CRITICAL — a combination of individually-sub-critical signals is treated as critical. (This borrower also breaches an individual critical, Statutory overdues; either path alone forces CRITICAL.)

Sheet Risk Bands (Config)
A1: Risk Bands & Scoring Configuration
A2: PROPOSED — not present in the source file. All values below are editable; every other sheet reads from here.
A4: Parameter | B4: Value | C4: Notes
A5: Normalisation Base | B5: 100 | C5: Normalised Score = Raw Score ÷ Maximum Score × Base
A6: Critical Override Trigger (Normalised ≥) | B6: 100 | C6: A CRITICAL-flagged indicator whose normalised score reaches this value forces FINAL STATUS = Critical, regardless of the average.
A8: Risk Band | B8: Score From | C8: Score To | D8: Lower Bound (lookup) | E8: Interpretation | F8: Recommended Supervisory Posture
A9: Green | B9: 0 | C9: 19 | D9: 0 | E9: Normal / Low Concern | F9: Business-as-usual monitoring at standard frequency.
A10: Yellow | B10: 20 | C10: 39 | D10: 20 | E10: Early Deterioration / Monitor | F10: Flag account; note trend; review at next monitoring cycle.
A11: Amber | B11: 40 | C11: 59 | D11: 40 | E11: Elevated Concern / Enhanced Monitoring | F11: Enhanced monitoring; RM commentary; tighten review frequency.
A12: Red | B12: 60 | C12: 79 | D12: 60 | E12: High Concern / Immediate Review | F12: Escalate to credit committee; borrower engagement; corrective plan.
A13: Critical | B13: 80 | C13: 100 | D13: 80 | E13: Severe EWS / Immediate Intervention | F13: Immediate intervention; classify/restructure/recovery as warranted.
A15: Additional parameters & conventions
A16: Minimum Data Coverage % (confidence floor) | B16: 60 | C16: If Data Coverage % is below this, the Overall Score is labelled INSUFFICIENT DATA / low-confidence rather than a benign band.
A18: Boundary convention | B18: Each band's exact inclusivity is given by its Operator in the Scoring Engine (Rules) sheet. Bands written as 'A–B' use ≥ lower & < upper unless the Operator states otherwise (e.g. '> lower & ≤ upper' for '>A to ≤B' bands). The worst band extends to the metric's limit. Example: a value of exactly 20% falls in the band whose Operator includes 20 at that edge.
A20: Max-score rationale | B20: The Overall Score normalises every indicator to 0–100, so all indicators are weighted EQUALLY regardless of their raw Max Score; differing max scores (25–50) only set within-indicator granularity. Indicator / category weighting is a proposed future enhancement.
A22: Critical Combination Rules (co-occurrence → immediate Critical)
A23: Combination Trigger (both indicators Normalised score ≥ 20) | B23: 1 | C23: A pair fires when BOTH indicators are scored and breached at or above this normalised level (default 1 = both above their Normal band). When any pair fires, the Critical Override triggers immediately.
A25: Rule | B25: Indicator A | C25: Indicator B | D25: Meaning
A26: Pair 1 | B26: EWS-004 | C26: EWS-011 | D26: Payment defaults + stretched creditors
A27: Pair 2 | B27: EWS-005 | C27: EWS-014 | D27: Non-core repayment source + rising unsecured loans
A28: Pair 3 | B28: EWS-009 | C28: EWS-012 | D28: Stretched debtors + rising provisions

Sheet Alert Lifecycle
A1: ALERT LIFECYCLE
A2: When the system creates an alert, how it is prioritised, and how duplicates/repeats are handled. Bands, severities and the override follow this file’s Scoring Engine and Risk Bands (Config). Distinguishes signal vs alert.
A4: A. Alert generation rules
A5: Alert ID | B5: Trigger | C5: Condition | D5: Severity | E5: Priority | F5: Recipient | G5: Notification | H5: Action SLA | I5: Escalation | J5: Duplicate Suppression | K5: Status
A6: ALERT-001 | B6: No breach | C6: All applicable indicators in the '0' (Normal) band | D6: None | E6: — | F6: — | G6: None | H6: — | I6: — | J6: — | K6: No alert
A7: ALERT-002 | B7: Indicator breach (single, immaterial) | C7: One indicator in a low non-zero band, not persistent | D7: Low | E7: P4 | F7: RM | G7: Dashboard only | H7: TBD | I7: On repeat → P3 | J7: Collapse into one open signal per indicator | K7: Signal
A8: ALERT-003 | B8: Material / repeated indicator breach | C8: Indicator reaches its material band or repeats over lookback | D8: Medium | E8: P3 | F8: RM | G8: Dashboard + email | H8: TBD | I8: Persist → Credit | J8: Suppress if same indicator already open & unchanged | K8: Alert
A9: ALERT-004 | B9: Overall score → Yellow (20-39) | C9: Overall Score in Yellow band (point-in-time); transition-based if a Previous Overall Score is recorded on the Overall Score Engine | D9: Medium | E9: P3 | F9: RM | G9: Dashboard + email | H9: TBD | I9: No action in SLA → escalate | J9: One alert per band transition | K9: Yellow Alert
A10: ALERT-005 | B10: Overall score → Amber (40-59) | C10: Overall Score in Amber band (point-in-time); transition if previous score recorded | D10: Medium-High | E10: P2 | F10: RM + Credit | G10: Dashboard + email | H10: TBD | I10: → Credit review | J10: One per transition; re-fire on worsening | K10: Amber Alert
A11: ALERT-006 | B11: Overall score → Red (60-79) | C11: Overall Score in Red band (point-in-time); transition if previous score recorded | D11: High | E11: P2 | F11: Credit Committee | G11: Dashboard + email + workflow | H11: TBD | I11: → Senior credit | J11: One per transition; re-fire on worsening | K11: Red Alert
A12: ALERT-007 | B12: Overall score → Critical (80-100) | C12: Overall Score in Critical band (point-in-time); transition if previous score recorded | D12: Critical | E12: P1 | F12: Credit Head + Senior | G12: Email + workflow | H12: Immediate | I12: → Senior credit / committee | J12: One per transition; re-fire on worsening | K12: Critical Alert
A13: ALERT-008 | B13: Critical override TRUE | C13: Any CRITICAL-flagged indicator (EWS-014, EWS-027, EWS-034) hits the override trigger — Overall Score Engine → Critical Override | D13: Critical | E13: P1 | F13: Credit Head + Senior + Risk head | G13: Email + workflow | H13: Immediate | I13: Immediate senior review | J13: Never suppressed (always surfaced) | K13: Immediate Critical Alert
A16: B. RM / Credit Action Logic (by risk band)
A17: Status | B17: Trigger | C17: Responsible Role | D17: Required Action | E17: Timeline / SLA | F17: Required Documents | G17: Decision | H17: Escalation | I17: Closure Criteria
A18: Green / Normal | B18: Score 0-19, no override | C18: RM | D18: Standard monitoring; no special action. | E18: BAU cycle | F18: None extra | G18: Continue monitoring | H18: — | I18: N/A
A19: Yellow / Monitor | B19: Score 20-39 | C19: RM | D19: Log trend; RM commentary; review borrower conduct at next cycle. | E19: Next cycle (TBD) | F19: Account statement review; RM remarks | G19: RM notes cause & plan | H19: If unresolved → Credit | I19: Signals return to '0' bands / remarks accepted
A20: Amber / Watchlist | B20: Score 40-59 | C20: RM + Credit | D20: Enhanced monitoring; request updated financials; borrower discussion. | E20: 2-4 weeks (TBD) | F20: Updated financials; account review | G20: RM + Credit note cause & plan | H20: If unresolved → Credit Committee | I20: Condition improves to a lower band & remarks accepted
A21: Red / High | B21: Score 60-79 | C21: Credit Committee | D21: Credit review; obtain updated financials, stock statement, repayment plan; exposure review. | E21: 1-2 weeks (TBD) | F21: Updated financials; stock statement; repayment plan | G21: Credit decides monitoring / exit | H21: If worsening → Senior credit | I21: Condition cleared & Credit sign-off
A22: Red / Critical | B22: Score 80-100 OR critical override | C22: Senior Credit / Committee | D22: Senior credit review; exposure review; possible freeze / recovery / restructuring depending on trigger. | E22: Immediate | F22: Full credit note; legal / recovery inputs | G22: Committee decision | H22: Recovery / legal / restructuring path | I22: Formal resolution per policy
A24: C. Lifecycle states
A25: State | B25: Entry condition | C25: Owner | D25: Allowed next states | E25: Backward move?
A26: Generated | B26: Alert generated in section A | C26: System | D26: Assigned | E26: No
A27: Assigned | B27: Routed to RM / Credit | C27: System | D27: Under Review | E27: No
A28: Under Review | B28: Owner investigating | C28: RM / Credit | D28: Action Required / Resolved | E28: No
A29: Action Required | B29: Borrower action / docs needed | C29: RM / Credit | D29: Escalated / Resolved | E29: No
A30: Escalated | B30: SLA breach or severity up | C30: Credit / Senior | D30: Resolved / Action Required | E30: Yes (to Action Required)
A31: Resolved | B31: Condition cleared, pending closure check | C31: Credit | D31: Closed / Reopened | E31: No
A32: Closed | B32: Closure criteria met (see section E) | C32: Credit | D32: Reopened | E32: Yes (Reopened)
A33: Reopened | B33: Condition recurs / premature closure | C33: Credit | D33: Under Review | E33: Yes
A35: Critical Combination rule: certain indicator pairs escalate to CRITICAL when they co-occur, even if neither is individually critical — EWS-004+EWS-011 (payment defaults + stretched creditors), EWS-005+EWS-014 (non-core repayment + rising unsecured loans), EWS-009+EWS-012 (stretched debtors + rising provisions). A fired pair triggers the Critical Override immediately (see Overall Score Engine → Critical Combination Rules).

Sheet Recommendations
A1: Final Recommendation / Action & AI-Suggested Path
A2: How the Final Status maps to action, and how the tool ranks the drivers behind the score to suggest a remediation path.
A4: A. Action Matrix by Final Status
A5: Final Status | B5: What it means | C5: Recommended Action | D5: Owner | E5: Timeline
A6: Green | B6: Normal / low concern | C6: Standard monitoring; no action beyond routine review. | D6: RM | E6: Routine cycle
A7: Yellow | B7: Early deterioration | C7: Log trend; RM commentary; watch next cycle. | D7: RM | E7: Next cycle
A8: Amber | B8: Elevated concern | C8: Enhanced monitoring; request updated financials; tighten review frequency. | D8: RM + Credit | E8: 2–4 weeks
A9: Red | B9: High concern | C9: Escalate to credit committee; borrower engagement; corrective action plan. | D9: Credit Committee | E9: 1–2 weeks
A10: Critical | B10: Severe EWS | C10: Immediate intervention; site visit; classify / restructure / initiate recovery as warranted. | D10: Credit Head / Risk | E10: Immediate
A11: CRITICAL (Override) | B11: A critical event is present regardless of average | C11: Treat as Critical immediately; investigate the specific critical indicator(s) first; do not wait for the average to catch up. | D11: Credit Head / Risk | E11: Immediate
A13: B. How the AI suggests the recommended path
A14: 1. Take all applicable indicators that have valid data (the same set used for the Overall Score).
A15: 2. Rank them by Normalised Score (highest first); any CRITICAL-flagged indicator at its worst band is pulled to the top automatically.
A16: 3. Read the top contributors as the "drivers" of the score, and group them by Category (e.g., Account Conduct, Financial Performance, Compliance).
A17: 4. For each driver, pull the band-specific remark, remedial plan and owner from the Scoring Engine (Rules) sheet (matched on UID + Normalised).
A18: 5. Because every driver traces back to UID → Raw Score → threshold band → borrower input, each recommendation is fully auditable.
A20: C. Top score drivers for the Borrower Example (remarks/actions pulled live from the Rules sheet by UID + Normalised)
A21: Rank | B21: UID | C21: Indicator | D21: Category | E21: Normalised | F21: What it signals & likely drivers | G21: Remedial action plan (step-by-step) | H21: Primary owner | I21: raw (helper)
A22: 1 | B22: EWS-001 | C22: Utilization % (outstanding / sanctioned) | D22: Account Conduct | E22: 100 | F22: =IFERROR(INDEX('Scoring Engine (Rules)'!$O$5:$O$163,MATCH($B22&"|"&$I22,'Scoring Engine (Rules)'!$R$5:$R$163,0)),"") -> Severe / critical — utilisation above 95% for 30+ days; chronic over-reliance — possible inability to rotate WC, or diversion/ever-greening. | G22: =IFERROR(INDEX('Scoring Engine (Rules)'!$P$5:$P$163,MATCH($B22&"|"&$I22,'Scoring Engine (Rules)'!$R$5:$R$163,0)),"") -> 1) Restrict fresh drawals pending review. 2) Investigate diversion (routing gaps, ad-hoc pattern). 3) Full viability / limit-rationalisation review; escalate to Credit. | H22: =IFERROR(INDEX('Scoring Engine (Rules)'!$Q$5:$Q$163,MATCH($B22&"|"&$I22,'Scoring Engine (Rules)'!$R$5:$R$163,0)),"") -> Credit Head / Risk | I22: 30
A23: 2 | B23: EWS-026 | C23: Statutory overdues | D23: Compliance | E23: 100 | F23: =IFERROR(INDEX('Scoring Engine (Rules)'!$O$5:$O$163,MATCH($B23&"|"&$I23,'Scoring Engine (Rules)'!$R$5:$R$163,0)),"") -> Severe / critical — 3+ months overdue; severe — large statutory arrears ranking ahead of the bank, attachment risk. | G23: =IFERROR(INDEX('Scoring Engine (Rules)'!$P$5:$P$163,MATCH($B23&"|"&$I23,'Scoring Engine (Rules)'!$R$5:$R$163,0)),"") -> [CRITICAL] 1) Treat as serious stress — statutory dues rank ahead of the bank. 2) Verify no attachment/first-charge; liquidity/forensic review. 3) Corrective / recovery plan; escalate immediately. NOTE: CRITICAL indicator — statutory dues rank ahead of the bank; worst band fires the Critical Override → final status escalates to Critical. | H23: =IFERROR(INDEX('Scoring Engine (Rules)'!$Q$5:$Q$163,MATCH($B23&"|"&$I23,'Scoring Engine (Rules)'!$R$5:$R$163,0)),"") -> Credit Head / Risk (immediate) | I23: 35
A24: 3 | B24: EWS-041 | C24: DSCR | D24: Credit Risk | E24: 100 | F24: =IFERROR(INDEX('Scoring Engine (Rules)'!$O$5:$O$163,MATCH($B24&"|"&$I24,'Scoring Engine (Rules)'!$R$5:$R$163,0)),"") -> Severe / critical — DSCR below 1.25; thin-to-inadequate coverage, cash accruals may not comfortably cover debt service. | G24: =IFERROR(INDEX('Scoring Engine (Rules)'!$P$5:$P$163,MATCH($B24&"|"&$I24,'Scoring Engine (Rules)'!$R$5:$R$163,0)),"") -> 1) Reassess repayment capacity, refinancing risk and viability. 2) Corrective / restructuring assessment. 3) Escalate to Credit. | H24: =IFERROR(INDEX('Scoring Engine (Rules)'!$Q$5:$Q$163,MATCH($B24&"|"&$I24,'Scoring Engine (Rules)'!$R$5:$R$163,0)),"") -> Credit Head / Risk | I24: 40
A25: 4 | B25: EWS-042 | C25: Leverage Ratio | D25: Credit Risk | E25: 100 | F25: =IFERROR(INDEX('Scoring Engine (Rules)'!$O$5:$O$163,MATCH($B25&"|"&$I25,'Scoring Engine (Rules)'!$R$5:$R$163,0)),"") -> Severe / critical — leverage above 3.0; high/severe, thin net worth relative to debt and over-leverage risk. | G25: =IFERROR(INDEX('Scoring Engine (Rules)'!$P$5:$P$163,MATCH($B25&"|"&$I25,'Scoring Engine (Rules)'!$R$5:$R$163,0)),"") -> 1) Reassess leverage and net-worth adequacy; seek promoter infusion. 2) Corrective / viability review. 3) Escalate to Credit. | H25: =IFERROR(INDEX('Scoring Engine (Rules)'!$Q$5:$Q$163,MATCH($B25&"|"&$I25,'Scoring Engine (Rules)'!$R$5:$R$163,0)),"") -> Credit Head / Risk | I25: 40
A26: 5 | B26: EWS-012 | C26: Provisions/write-offs change % | D26: Financial Performance | E26: 75 | F26: =IFERROR(INDEX('Scoring Engine (Rules)'!$O$5:$O$163,MATCH($B26&"|"&$I26,'Scoring Engine (Rules)'!$R$5:$R$163,0)),"") -> High concern — provisions up >25–50%; material deterioration in asset quality. | G26: =IFERROR(INDEX('Scoring Engine (Rules)'!$P$5:$P$163,MATCH($B26&"|"&$I26,'Scoring Engine (Rules)'!$R$5:$R$163,0)),"") -> 1) Reassess viability given the losses. 2) Enhanced monitoring. 3) Escalate to Credit. | H26: =IFERROR(INDEX('Scoring Engine (Rules)'!$Q$5:$Q$163,MATCH($B26&"|"&$I26,'Scoring Engine (Rules)'!$R$5:$R$163,0)),"") -> Credit Committee / Zonal Credit | I26: 30
A27: 6 | B27: EWS-009 | C27: Debtor days vs normal | D27: Financial Performance | E27: 66.7 | F27: =IFERROR(INDEX('Scoring Engine (Rules)'!$O$5:$O$163,MATCH($B27&"|"&$I27,'Scoring Engine (Rules)'!$R$5:$R$163,0)),"") -> Elevated concern — debtor days +30–60; material tie-up of working capital in receivables. | G27: =IFERROR(INDEX('Scoring Engine (Rules)'!$P$5:$P$163,MATCH($B27&"|"&$I27,'Scoring Engine (Rules)'!$R$5:$R$163,0)),"") -> 1) Order a receivables audit. 2) Exclude >90-day receivables from DP. 3) Monitor monthly. | H27: =IFERROR(INDEX('Scoring Engine (Rules)'!$Q$5:$Q$163,MATCH($B27&"|"&$I27,'Scoring Engine (Rules)'!$R$5:$R$163,0)),"") -> Credit Committee / Zonal Credit | I27: 20
A28: 7 | B28: EWS-003 | C28: Monthly sales vs credit summation | D28: Account Conduct | E28: 57.1 | F28: =IFERROR(INDEX('Scoring Engine (Rules)'!$O$5:$O$163,MATCH($B28&"|"&$I28,'Scoring Engine (Rules)'!$R$5:$R$163,0)),"") -> Elevated concern — credits down 20–40%; material drop — genuine sales fall or turnover being diverted elsewhere. | G28: =IFERROR(INDEX('Scoring Engine (Rules)'!$P$5:$P$163,MATCH($B28&"|"&$I28,'Scoring Engine (Rules)'!$R$5:$R$163,0)),"") -> 1) Stipulate proportionate turnover routing through the bank. 2) Verify sales via GST returns. 3) Monitor monthly credits vs sales. | H28: =IFERROR(INDEX('Scoring Engine (Rules)'!$Q$5:$Q$163,MATCH($B28&"|"&$I28,'Scoring Engine (Rules)'!$R$5:$R$163,0)),"") -> RM + Credit Analyst | I28: 20
A29: 8 | B29: EWS-007 | C29: Sales turnover YoY/QoQ change % | D29: Financial Performance | E29: 57.1 | F29: =IFERROR(INDEX('Scoring Engine (Rules)'!$O$5:$O$163,MATCH($B29&"|"&$I29,'Scoring Engine (Rules)'!$R$5:$R$163,0)),"") -> Elevated concern — turnover down 20–40%; a genuine downturn or loss of key customers. | G29: =IFERROR(INDEX('Scoring Engine (Rules)'!$P$5:$P$163,MATCH($B29&"|"&$I29,'Scoring Engine (Rules)'!$R$5:$R$163,0)),"") -> 1) Reassess repayment capacity and viability with a sensitivity run. 2) Consider whether restructuring is needed. 3) Escalate to Credit. | H29: =IFERROR(INDEX('Scoring Engine (Rules)'!$Q$5:$Q$163,MATCH($B29&"|"&$I29,'Scoring Engine (Rules)'!$R$5:$R$163,0)),"") -> RM + Credit Analyst | I29: 20
